[
 {
  "organismo_nombre":"Fondo de Solidaridad e Inversión Social (FOSIS)",
  "base":"Contrata",
  "sexo":"desconocido",
  "Enero_2018":0,
  "Febrero_2018":0,
  "Marzo_2018":0,
  "Abril_2018":0,
  "Mayo_2018":0,
  "Junio_2018":0,
  "Julio_2018":0,
  "Agosto_2018":7,
  "Septiembre_2018":7,
  "Octubre_2018":6,
  "Noviembre_2018":6,
  "Diciembre_2018":6,
  "Enero_2019":7,
  "Febrero_2019":7,
  "Marzo_2019":8,
  "Abril_2019":7,
  "Mayo_2019":6,
  "Junio_2019":6,
  "Julio_2019":6,
  "Agosto_2019":6,
  "Septiembre_2019":7,
  "Octubre_2019":7,
  "Noviembre_2019":7,
  "Diciembre_2019":7,
  "Enero_2020":7,
  "Febrero_2020":6,
  "Marzo_2020":7,
  "Abril_2020":7,
  "Mayo_2020":7,
  "Junio_2020":7,
  "Julio_2020":7,
  "Agosto_2020":7,
  "Septiembre_2020":7,
  "Octubre_2020":7,
  "Noviembre_2020":7,
  "Diciembre_2020":7,
  "Enero_2021":7,
  "Febrero_2021":7,
  "Marzo_2021":7,
  "Abril_2021":7,
  "Mayo_2021":7,
  "Junio_2021":7,
  "Julio_2021":6,
  "Agosto_2021":6,
  "Septiembre_2021":6,
  "Octubre_2021":6,
  "Noviembre_2021":6,
  "Diciembre_2021":6,
  "Enero_2022":6,
  "Febrero_2022":5,
  "Marzo_2022":6,
  "Abril_2022":5,
  "Mayo_2022":5,
  "Junio_2022":5,
  "Julio_2022":5,
  "Agosto_2022":5,
  "Septiembre_2022":5,
  "Octubre_2022":5,
  "Noviembre_2022":5,
  "Diciembre_2022":5,
  "Enero_2023":5,
  "Febrero_2023":5,
  "Marzo_2023":5,
  "Abril_2023":5,
  "Mayo_2023":5,
  "Junio_2023":5,
  "Julio_2023":5,
  "Agosto_2023":5,
  "Septiembre_2023":5,
  "Octubre_2023":5,
  "Noviembre_2023":6,
  "Diciembre_2023":6,
  "Enero_2024":6,
  "Febrero_2024":6,
  "Marzo_2024":6,
  "Abril_2024":5,
  "Mayo_2024":5,
  "Junio_2024":4,
  "Julio_2024":4,
  "Agosto_2024":4,
  "Septiembre_2024":4,
  "Octubre_2024":4,
  "Noviembre_2024":5,
  "Diciembre_2024":5,
  "Enero_2025":5,
  "Febrero_2025":5,
  "Marzo_2025":5,
  "Abril_2025":5,
  "Mayo_2025":5,
  "Junio_2025":5,
  "Julio_2025":5,
  "Agosto_2025":6,
  "Septiembre_2025":6,
  "Octubre_2025":6,
  "Noviembre_2025":0,
  "Diciembre_2025":0
 },
 {
  "organismo_nombre":"Fondo de Solidaridad e Inversión Social (FOSIS)",
  "base":"Contrata",
  "sexo":"hombre",
  "Enero_2018":0,
  "Febrero_2018":0,
  "Marzo_2018":0,
  "Abril_2018":0,
  "Mayo_2018":0,
  "Junio_2018":0,
  "Julio_2018":0,
  "Agosto_2018":278,
  "Septiembre_2018":278,
  "Octubre_2018":255,
  "Noviembre_2018":268,
  "Diciembre_2018":271,
  "Enero_2019":270,
  "Febrero_2019":279,
  "Marzo_2019":281,
  "Abril_2019":283,
  "Mayo_2019":287,
  "Junio_2019":292,
  "Julio_2019":289,
  "Agosto_2019":292,
  "Septiembre_2019":297,
  "Octubre_2019":298,
  "Noviembre_2019":302,
  "Diciembre_2019":301,
  "Enero_2020":305,
  "Febrero_2020":295,
  "Marzo_2020":307,
  "Abril_2020":300,
  "Mayo_2020":297,
  "Junio_2020":297,
  "Julio_2020":296,
  "Agosto_2020":296,
  "Septiembre_2020":297,
  "Octubre_2020":297,
  "Noviembre_2020":295,
  "Diciembre_2020":295,
  "Enero_2021":297,
  "Febrero_2021":294,
  "Marzo_2021":296,
  "Abril_2021":298,
  "Mayo_2021":298,
  "Junio_2021":299,
  "Julio_2021":292,
  "Agosto_2021":292,
  "Septiembre_2021":293,
  "Octubre_2021":336,
  "Noviembre_2021":246,
  "Diciembre_2021":289,
  "Enero_2022":295,
  "Febrero_2022":296,
  "Marzo_2022":296,
  "Abril_2022":293,
  "Mayo_2022":289,
  "Junio_2022":291,
  "Julio_2022":298,
  "Agosto_2022":298,
  "Septiembre_2022":298,
  "Octubre_2022":295,
  "Noviembre_2022":296,
  "Diciembre_2022":299,
  "Enero_2023":304,
  "Febrero_2023":304,
  "Marzo_2023":304,
  "Abril_2023":303,
  "Mayo_2023":302,
  "Junio_2023":302,
  "Julio_2023":306,
  "Agosto_2023":285,
  "Septiembre_2023":303,
  "Octubre_2023":298,
  "Noviembre_2023":316,
  "Diciembre_2023":317,
  "Enero_2024":319,
  "Febrero_2024":317,
  "Marzo_2024":317,
  "Abril_2024":315,
  "Mayo_2024":316,
  "Junio_2024":317,
  "Julio_2024":317,
  "Agosto_2024":320,
  "Septiembre_2024":324,
  "Octubre_2024":326,
  "Noviembre_2024":340,
  "Diciembre_2024":344,
  "Enero_2025":344,
  "Febrero_2025":343,
  "Marzo_2025":343,
  "Abril_2025":341,
  "Mayo_2025":354,
  "Junio_2025":328,
  "Julio_2025":342,
  "Agosto_2025":344,
  "Septiembre_2025":348,
  "Octubre_2025":350,
  "Noviembre_2025":0,
  "Diciembre_2025":0
 },
 {
  "organismo_nombre":"Fondo de Solidaridad e Inversión Social (FOSIS)",
  "base":"Contrata",
  "sexo":"male",
  "Enero_2018":0,
  "Febrero_2018":0,
  "Marzo_2018":0,
  "Abril_2018":0,
  "Mayo_2018":0,
  "Junio_2018":0,
  "Julio_2018":0,
  "Agosto_2018":0,
  "Septiembre_2018":0,
  "Octubre_2018":0,
  "Noviembre_2018":0,
  "Diciembre_2018":0,
  "Enero_2019":0,
  "Febrero_2019":0,
  "Marzo_2019":0,
  "Abril_2019":0,
  "Mayo_2019":0,
  "Junio_2019":0,
  "Julio_2019":0,
  "Agosto_2019":0,
  "Septiembre_2019":0,
  "Octubre_2019":0,
  "Noviembre_2019":0,
  "Diciembre_2019":0,
  "Enero_2020":0,
  "Febrero_2020":0,
  "Marzo_2020":0,
  "Abril_2020":0,
  "Mayo_2020":0,
  "Junio_2020":0,
  "Julio_2020":0,
  "Agosto_2020":0,
  "Septiembre_2020":0,
  "Octubre_2020":0,
  "Noviembre_2020":0,
  "Diciembre_2020":0,
  "Enero_2021":0,
  "Febrero_2021":0,
  "Marzo_2021":0,
  "Abril_2021":0,
  "Mayo_2021":0,
  "Junio_2021":0,
  "Julio_2021":0,
  "Agosto_2021":0,
  "Septiembre_2021":0,
  "Octubre_2021":0,
  "Noviembre_2021":0,
  "Diciembre_2021":0,
  "Enero_2022":0,
  "Febrero_2022":0,
  "Marzo_2022":0,
  "Abril_2022":0,
  "Mayo_2022":0,
  "Junio_2022":0,
  "Julio_2022":0,
  "Agosto_2022":0,
  "Septiembre_2022":0,
  "Octubre_2022":0,
  "Noviembre_2022":0,
  "Diciembre_2022":0,
  "Enero_2023":0,
  "Febrero_2023":0,
  "Marzo_2023":0,
  "Abril_2023":0,
  "Mayo_2023":0,
  "Junio_2023":0,
  "Julio_2023":0,
  "Agosto_2023":0,
  "Septiembre_2023":0,
  "Octubre_2023":0,
  "Noviembre_2023":0,
  "Diciembre_2023":0,
  "Enero_2024":0,
  "Febrero_2024":0,
  "Marzo_2024":0,
  "Abril_2024":0,
  "Mayo_2024":0,
  "Junio_2024":0,
  "Julio_2024":0,
  "Agosto_2024":0,
  "Septiembre_2024":0,
  "Octubre_2024":0,
  "Noviembre_2024":0,
  "Diciembre_2024":0,
  "Enero_2025":0,
  "Febrero_2025":0,
  "Marzo_2025":0,
  "Abril_2025":0,
  "Mayo_2025":0,
  "Junio_2025":0,
  "Julio_2025":0,
  "Agosto_2025":0,
  "Septiembre_2025":1,
  "Octubre_2025":2,
  "Noviembre_2025":0,
  "Diciembre_2025":0
 },
 {
  "organismo_nombre":"Fondo de Solidaridad e Inversión Social (FOSIS)",
  "base":"Contrata",
  "sexo":"mujer",
  "Enero_2018":0,
  "Febrero_2018":0,
  "Marzo_2018":0,
  "Abril_2018":0,
  "Mayo_2018":0,
  "Junio_2018":0,
  "Julio_2018":0,
  "Agosto_2018":409,
  "Septiembre_2018":417,
  "Octubre_2018":395,
  "Noviembre_2018":413,
  "Diciembre_2018":419,
  "Enero_2019":425,
  "Febrero_2019":439,
  "Marzo_2019":443,
  "Abril_2019":443,
  "Mayo_2019":444,
  "Junio_2019":446,
  "Julio_2019":449,
  "Agosto_2019":447,
  "Septiembre_2019":453,
  "Octubre_2019":449,
  "Noviembre_2019":451,
  "Diciembre_2019":446,
  "Enero_2020":457,
  "Febrero_2020":443,
  "Marzo_2020":462,
  "Abril_2020":455,
  "Mayo_2020":453,
  "Junio_2020":451,
  "Julio_2020":450,
  "Agosto_2020":448,
  "Septiembre_2020":449,
  "Octubre_2020":449,
  "Noviembre_2020":446,
  "Diciembre_2020":445,
  "Enero_2021":467,
  "Febrero_2021":469,
  "Marzo_2021":472,
  "Abril_2021":471,
  "Mayo_2021":471,
  "Junio_2021":469,
  "Julio_2021":465,
  "Agosto_2021":464,
  "Septiembre_2021":465,
  "Octubre_2021":547,
  "Noviembre_2021":376,
  "Diciembre_2021":462,
  "Enero_2022":479,
  "Febrero_2022":479,
  "Marzo_2022":485,
  "Abril_2022":478,
  "Mayo_2022":477,
  "Junio_2022":480,
  "Julio_2022":493,
  "Agosto_2022":493,
  "Septiembre_2022":494,
  "Octubre_2022":487,
  "Noviembre_2022":489,
  "Diciembre_2022":488,
  "Enero_2023":497,
  "Febrero_2023":497,
  "Marzo_2023":497,
  "Abril_2023":490,
  "Mayo_2023":483,
  "Junio_2023":486,
  "Julio_2023":483,
  "Agosto_2023":434,
  "Septiembre_2023":483,
  "Octubre_2023":482,
  "Noviembre_2023":527,
  "Diciembre_2023":525,
  "Enero_2024":531,
  "Febrero_2024":531,
  "Marzo_2024":531,
  "Abril_2024":530,
  "Mayo_2024":530,
  "Junio_2024":529,
  "Julio_2024":527,
  "Agosto_2024":530,
  "Septiembre_2024":528,
  "Octubre_2024":530,
  "Noviembre_2024":557,
  "Diciembre_2024":561,
  "Enero_2025":562,
  "Febrero_2025":556,
  "Marzo_2025":554,
  "Abril_2025":550,
  "Mayo_2025":567,
  "Junio_2025":538,
  "Julio_2025":555,
  "Agosto_2025":553,
  "Septiembre_2025":556,
  "Octubre_2025":557,
  "Noviembre_2025":0,
  "Diciembre_2025":0
 },
 {
  "organismo_nombre":"Fondo de Solidaridad e Inversión Social (FOSIS)",
  "base":"Honorarios",
  "sexo":"desconocido",
  "Enero_2018":0,
  "Febrero_2018":0,
  "Marzo_2018":0,
  "Abril_2018":0,
  "Mayo_2018":0,
  "Junio_2018":0,
  "Julio_2018":0,
  "Agosto_2018":8,
  "Septiembre_2018":8,
  "Octubre_2018":7,
  "Noviembre_2018":7,
  "Diciembre_2018":8,
  "Enero_2019":5,
  "Febrero_2019":6,
  "Marzo_2019":5,
  "Abril_2019":5,
  "Mayo_2019":4,
  "Junio_2019":4,
  "Julio_2019":5,
  "Agosto_2019":5,
  "Septiembre_2019":5,
  "Octubre_2019":5,
  "Noviembre_2019":5,
  "Diciembre_2019":5,
  "Enero_2020":5,
  "Febrero_2020":5,
  "Marzo_2020":5,
  "Abril_2020":5,
  "Mayo_2020":5,
  "Junio_2020":5,
  "Julio_2020":5,
  "Agosto_2020":5,
  "Septiembre_2020":5,
  "Octubre_2020":5,
  "Noviembre_2020":5,
  "Diciembre_2020":4,
  "Enero_2021":4,
  "Febrero_2021":4,
  "Marzo_2021":4,
  "Abril_2021":4,
  "Mayo_2021":4,
  "Junio_2021":4,
  "Julio_2021":5,
  "Agosto_2021":6,
  "Septiembre_2021":6,
  "Octubre_2021":6,
  "Noviembre_2021":7,
  "Diciembre_2021":8,
  "Enero_2022":6,
  "Febrero_2022":7,
  "Marzo_2022":8,
  "Abril_2022":7,
  "Mayo_2022":7,
  "Junio_2022":8,
  "Julio_2022":7,
  "Agosto_2022":6,
  "Septiembre_2022":6,
  "Octubre_2022":6,
  "Noviembre_2022":6,
  "Diciembre_2022":6,
  "Enero_2023":6,
  "Febrero_2023":6,
  "Marzo_2023":5,
  "Abril_2023":5,
  "Mayo_2023":5,
  "Junio_2023":5,
  "Julio_2023":5,
  "Agosto_2023":5,
  "Septiembre_2023":6,
  "Octubre_2023":6,
  "Noviembre_2023":5,
  "Diciembre_2023":5,
  "Enero_2024":4,
  "Febrero_2024":4,
  "Marzo_2024":4,
  "Abril_2024":4,
  "Mayo_2024":4,
  "Junio_2024":4,
  "Julio_2024":4,
  "Agosto_2024":4,
  "Septiembre_2024":4,
  "Octubre_2024":4,
  "Noviembre_2024":3,
  "Diciembre_2024":3,
  "Enero_2025":2,
  "Febrero_2025":2,
  "Marzo_2025":2,
  "Abril_2025":2,
  "Mayo_2025":2,
  "Junio_2025":2,
  "Julio_2025":2,
  "Agosto_2025":2,
  "Septiembre_2025":2,
  "Octubre_2025":2,
  "Noviembre_2025":0,
  "Diciembre_2025":0
 },
 {
  "organismo_nombre":"Fondo de Solidaridad e Inversión Social (FOSIS)",
  "base":"Honorarios",
  "sexo":"female",
  "Enero_2018":0,
  "Febrero_2018":0,
  "Marzo_2018":0,
  "Abril_2018":0,
  "Mayo_2018":0,
  "Junio_2018":0,
  "Julio_2018":0,
  "Agosto_2018":0,
  "Septiembre_2018":0,
  "Octubre_2018":0,
  "Noviembre_2018":0,
  "Diciembre_2018":0,
  "Enero_2019":0,
  "Febrero_2019":0,
  "Marzo_2019":0,
  "Abril_2019":0,
  "Mayo_2019":0,
  "Junio_2019":0,
  "Julio_2019":0,
  "Agosto_2019":0,
  "Septiembre_2019":0,
  "Octubre_2019":0,
  "Noviembre_2019":0,
  "Diciembre_2019":0,
  "Enero_2020":0,
  "Febrero_2020":0,
  "Marzo_2020":0,
  "Abril_2020":0,
  "Mayo_2020":0,
  "Junio_2020":0,
  "Julio_2020":0,
  "Agosto_2020":0,
  "Septiembre_2020":0,
  "Octubre_2020":0,
  "Noviembre_2020":0,
  "Diciembre_2020":0,
  "Enero_2021":0,
  "Febrero_2021":0,
  "Marzo_2021":0,
  "Abril_2021":0,
  "Mayo_2021":0,
  "Junio_2021":0,
  "Julio_2021":0,
  "Agosto_2021":0,
  "Septiembre_2021":0,
  "Octubre_2021":0,
  "Noviembre_2021":0,
  "Diciembre_2021":0,
  "Enero_2022":0,
  "Febrero_2022":0,
  "Marzo_2022":0,
  "Abril_2022":0,
  "Mayo_2022":0,
  "Junio_2022":0,
  "Julio_2022":0,
  "Agosto_2022":0,
  "Septiembre_2022":0,
  "Octubre_2022":0,
  "Noviembre_2022":0,
  "Diciembre_2022":0,
  "Enero_2023":0,
  "Febrero_2023":0,
  "Marzo_2023":0,
  "Abril_2023":0,
  "Mayo_2023":0,
  "Junio_2023":0,
  "Julio_2023":0,
  "Agosto_2023":0,
  "Septiembre_2023":0,
  "Octubre_2023":0,
  "Noviembre_2023":0,
  "Diciembre_2023":0,
  "Enero_2024":0,
  "Febrero_2024":0,
  "Marzo_2024":0,
  "Abril_2024":0,
  "Mayo_2024":0,
  "Junio_2024":0,
  "Julio_2024":0,
  "Agosto_2024":0,
  "Septiembre_2024":0,
  "Octubre_2024":0,
  "Noviembre_2024":0,
  "Diciembre_2024":0,
  "Enero_2025":0,
  "Febrero_2025":0,
  "Marzo_2025":0,
  "Abril_2025":0,
  "Mayo_2025":0,
  "Junio_2025":0,
  "Julio_2025":0,
  "Agosto_2025":2,
  "Septiembre_2025":6,
  "Octubre_2025":6,
  "Noviembre_2025":0,
  "Diciembre_2025":0
 },
 {
  "organismo_nombre":"Fondo de Solidaridad e Inversión Social (FOSIS)",
  "base":"Honorarios",
  "sexo":"hombre",
  "Enero_2018":0,
  "Febrero_2018":0,
  "Marzo_2018":0,
  "Abril_2018":0,
  "Mayo_2018":0,
  "Junio_2018":0,
  "Julio_2018":0,
  "Agosto_2018":188,
  "Septiembre_2018":179,
  "Octubre_2018":186,
  "Noviembre_2018":200,
  "Diciembre_2018":204,
  "Enero_2019":157,
  "Febrero_2019":170,
  "Marzo_2019":173,
  "Abril_2019":180,
  "Mayo_2019":169,
  "Junio_2019":180,
  "Julio_2019":182,
  "Agosto_2019":178,
  "Septiembre_2019":190,
  "Octubre_2019":202,
  "Noviembre_2019":199,
  "Diciembre_2019":205,
  "Enero_2020":179,
  "Febrero_2020":180,
  "Marzo_2020":172,
  "Abril_2020":166,
  "Mayo_2020":171,
  "Junio_2020":178,
  "Julio_2020":175,
  "Agosto_2020":176,
  "Septiembre_2020":184,
  "Octubre_2020":196,
  "Noviembre_2020":196,
  "Diciembre_2020":192,
  "Enero_2021":154,
  "Febrero_2021":163,
  "Marzo_2021":171,
  "Abril_2021":171,
  "Mayo_2021":175,
  "Junio_2021":177,
  "Julio_2021":187,
  "Agosto_2021":171,
  "Septiembre_2021":181,
  "Octubre_2021":175,
  "Noviembre_2021":188,
  "Diciembre_2021":191,
  "Enero_2022":147,
  "Febrero_2022":146,
  "Marzo_2022":150,
  "Abril_2022":151,
  "Mayo_2022":154,
  "Junio_2022":150,
  "Julio_2022":145,
  "Agosto_2022":144,
  "Septiembre_2022":147,
  "Octubre_2022":151,
  "Noviembre_2022":147,
  "Diciembre_2022":147,
  "Enero_2023":133,
  "Febrero_2023":137,
  "Marzo_2023":137,
  "Abril_2023":135,
  "Mayo_2023":137,
  "Junio_2023":130,
  "Julio_2023":127,
  "Agosto_2023":125,
  "Septiembre_2023":127,
  "Octubre_2023":125,
  "Noviembre_2023":108,
  "Diciembre_2023":106,
  "Enero_2024":101,
  "Febrero_2024":104,
  "Marzo_2024":107,
  "Abril_2024":106,
  "Mayo_2024":105,
  "Junio_2024":108,
  "Julio_2024":108,
  "Agosto_2024":111,
  "Septiembre_2024":119,
  "Octubre_2024":130,
  "Noviembre_2024":123,
  "Diciembre_2024":122,
  "Enero_2025":108,
  "Febrero_2025":98,
  "Marzo_2025":97,
  "Abril_2025":98,
  "Mayo_2025":95,
  "Junio_2025":93,
  "Julio_2025":94,
  "Agosto_2025":95,
  "Septiembre_2025":99,
  "Octubre_2025":97,
  "Noviembre_2025":0,
  "Diciembre_2025":0
 },
 {
  "organismo_nombre":"Fondo de Solidaridad e Inversión Social (FOSIS)",
  "base":"Honorarios",
  "sexo":"male",
  "Enero_2018":0,
  "Febrero_2018":0,
  "Marzo_2018":0,
  "Abril_2018":0,
  "Mayo_2018":0,
  "Junio_2018":0,
  "Julio_2018":0,
  "Agosto_2018":0,
  "Septiembre_2018":0,
  "Octubre_2018":0,
  "Noviembre_2018":0,
  "Diciembre_2018":0,
  "Enero_2019":0,
  "Febrero_2019":0,
  "Marzo_2019":0,
  "Abril_2019":0,
  "Mayo_2019":0,
  "Junio_2019":0,
  "Julio_2019":0,
  "Agosto_2019":0,
  "Septiembre_2019":0,
  "Octubre_2019":0,
  "Noviembre_2019":0,
  "Diciembre_2019":0,
  "Enero_2020":0,
  "Febrero_2020":0,
  "Marzo_2020":0,
  "Abril_2020":0,
  "Mayo_2020":0,
  "Junio_2020":0,
  "Julio_2020":0,
  "Agosto_2020":0,
  "Septiembre_2020":0,
  "Octubre_2020":0,
  "Noviembre_2020":0,
  "Diciembre_2020":0,
  "Enero_2021":0,
  "Febrero_2021":0,
  "Marzo_2021":0,
  "Abril_2021":0,
  "Mayo_2021":0,
  "Junio_2021":0,
  "Julio_2021":0,
  "Agosto_2021":0,
  "Septiembre_2021":0,
  "Octubre_2021":0,
  "Noviembre_2021":0,
  "Diciembre_2021":0,
  "Enero_2022":0,
  "Febrero_2022":0,
  "Marzo_2022":0,
  "Abril_2022":0,
  "Mayo_2022":0,
  "Junio_2022":0,
  "Julio_2022":0,
  "Agosto_2022":0,
  "Septiembre_2022":0,
  "Octubre_2022":0,
  "Noviembre_2022":0,
  "Diciembre_2022":0,
  "Enero_2023":0,
  "Febrero_2023":0,
  "Marzo_2023":0,
  "Abril_2023":0,
  "Mayo_2023":0,
  "Junio_2023":0,
  "Julio_2023":0,
  "Agosto_2023":0,
  "Septiembre_2023":0,
  "Octubre_2023":0,
  "Noviembre_2023":0,
  "Diciembre_2023":0,
  "Enero_2024":0,
  "Febrero_2024":0,
  "Marzo_2024":0,
  "Abril_2024":0,
  "Mayo_2024":0,
  "Junio_2024":0,
  "Julio_2024":0,
  "Agosto_2024":0,
  "Septiembre_2024":0,
  "Octubre_2024":0,
  "Noviembre_2024":0,
  "Diciembre_2024":0,
  "Enero_2025":0,
  "Febrero_2025":0,
  "Marzo_2025":0,
  "Abril_2025":0,
  "Mayo_2025":0,
  "Junio_2025":0,
  "Julio_2025":0,
  "Agosto_2025":3,
  "Septiembre_2025":6,
  "Octubre_2025":6,
  "Noviembre_2025":0,
  "Diciembre_2025":0
 },
 {
  "organismo_nombre":"Fondo de Solidaridad e Inversión Social (FOSIS)",
  "base":"Honorarios",
  "sexo":"mujer",
  "Enero_2018":0,
  "Febrero_2018":0,
  "Marzo_2018":0,
  "Abril_2018":0,
  "Mayo_2018":0,
  "Junio_2018":0,
  "Julio_2018":0,
  "Agosto_2018":283,
  "Septiembre_2018":269,
  "Octubre_2018":275,
  "Noviembre_2018":293,
  "Diciembre_2018":299,
  "Enero_2019":219,
  "Febrero_2019":245,
  "Marzo_2019":262,
  "Abril_2019":267,
  "Mayo_2019":268,
  "Junio_2019":277,
  "Julio_2019":283,
  "Agosto_2019":291,
  "Septiembre_2019":299,
  "Octubre_2019":304,
  "Noviembre_2019":305,
  "Diciembre_2019":307,
  "Enero_2020":267,
  "Febrero_2020":269,
  "Marzo_2020":261,
  "Abril_2020":251,
  "Mayo_2020":260,
  "Junio_2020":260,
  "Julio_2020":265,
  "Agosto_2020":267,
  "Septiembre_2020":281,
  "Octubre_2020":295,
  "Noviembre_2020":295,
  "Diciembre_2020":288,
  "Enero_2021":210,
  "Febrero_2021":216,
  "Marzo_2021":227,
  "Abril_2021":229,
  "Mayo_2021":238,
  "Junio_2021":241,
  "Julio_2021":257,
  "Agosto_2021":247,
  "Septiembre_2021":253,
  "Octubre_2021":246,
  "Noviembre_2021":259,
  "Diciembre_2021":268,
  "Enero_2022":206,
  "Febrero_2022":207,
  "Marzo_2022":207,
  "Abril_2022":208,
  "Mayo_2022":197,
  "Junio_2022":188,
  "Julio_2022":181,
  "Agosto_2022":185,
  "Septiembre_2022":185,
  "Octubre_2022":187,
  "Noviembre_2022":188,
  "Diciembre_2022":190,
  "Enero_2023":176,
  "Febrero_2023":182,
  "Marzo_2023":178,
  "Abril_2023":178,
  "Mayo_2023":180,
  "Junio_2023":180,
  "Julio_2023":178,
  "Agosto_2023":175,
  "Septiembre_2023":174,
  "Octubre_2023":175,
  "Noviembre_2023":129,
  "Diciembre_2023":128,
  "Enero_2024":115,
  "Febrero_2024":118,
  "Marzo_2024":118,
  "Abril_2024":116,
  "Mayo_2024":116,
  "Junio_2024":117,
  "Julio_2024":127,
  "Agosto_2024":128,
  "Septiembre_2024":129,
  "Octubre_2024":134,
  "Noviembre_2024":112,
  "Diciembre_2024":117,
  "Enero_2025":102,
  "Febrero_2025":93,
  "Marzo_2025":99,
  "Abril_2025":102,
  "Mayo_2025":103,
  "Junio_2025":96,
  "Julio_2025":93,
  "Agosto_2025":91,
  "Septiembre_2025":90,
  "Octubre_2025":92,
  "Noviembre_2025":0,
  "Diciembre_2025":0
 },
 {
  "organismo_nombre":"Fondo de Solidaridad e Inversión Social (FOSIS)",
  "base":"Planta",
  "sexo":"hombre",
  "Enero_2018":0,
  "Febrero_2018":0,
  "Marzo_2018":0,
  "Abril_2018":0,
  "Mayo_2018":0,
  "Junio_2018":0,
  "Julio_2018":0,
  "Agosto_2018":20,
  "Septiembre_2018":10,
  "Octubre_2018":15,
  "Noviembre_2018":14,
  "Diciembre_2018":14,
  "Enero_2019":15,
  "Febrero_2019":15,
  "Marzo_2019":12,
  "Abril_2019":14,
  "Mayo_2019":13,
  "Junio_2019":13,
  "Julio_2019":13,
  "Agosto_2019":13,
  "Septiembre_2019":13,
  "Octubre_2019":14,
  "Noviembre_2019":14,
  "Diciembre_2019":14,
  "Enero_2020":14,
  "Febrero_2020":14,
  "Marzo_2020":14,
  "Abril_2020":14,
  "Mayo_2020":14,
  "Junio_2020":14,
  "Julio_2020":14,
  "Agosto_2020":14,
  "Septiembre_2020":15,
  "Octubre_2020":15,
  "Noviembre_2020":15,
  "Diciembre_2020":15,
  "Enero_2021":14,
  "Febrero_2021":14,
  "Marzo_2021":14,
  "Abril_2021":14,
  "Mayo_2021":14,
  "Junio_2021":14,
  "Julio_2021":14,
  "Agosto_2021":13,
  "Septiembre_2021":13,
  "Octubre_2021":13,
  "Noviembre_2021":12,
  "Diciembre_2021":12,
  "Enero_2022":12,
  "Febrero_2022":13,
  "Marzo_2022":13,
  "Abril_2022":12,
  "Mayo_2022":12,
  "Junio_2022":12,
  "Julio_2022":15,
  "Agosto_2022":6,
  "Septiembre_2022":10,
  "Octubre_2022":10,
  "Noviembre_2022":11,
  "Diciembre_2022":10,
  "Enero_2023":11,
  "Febrero_2023":11,
  "Marzo_2023":11,
  "Abril_2023":12,
  "Mayo_2023":13,
  "Junio_2023":13,
  "Julio_2023":13,
  "Agosto_2023":12,
  "Septiembre_2023":14,
  "Octubre_2023":14,
  "Noviembre_2023":13,
  "Diciembre_2023":13,
  "Enero_2024":13,
  "Febrero_2024":13,
  "Marzo_2024":13,
  "Abril_2024":13,
  "Mayo_2024":14,
  "Junio_2024":7,
  "Julio_2024":14,
  "Agosto_2024":14,
  "Septiembre_2024":14,
  "Octubre_2024":15,
  "Noviembre_2024":15,
  "Diciembre_2024":15,
  "Enero_2025":15,
  "Febrero_2025":15,
  "Marzo_2025":15,
  "Abril_2025":15,
  "Mayo_2025":14,
  "Junio_2025":14,
  "Julio_2025":14,
  "Agosto_2025":14,
  "Septiembre_2025":14,
  "Octubre_2025":14,
  "Noviembre_2025":0,
  "Diciembre_2025":0
 },
 {
  "organismo_nombre":"Fondo de Solidaridad e Inversión Social (FOSIS)",
  "base":"Planta",
  "sexo":"mujer",
  "Enero_2018":0,
  "Febrero_2018":0,
  "Marzo_2018":0,
  "Abril_2018":0,
  "Mayo_2018":0,
  "Junio_2018":0,
  "Julio_2018":0,
  "Agosto_2018":3,
  "Septiembre_2018":1,
  "Octubre_2018":3,
  "Noviembre_2018":3,
  "Diciembre_2018":3,
  "Enero_2019":3,
  "Febrero_2019":4,
  "Marzo_2019":2,
  "Abril_2019":3,
  "Mayo_2019":3,
  "Junio_2019":3,
  "Julio_2019":3,
  "Agosto_2019":4,
  "Septiembre_2019":4,
  "Octubre_2019":4,
  "Noviembre_2019":4,
  "Diciembre_2019":4,
  "Enero_2020":4,
  "Febrero_2020":4,
  "Marzo_2020":4,
  "Abril_2020":4,
  "Mayo_2020":4,
  "Junio_2020":4,
  "Julio_2020":4,
  "Agosto_2020":4,
  "Septiembre_2020":4,
  "Octubre_2020":3,
  "Noviembre_2020":3,
  "Diciembre_2020":3,
  "Enero_2021":3,
  "Febrero_2021":3,
  "Marzo_2021":3,
  "Abril_2021":3,
  "Mayo_2021":4,
  "Junio_2021":4,
  "Julio_2021":4,
  "Agosto_2021":4,
  "Septiembre_2021":4,
  "Octubre_2021":4,
  "Noviembre_2021":4,
  "Diciembre_2021":4,
  "Enero_2022":4,
  "Febrero_2022":3,
  "Marzo_2022":4,
  "Abril_2022":3,
  "Mayo_2022":3,
  "Junio_2022":3,
  "Julio_2022":3,
  "Agosto_2022":1,
  "Septiembre_2022":1,
  "Octubre_2022":1,
  "Noviembre_2022":1,
  "Diciembre_2022":1,
  "Enero_2023":1,
  "Febrero_2023":1,
  "Marzo_2023":1,
  "Abril_2023":1,
  "Mayo_2023":1,
  "Junio_2023":1,
  "Julio_2023":1,
  "Agosto_2023":1,
  "Septiembre_2023":1,
  "Octubre_2023":1,
  "Noviembre_2023":1,
  "Diciembre_2023":1,
  "Enero_2024":1,
  "Febrero_2024":1,
  "Marzo_2024":1,
  "Abril_2024":1,
  "Mayo_2024":1,
  "Junio_2024":1,
  "Julio_2024":1,
  "Agosto_2024":1,
  "Septiembre_2024":1,
  "Octubre_2024":1,
  "Noviembre_2024":1,
  "Diciembre_2024":1,
  "Enero_2025":1,
  "Febrero_2025":1,
  "Marzo_2025":1,
  "Abril_2025":1,
  "Mayo_2025":1,
  "Junio_2025":1,
  "Julio_2025":1,
  "Agosto_2025":1,
  "Septiembre_2025":1,
  "Octubre_2025":1,
  "Noviembre_2025":0,
  "Diciembre_2025":0
 }
]