[
 {
  "organismo_nombre":"Municipalidad de Lo Prado",
  "base":"Cod. Trabajo",
  "sexo":"desconocido",
  "Enero_2018":0,
  "Febrero_2018":0,
  "Marzo_2018":0,
  "Abril_2018":0,
  "Mayo_2018":0,
  "Junio_2018":0,
  "Julio_2018":0,
  "Agosto_2018":0,
  "Septiembre_2018":0,
  "Octubre_2018":0,
  "Noviembre_2018":0,
  "Diciembre_2018":0,
  "Enero_2019":0,
  "Febrero_2019":0,
  "Marzo_2019":0,
  "Abril_2019":0,
  "Mayo_2019":0,
  "Junio_2019":0,
  "Julio_2019":0,
  "Agosto_2019":0,
  "Septiembre_2019":0,
  "Octubre_2019":0,
  "Noviembre_2019":0,
  "Diciembre_2019":0,
  "Enero_2020":0,
  "Febrero_2020":0,
  "Marzo_2020":1,
  "Abril_2020":0,
  "Mayo_2020":0,
  "Junio_2020":0,
  "Julio_2020":0,
  "Agosto_2020":0,
  "Septiembre_2020":0,
  "Octubre_2020":0,
  "Noviembre_2020":0,
  "Diciembre_2020":0,
  "Enero_2021":0,
  "Febrero_2021":0,
  "Marzo_2021":0,
  "Abril_2021":0,
  "Mayo_2021":0,
  "Junio_2021":0,
  "Julio_2021":0,
  "Agosto_2021":0,
  "Septiembre_2021":0,
  "Octubre_2021":0,
  "Noviembre_2021":0,
  "Diciembre_2021":0,
  "Enero_2022":0,
  "Febrero_2022":0,
  "Marzo_2022":0,
  "Abril_2022":0,
  "Mayo_2022":0,
  "Junio_2022":0,
  "Julio_2022":0,
  "Agosto_2022":0,
  "Septiembre_2022":0,
  "Octubre_2022":0,
  "Noviembre_2022":0,
  "Diciembre_2022":0,
  "Enero_2023":0,
  "Febrero_2023":0,
  "Marzo_2023":0,
  "Abril_2023":0,
  "Mayo_2023":0,
  "Junio_2023":0,
  "Julio_2023":0,
  "Agosto_2023":0,
  "Septiembre_2023":0,
  "Octubre_2023":0,
  "Noviembre_2023":0,
  "Diciembre_2023":0,
  "Enero_2024":0,
  "Febrero_2024":0,
  "Marzo_2024":0,
  "Abril_2024":0,
  "Mayo_2024":0,
  "Junio_2024":0,
  "Julio_2024":0,
  "Agosto_2024":0,
  "Septiembre_2024":0,
  "Octubre_2024":0,
  "Noviembre_2024":0,
  "Diciembre_2024":0,
  "Enero_2025":0,
  "Febrero_2025":0,
  "Marzo_2025":0,
  "Abril_2025":1,
  "Mayo_2025":1,
  "Junio_2025":1,
  "Julio_2025":1,
  "Agosto_2025":1,
  "Septiembre_2025":1,
  "Octubre_2025":0,
  "Noviembre_2025":0,
  "Diciembre_2025":0
 },
 {
  "organismo_nombre":"Municipalidad de Lo Prado",
  "base":"Cod. Trabajo",
  "sexo":"hombre",
  "Enero_2018":0,
  "Febrero_2018":0,
  "Marzo_2018":0,
  "Abril_2018":0,
  "Mayo_2018":0,
  "Junio_2018":0,
  "Julio_2018":0,
  "Agosto_2018":1,
  "Septiembre_2018":0,
  "Octubre_2018":0,
  "Noviembre_2018":2,
  "Diciembre_2018":1,
  "Enero_2019":1,
  "Febrero_2019":0,
  "Marzo_2019":0,
  "Abril_2019":0,
  "Mayo_2019":0,
  "Junio_2019":1,
  "Julio_2019":1,
  "Agosto_2019":1,
  "Septiembre_2019":1,
  "Octubre_2019":0,
  "Noviembre_2019":0,
  "Diciembre_2019":0,
  "Enero_2020":0,
  "Febrero_2020":0,
  "Marzo_2020":0,
  "Abril_2020":0,
  "Mayo_2020":0,
  "Junio_2020":0,
  "Julio_2020":0,
  "Agosto_2020":0,
  "Septiembre_2020":0,
  "Octubre_2020":0,
  "Noviembre_2020":0,
  "Diciembre_2020":0,
  "Enero_2021":0,
  "Febrero_2021":0,
  "Marzo_2021":1,
  "Abril_2021":1,
  "Mayo_2021":1,
  "Junio_2021":1,
  "Julio_2021":1,
  "Agosto_2021":1,
  "Septiembre_2021":1,
  "Octubre_2021":1,
  "Noviembre_2021":1,
  "Diciembre_2021":1,
  "Enero_2022":1,
  "Febrero_2022":1,
  "Marzo_2022":1,
  "Abril_2022":1,
  "Mayo_2022":1,
  "Junio_2022":1,
  "Julio_2022":1,
  "Agosto_2022":1,
  "Septiembre_2022":1,
  "Octubre_2022":1,
  "Noviembre_2022":2,
  "Diciembre_2022":1,
  "Enero_2023":10,
  "Febrero_2023":18,
  "Marzo_2023":9,
  "Abril_2023":9,
  "Mayo_2023":9,
  "Junio_2023":7,
  "Julio_2023":7,
  "Agosto_2023":12,
  "Septiembre_2023":13,
  "Octubre_2023":21,
  "Noviembre_2023":23,
  "Diciembre_2023":42,
  "Enero_2024":32,
  "Febrero_2024":32,
  "Marzo_2024":32,
  "Abril_2024":32,
  "Mayo_2024":35,
  "Junio_2024":48,
  "Julio_2024":47,
  "Agosto_2024":53,
  "Septiembre_2024":45,
  "Octubre_2024":46,
  "Noviembre_2024":49,
  "Diciembre_2024":50,
  "Enero_2025":66,
  "Febrero_2025":62,
  "Marzo_2025":63,
  "Abril_2025":59,
  "Mayo_2025":60,
  "Junio_2025":63,
  "Julio_2025":59,
  "Agosto_2025":59,
  "Septiembre_2025":56,
  "Octubre_2025":0,
  "Noviembre_2025":0,
  "Diciembre_2025":0
 },
 {
  "organismo_nombre":"Municipalidad de Lo Prado",
  "base":"Cod. Trabajo",
  "sexo":"male",
  "Enero_2018":0,
  "Febrero_2018":0,
  "Marzo_2018":0,
  "Abril_2018":0,
  "Mayo_2018":0,
  "Junio_2018":0,
  "Julio_2018":0,
  "Agosto_2018":0,
  "Septiembre_2018":0,
  "Octubre_2018":0,
  "Noviembre_2018":0,
  "Diciembre_2018":0,
  "Enero_2019":0,
  "Febrero_2019":0,
  "Marzo_2019":0,
  "Abril_2019":0,
  "Mayo_2019":0,
  "Junio_2019":0,
  "Julio_2019":0,
  "Agosto_2019":0,
  "Septiembre_2019":0,
  "Octubre_2019":0,
  "Noviembre_2019":0,
  "Diciembre_2019":0,
  "Enero_2020":0,
  "Febrero_2020":0,
  "Marzo_2020":0,
  "Abril_2020":0,
  "Mayo_2020":0,
  "Junio_2020":0,
  "Julio_2020":0,
  "Agosto_2020":0,
  "Septiembre_2020":0,
  "Octubre_2020":0,
  "Noviembre_2020":0,
  "Diciembre_2020":0,
  "Enero_2021":0,
  "Febrero_2021":0,
  "Marzo_2021":0,
  "Abril_2021":0,
  "Mayo_2021":0,
  "Junio_2021":0,
  "Julio_2021":0,
  "Agosto_2021":0,
  "Septiembre_2021":0,
  "Octubre_2021":0,
  "Noviembre_2021":0,
  "Diciembre_2021":0,
  "Enero_2022":0,
  "Febrero_2022":0,
  "Marzo_2022":0,
  "Abril_2022":0,
  "Mayo_2022":0,
  "Junio_2022":0,
  "Julio_2022":0,
  "Agosto_2022":0,
  "Septiembre_2022":0,
  "Octubre_2022":0,
  "Noviembre_2022":0,
  "Diciembre_2022":0,
  "Enero_2023":0,
  "Febrero_2023":0,
  "Marzo_2023":0,
  "Abril_2023":0,
  "Mayo_2023":0,
  "Junio_2023":0,
  "Julio_2023":0,
  "Agosto_2023":0,
  "Septiembre_2023":0,
  "Octubre_2023":0,
  "Noviembre_2023":0,
  "Diciembre_2023":0,
  "Enero_2024":0,
  "Febrero_2024":0,
  "Marzo_2024":0,
  "Abril_2024":0,
  "Mayo_2024":0,
  "Junio_2024":0,
  "Julio_2024":0,
  "Agosto_2024":0,
  "Septiembre_2024":0,
  "Octubre_2024":0,
  "Noviembre_2024":0,
  "Diciembre_2024":0,
  "Enero_2025":0,
  "Febrero_2025":0,
  "Marzo_2025":0,
  "Abril_2025":0,
  "Mayo_2025":0,
  "Junio_2025":0,
  "Julio_2025":0,
  "Agosto_2025":1,
  "Septiembre_2025":1,
  "Octubre_2025":0,
  "Noviembre_2025":0,
  "Diciembre_2025":0
 },
 {
  "organismo_nombre":"Municipalidad de Lo Prado",
  "base":"Cod. Trabajo",
  "sexo":"mujer",
  "Enero_2018":3,
  "Febrero_2018":2,
  "Marzo_2018":2,
  "Abril_2018":2,
  "Mayo_2018":2,
  "Junio_2018":2,
  "Julio_2018":2,
  "Agosto_2018":2,
  "Septiembre_2018":2,
  "Octubre_2018":2,
  "Noviembre_2018":3,
  "Diciembre_2018":2,
  "Enero_2019":2,
  "Febrero_2019":2,
  "Marzo_2019":2,
  "Abril_2019":2,
  "Mayo_2019":4,
  "Junio_2019":2,
  "Julio_2019":2,
  "Agosto_2019":2,
  "Septiembre_2019":2,
  "Octubre_2019":2,
  "Noviembre_2019":2,
  "Diciembre_2019":2,
  "Enero_2020":3,
  "Febrero_2020":3,
  "Marzo_2020":3,
  "Abril_2020":3,
  "Mayo_2020":3,
  "Junio_2020":3,
  "Julio_2020":3,
  "Agosto_2020":3,
  "Septiembre_2020":3,
  "Octubre_2020":3,
  "Noviembre_2020":4,
  "Diciembre_2020":4,
  "Enero_2021":3,
  "Febrero_2021":3,
  "Marzo_2021":3,
  "Abril_2021":3,
  "Mayo_2021":3,
  "Junio_2021":2,
  "Julio_2021":2,
  "Agosto_2021":2,
  "Septiembre_2021":2,
  "Octubre_2021":2,
  "Noviembre_2021":2,
  "Diciembre_2021":2,
  "Enero_2022":2,
  "Febrero_2022":2,
  "Marzo_2022":2,
  "Abril_2022":2,
  "Mayo_2022":2,
  "Junio_2022":2,
  "Julio_2022":2,
  "Agosto_2022":2,
  "Septiembre_2022":2,
  "Octubre_2022":2,
  "Noviembre_2022":2,
  "Diciembre_2022":2,
  "Enero_2023":8,
  "Febrero_2023":16,
  "Marzo_2023":7,
  "Abril_2023":7,
  "Mayo_2023":8,
  "Junio_2023":9,
  "Julio_2023":9,
  "Agosto_2023":13,
  "Septiembre_2023":13,
  "Octubre_2023":15,
  "Noviembre_2023":14,
  "Diciembre_2023":26,
  "Enero_2024":22,
  "Febrero_2024":23,
  "Marzo_2024":22,
  "Abril_2024":22,
  "Mayo_2024":23,
  "Junio_2024":28,
  "Julio_2024":23,
  "Agosto_2024":32,
  "Septiembre_2024":32,
  "Octubre_2024":32,
  "Noviembre_2024":33,
  "Diciembre_2024":33,
  "Enero_2025":32,
  "Febrero_2025":30,
  "Marzo_2025":32,
  "Abril_2025":33,
  "Mayo_2025":36,
  "Junio_2025":34,
  "Julio_2025":35,
  "Agosto_2025":38,
  "Septiembre_2025":36,
  "Octubre_2025":0,
  "Noviembre_2025":0,
  "Diciembre_2025":0
 },
 {
  "organismo_nombre":"Municipalidad de Lo Prado",
  "base":"Contrata",
  "sexo":"desconocido",
  "Enero_2018":1,
  "Febrero_2018":2,
  "Marzo_2018":1,
  "Abril_2018":1,
  "Mayo_2018":1,
  "Junio_2018":1,
  "Julio_2018":1,
  "Agosto_2018":1,
  "Septiembre_2018":1,
  "Octubre_2018":1,
  "Noviembre_2018":1,
  "Diciembre_2018":1,
  "Enero_2019":1,
  "Febrero_2019":1,
  "Marzo_2019":2,
  "Abril_2019":0,
  "Mayo_2019":1,
  "Junio_2019":1,
  "Julio_2019":1,
  "Agosto_2019":1,
  "Septiembre_2019":1,
  "Octubre_2019":1,
  "Noviembre_2019":1,
  "Diciembre_2019":1,
  "Enero_2020":1,
  "Febrero_2020":1,
  "Marzo_2020":1,
  "Abril_2020":1,
  "Mayo_2020":1,
  "Junio_2020":1,
  "Julio_2020":1,
  "Agosto_2020":1,
  "Septiembre_2020":1,
  "Octubre_2020":1,
  "Noviembre_2020":1,
  "Diciembre_2020":1,
  "Enero_2021":1,
  "Febrero_2021":1,
  "Marzo_2021":1,
  "Abril_2021":1,
  "Mayo_2021":1,
  "Junio_2021":1,
  "Julio_2021":1,
  "Agosto_2021":1,
  "Septiembre_2021":1,
  "Octubre_2021":1,
  "Noviembre_2021":1,
  "Diciembre_2021":1,
  "Enero_2022":1,
  "Febrero_2022":1,
  "Marzo_2022":1,
  "Abril_2022":1,
  "Mayo_2022":1,
  "Junio_2022":1,
  "Julio_2022":1,
  "Agosto_2022":1,
  "Septiembre_2022":1,
  "Octubre_2022":3,
  "Noviembre_2022":1,
  "Diciembre_2022":1,
  "Enero_2023":1,
  "Febrero_2023":1,
  "Marzo_2023":1,
  "Abril_2023":1,
  "Mayo_2023":1,
  "Junio_2023":1,
  "Julio_2023":1,
  "Agosto_2023":1,
  "Septiembre_2023":1,
  "Octubre_2023":1,
  "Noviembre_2023":0,
  "Diciembre_2023":0,
  "Enero_2024":0,
  "Febrero_2024":0,
  "Marzo_2024":0,
  "Abril_2024":0,
  "Mayo_2024":1,
  "Junio_2024":1,
  "Julio_2024":1,
  "Agosto_2024":1,
  "Septiembre_2024":1,
  "Octubre_2024":1,
  "Noviembre_2024":1,
  "Diciembre_2024":1,
  "Enero_2025":2,
  "Febrero_2025":2,
  "Marzo_2025":2,
  "Abril_2025":2,
  "Mayo_2025":2,
  "Junio_2025":2,
  "Julio_2025":2,
  "Agosto_2025":2,
  "Septiembre_2025":2,
  "Octubre_2025":0,
  "Noviembre_2025":0,
  "Diciembre_2025":0
 },
 {
  "organismo_nombre":"Municipalidad de Lo Prado",
  "base":"Contrata",
  "sexo":"hombre",
  "Enero_2018":67,
  "Febrero_2018":65,
  "Marzo_2018":69,
  "Abril_2018":62,
  "Mayo_2018":65,
  "Junio_2018":63,
  "Julio_2018":66,
  "Agosto_2018":66,
  "Septiembre_2018":66,
  "Octubre_2018":65,
  "Noviembre_2018":65,
  "Diciembre_2018":69,
  "Enero_2019":69,
  "Febrero_2019":68,
  "Marzo_2019":142,
  "Abril_2019":0,
  "Mayo_2019":75,
  "Junio_2019":74,
  "Julio_2019":76,
  "Agosto_2019":74,
  "Septiembre_2019":73,
  "Octubre_2019":76,
  "Noviembre_2019":75,
  "Diciembre_2019":75,
  "Enero_2020":78,
  "Febrero_2020":79,
  "Marzo_2020":80,
  "Abril_2020":79,
  "Mayo_2020":81,
  "Junio_2020":78,
  "Julio_2020":78,
  "Agosto_2020":78,
  "Septiembre_2020":78,
  "Octubre_2020":78,
  "Noviembre_2020":79,
  "Diciembre_2020":79,
  "Enero_2021":78,
  "Febrero_2021":79,
  "Marzo_2021":80,
  "Abril_2021":79,
  "Mayo_2021":80,
  "Junio_2021":75,
  "Julio_2021":76,
  "Agosto_2021":75,
  "Septiembre_2021":74,
  "Octubre_2021":76,
  "Noviembre_2021":75,
  "Diciembre_2021":79,
  "Enero_2022":80,
  "Febrero_2022":73,
  "Marzo_2022":72,
  "Abril_2022":68,
  "Mayo_2022":68,
  "Junio_2022":70,
  "Julio_2022":73,
  "Agosto_2022":74,
  "Septiembre_2022":73,
  "Octubre_2022":146,
  "Noviembre_2022":72,
  "Diciembre_2022":71,
  "Enero_2023":78,
  "Febrero_2023":76,
  "Marzo_2023":76,
  "Abril_2023":78,
  "Mayo_2023":82,
  "Junio_2023":82,
  "Julio_2023":82,
  "Agosto_2023":84,
  "Septiembre_2023":86,
  "Octubre_2023":87,
  "Noviembre_2023":87,
  "Diciembre_2023":89,
  "Enero_2024":84,
  "Febrero_2024":81,
  "Marzo_2024":38,
  "Abril_2024":78,
  "Mayo_2024":89,
  "Junio_2024":88,
  "Julio_2024":89,
  "Agosto_2024":89,
  "Septiembre_2024":87,
  "Octubre_2024":91,
  "Noviembre_2024":88,
  "Diciembre_2024":88,
  "Enero_2025":90,
  "Febrero_2025":86,
  "Marzo_2025":86,
  "Abril_2025":89,
  "Mayo_2025":90,
  "Junio_2025":87,
  "Julio_2025":89,
  "Agosto_2025":87,
  "Septiembre_2025":87,
  "Octubre_2025":0,
  "Noviembre_2025":0,
  "Diciembre_2025":0
 },
 {
  "organismo_nombre":"Municipalidad de Lo Prado",
  "base":"Contrata",
  "sexo":"male",
  "Enero_2018":0,
  "Febrero_2018":0,
  "Marzo_2018":0,
  "Abril_2018":0,
  "Mayo_2018":0,
  "Junio_2018":0,
  "Julio_2018":0,
  "Agosto_2018":0,
  "Septiembre_2018":0,
  "Octubre_2018":0,
  "Noviembre_2018":0,
  "Diciembre_2018":0,
  "Enero_2019":0,
  "Febrero_2019":0,
  "Marzo_2019":0,
  "Abril_2019":0,
  "Mayo_2019":0,
  "Junio_2019":0,
  "Julio_2019":0,
  "Agosto_2019":0,
  "Septiembre_2019":0,
  "Octubre_2019":0,
  "Noviembre_2019":0,
  "Diciembre_2019":0,
  "Enero_2020":0,
  "Febrero_2020":0,
  "Marzo_2020":0,
  "Abril_2020":0,
  "Mayo_2020":0,
  "Junio_2020":0,
  "Julio_2020":0,
  "Agosto_2020":0,
  "Septiembre_2020":0,
  "Octubre_2020":0,
  "Noviembre_2020":0,
  "Diciembre_2020":0,
  "Enero_2021":0,
  "Febrero_2021":0,
  "Marzo_2021":0,
  "Abril_2021":0,
  "Mayo_2021":0,
  "Junio_2021":0,
  "Julio_2021":0,
  "Agosto_2021":0,
  "Septiembre_2021":0,
  "Octubre_2021":0,
  "Noviembre_2021":0,
  "Diciembre_2021":0,
  "Enero_2022":0,
  "Febrero_2022":0,
  "Marzo_2022":0,
  "Abril_2022":0,
  "Mayo_2022":0,
  "Junio_2022":0,
  "Julio_2022":0,
  "Agosto_2022":0,
  "Septiembre_2022":0,
  "Octubre_2022":0,
  "Noviembre_2022":0,
  "Diciembre_2022":0,
  "Enero_2023":0,
  "Febrero_2023":0,
  "Marzo_2023":0,
  "Abril_2023":0,
  "Mayo_2023":0,
  "Junio_2023":0,
  "Julio_2023":0,
  "Agosto_2023":0,
  "Septiembre_2023":0,
  "Octubre_2023":0,
  "Noviembre_2023":0,
  "Diciembre_2023":0,
  "Enero_2024":0,
  "Febrero_2024":0,
  "Marzo_2024":0,
  "Abril_2024":0,
  "Mayo_2024":0,
  "Junio_2024":0,
  "Julio_2024":0,
  "Agosto_2024":0,
  "Septiembre_2024":0,
  "Octubre_2024":0,
  "Noviembre_2024":0,
  "Diciembre_2024":0,
  "Enero_2025":0,
  "Febrero_2025":0,
  "Marzo_2025":0,
  "Abril_2025":0,
  "Mayo_2025":0,
  "Junio_2025":0,
  "Julio_2025":0,
  "Agosto_2025":0,
  "Septiembre_2025":1,
  "Octubre_2025":0,
  "Noviembre_2025":0,
  "Diciembre_2025":0
 },
 {
  "organismo_nombre":"Municipalidad de Lo Prado",
  "base":"Contrata",
  "sexo":"mujer",
  "Enero_2018":42,
  "Febrero_2018":42,
  "Marzo_2018":42,
  "Abril_2018":44,
  "Mayo_2018":44,
  "Junio_2018":44,
  "Julio_2018":46,
  "Agosto_2018":46,
  "Septiembre_2018":48,
  "Octubre_2018":48,
  "Noviembre_2018":47,
  "Diciembre_2018":47,
  "Enero_2019":48,
  "Febrero_2019":50,
  "Marzo_2019":100,
  "Abril_2019":0,
  "Mayo_2019":52,
  "Junio_2019":51,
  "Julio_2019":53,
  "Agosto_2019":53,
  "Septiembre_2019":53,
  "Octubre_2019":53,
  "Noviembre_2019":53,
  "Diciembre_2019":53,
  "Enero_2020":53,
  "Febrero_2020":55,
  "Marzo_2020":53,
  "Abril_2020":52,
  "Mayo_2020":54,
  "Junio_2020":49,
  "Julio_2020":51,
  "Agosto_2020":48,
  "Septiembre_2020":49,
  "Octubre_2020":51,
  "Noviembre_2020":49,
  "Diciembre_2020":49,
  "Enero_2021":48,
  "Febrero_2021":48,
  "Marzo_2021":48,
  "Abril_2021":47,
  "Mayo_2021":48,
  "Junio_2021":48,
  "Julio_2021":52,
  "Agosto_2021":50,
  "Septiembre_2021":47,
  "Octubre_2021":49,
  "Noviembre_2021":47,
  "Diciembre_2021":50,
  "Enero_2022":49,
  "Febrero_2022":45,
  "Marzo_2022":45,
  "Abril_2022":46,
  "Mayo_2022":47,
  "Junio_2022":47,
  "Julio_2022":53,
  "Agosto_2022":52,
  "Septiembre_2022":53,
  "Octubre_2022":175,
  "Noviembre_2022":54,
  "Diciembre_2022":55,
  "Enero_2023":61,
  "Febrero_2023":58,
  "Marzo_2023":58,
  "Abril_2023":58,
  "Mayo_2023":62,
  "Junio_2023":58,
  "Julio_2023":58,
  "Agosto_2023":60,
  "Septiembre_2023":60,
  "Octubre_2023":60,
  "Noviembre_2023":63,
  "Diciembre_2023":63,
  "Enero_2024":54,
  "Febrero_2024":52,
  "Marzo_2024":18,
  "Abril_2024":54,
  "Mayo_2024":59,
  "Junio_2024":60,
  "Julio_2024":63,
  "Agosto_2024":61,
  "Septiembre_2024":61,
  "Octubre_2024":61,
  "Noviembre_2024":62,
  "Diciembre_2024":63,
  "Enero_2025":64,
  "Febrero_2025":61,
  "Marzo_2025":60,
  "Abril_2025":60,
  "Mayo_2025":61,
  "Junio_2025":60,
  "Julio_2025":62,
  "Agosto_2025":59,
  "Septiembre_2025":59,
  "Octubre_2025":0,
  "Noviembre_2025":0,
  "Diciembre_2025":0
 },
 {
  "organismo_nombre":"Municipalidad de Lo Prado",
  "base":"Honorarios",
  "sexo":"desconocido",
  "Enero_2018":1,
  "Febrero_2018":1,
  "Marzo_2018":1,
  "Abril_2018":0,
  "Mayo_2018":0,
  "Junio_2018":0,
  "Julio_2018":0,
  "Agosto_2018":0,
  "Septiembre_2018":0,
  "Octubre_2018":0,
  "Noviembre_2018":0,
  "Diciembre_2018":1,
  "Enero_2019":0,
  "Febrero_2019":0,
  "Marzo_2019":0,
  "Abril_2019":0,
  "Mayo_2019":0,
  "Junio_2019":0,
  "Julio_2019":0,
  "Agosto_2019":1,
  "Septiembre_2019":1,
  "Octubre_2019":1,
  "Noviembre_2019":1,
  "Diciembre_2019":1,
  "Enero_2020":1,
  "Febrero_2020":2,
  "Marzo_2020":2,
  "Abril_2020":1,
  "Mayo_2020":1,
  "Junio_2020":1,
  "Julio_2020":1,
  "Agosto_2020":1,
  "Septiembre_2020":1,
  "Octubre_2020":1,
  "Noviembre_2020":1,
  "Diciembre_2020":1,
  "Enero_2021":2,
  "Febrero_2021":0,
  "Marzo_2021":1,
  "Abril_2021":1,
  "Mayo_2021":1,
  "Junio_2021":1,
  "Julio_2021":1,
  "Agosto_2021":1,
  "Septiembre_2021":1,
  "Octubre_2021":1,
  "Noviembre_2021":1,
  "Diciembre_2021":1,
  "Enero_2022":0,
  "Febrero_2022":0,
  "Marzo_2022":0,
  "Abril_2022":0,
  "Mayo_2022":1,
  "Junio_2022":1,
  "Julio_2022":1,
  "Agosto_2022":5,
  "Septiembre_2022":0,
  "Octubre_2022":0,
  "Noviembre_2022":0,
  "Diciembre_2022":0,
  "Enero_2023":5,
  "Febrero_2023":0,
  "Marzo_2023":0,
  "Abril_2023":0,
  "Mayo_2023":0,
  "Junio_2023":0,
  "Julio_2023":1,
  "Agosto_2023":3,
  "Septiembre_2023":3,
  "Octubre_2023":3,
  "Noviembre_2023":2,
  "Diciembre_2023":5,
  "Enero_2024":4,
  "Febrero_2024":3,
  "Marzo_2024":3,
  "Abril_2024":2,
  "Mayo_2024":2,
  "Junio_2024":2,
  "Julio_2024":2,
  "Agosto_2024":2,
  "Septiembre_2024":2,
  "Octubre_2024":2,
  "Noviembre_2024":3,
  "Diciembre_2024":4,
  "Enero_2025":4,
  "Febrero_2025":4,
  "Marzo_2025":3,
  "Abril_2025":3,
  "Mayo_2025":2,
  "Junio_2025":3,
  "Julio_2025":3,
  "Agosto_2025":3,
  "Septiembre_2025":5,
  "Octubre_2025":0,
  "Noviembre_2025":0,
  "Diciembre_2025":0
 },
 {
  "organismo_nombre":"Municipalidad de Lo Prado",
  "base":"Honorarios",
  "sexo":"female",
  "Enero_2018":0,
  "Febrero_2018":0,
  "Marzo_2018":0,
  "Abril_2018":0,
  "Mayo_2018":0,
  "Junio_2018":0,
  "Julio_2018":0,
  "Agosto_2018":0,
  "Septiembre_2018":0,
  "Octubre_2018":0,
  "Noviembre_2018":0,
  "Diciembre_2018":0,
  "Enero_2019":0,
  "Febrero_2019":0,
  "Marzo_2019":0,
  "Abril_2019":0,
  "Mayo_2019":0,
  "Junio_2019":0,
  "Julio_2019":0,
  "Agosto_2019":0,
  "Septiembre_2019":0,
  "Octubre_2019":0,
  "Noviembre_2019":0,
  "Diciembre_2019":0,
  "Enero_2020":0,
  "Febrero_2020":0,
  "Marzo_2020":0,
  "Abril_2020":0,
  "Mayo_2020":0,
  "Junio_2020":0,
  "Julio_2020":0,
  "Agosto_2020":0,
  "Septiembre_2020":0,
  "Octubre_2020":0,
  "Noviembre_2020":0,
  "Diciembre_2020":0,
  "Enero_2021":0,
  "Febrero_2021":0,
  "Marzo_2021":0,
  "Abril_2021":0,
  "Mayo_2021":0,
  "Junio_2021":0,
  "Julio_2021":0,
  "Agosto_2021":0,
  "Septiembre_2021":0,
  "Octubre_2021":0,
  "Noviembre_2021":0,
  "Diciembre_2021":0,
  "Enero_2022":0,
  "Febrero_2022":0,
  "Marzo_2022":0,
  "Abril_2022":0,
  "Mayo_2022":0,
  "Junio_2022":0,
  "Julio_2022":0,
  "Agosto_2022":0,
  "Septiembre_2022":0,
  "Octubre_2022":0,
  "Noviembre_2022":0,
  "Diciembre_2022":0,
  "Enero_2023":0,
  "Febrero_2023":0,
  "Marzo_2023":0,
  "Abril_2023":0,
  "Mayo_2023":0,
  "Junio_2023":0,
  "Julio_2023":0,
  "Agosto_2023":0,
  "Septiembre_2023":0,
  "Octubre_2023":0,
  "Noviembre_2023":0,
  "Diciembre_2023":0,
  "Enero_2024":0,
  "Febrero_2024":0,
  "Marzo_2024":0,
  "Abril_2024":0,
  "Mayo_2024":0,
  "Junio_2024":0,
  "Julio_2024":0,
  "Agosto_2024":0,
  "Septiembre_2024":0,
  "Octubre_2024":0,
  "Noviembre_2024":0,
  "Diciembre_2024":0,
  "Enero_2025":0,
  "Febrero_2025":0,
  "Marzo_2025":0,
  "Abril_2025":0,
  "Mayo_2025":0,
  "Junio_2025":1,
  "Julio_2025":0,
  "Agosto_2025":5,
  "Septiembre_2025":14,
  "Octubre_2025":0,
  "Noviembre_2025":0,
  "Diciembre_2025":0
 },
 {
  "organismo_nombre":"Municipalidad de Lo Prado",
  "base":"Honorarios",
  "sexo":"hombre",
  "Enero_2018":48,
  "Febrero_2018":56,
  "Marzo_2018":45,
  "Abril_2018":45,
  "Mayo_2018":52,
  "Junio_2018":53,
  "Julio_2018":47,
  "Agosto_2018":45,
  "Septiembre_2018":46,
  "Octubre_2018":45,
  "Noviembre_2018":49,
  "Diciembre_2018":47,
  "Enero_2019":44,
  "Febrero_2019":43,
  "Marzo_2019":52,
  "Abril_2019":51,
  "Mayo_2019":50,
  "Junio_2019":51,
  "Julio_2019":49,
  "Agosto_2019":51,
  "Septiembre_2019":55,
  "Octubre_2019":59,
  "Noviembre_2019":60,
  "Diciembre_2019":66,
  "Enero_2020":50,
  "Febrero_2020":80,
  "Marzo_2020":67,
  "Abril_2020":59,
  "Mayo_2020":59,
  "Junio_2020":71,
  "Julio_2020":73,
  "Agosto_2020":70,
  "Septiembre_2020":58,
  "Octubre_2020":59,
  "Noviembre_2020":59,
  "Diciembre_2020":85,
  "Enero_2021":64,
  "Febrero_2021":28,
  "Marzo_2021":66,
  "Abril_2021":56,
  "Mayo_2021":57,
  "Junio_2021":56,
  "Julio_2021":57,
  "Agosto_2021":59,
  "Septiembre_2021":59,
  "Octubre_2021":59,
  "Noviembre_2021":61,
  "Diciembre_2021":56,
  "Enero_2022":52,
  "Febrero_2022":69,
  "Marzo_2022":53,
  "Abril_2022":60,
  "Mayo_2022":56,
  "Junio_2022":56,
  "Julio_2022":76,
  "Agosto_2022":144,
  "Septiembre_2022":36,
  "Octubre_2022":30,
  "Noviembre_2022":97,
  "Diciembre_2022":42,
  "Enero_2023":179,
  "Febrero_2023":27,
  "Marzo_2023":20,
  "Abril_2023":23,
  "Mayo_2023":41,
  "Junio_2023":24,
  "Julio_2023":67,
  "Agosto_2023":78,
  "Septiembre_2023":69,
  "Octubre_2023":68,
  "Noviembre_2023":53,
  "Diciembre_2023":148,
  "Enero_2024":58,
  "Febrero_2024":62,
  "Marzo_2024":59,
  "Abril_2024":69,
  "Mayo_2024":72,
  "Junio_2024":73,
  "Julio_2024":76,
  "Agosto_2024":99,
  "Septiembre_2024":107,
  "Octubre_2024":113,
  "Noviembre_2024":125,
  "Diciembre_2024":137,
  "Enero_2025":110,
  "Febrero_2025":133,
  "Marzo_2025":122,
  "Abril_2025":120,
  "Mayo_2025":76,
  "Junio_2025":145,
  "Julio_2025":143,
  "Agosto_2025":144,
  "Septiembre_2025":141,
  "Octubre_2025":0,
  "Noviembre_2025":0,
  "Diciembre_2025":0
 },
 {
  "organismo_nombre":"Municipalidad de Lo Prado",
  "base":"Honorarios",
  "sexo":"male",
  "Enero_2018":0,
  "Febrero_2018":0,
  "Marzo_2018":0,
  "Abril_2018":0,
  "Mayo_2018":0,
  "Junio_2018":0,
  "Julio_2018":0,
  "Agosto_2018":0,
  "Septiembre_2018":0,
  "Octubre_2018":0,
  "Noviembre_2018":0,
  "Diciembre_2018":0,
  "Enero_2019":0,
  "Febrero_2019":0,
  "Marzo_2019":0,
  "Abril_2019":0,
  "Mayo_2019":0,
  "Junio_2019":0,
  "Julio_2019":0,
  "Agosto_2019":0,
  "Septiembre_2019":0,
  "Octubre_2019":0,
  "Noviembre_2019":0,
  "Diciembre_2019":0,
  "Enero_2020":0,
  "Febrero_2020":0,
  "Marzo_2020":0,
  "Abril_2020":0,
  "Mayo_2020":0,
  "Junio_2020":0,
  "Julio_2020":0,
  "Agosto_2020":0,
  "Septiembre_2020":0,
  "Octubre_2020":0,
  "Noviembre_2020":0,
  "Diciembre_2020":0,
  "Enero_2021":0,
  "Febrero_2021":0,
  "Marzo_2021":0,
  "Abril_2021":0,
  "Mayo_2021":0,
  "Junio_2021":0,
  "Julio_2021":0,
  "Agosto_2021":0,
  "Septiembre_2021":0,
  "Octubre_2021":0,
  "Noviembre_2021":0,
  "Diciembre_2021":0,
  "Enero_2022":0,
  "Febrero_2022":0,
  "Marzo_2022":0,
  "Abril_2022":0,
  "Mayo_2022":0,
  "Junio_2022":0,
  "Julio_2022":0,
  "Agosto_2022":0,
  "Septiembre_2022":0,
  "Octubre_2022":0,
  "Noviembre_2022":0,
  "Diciembre_2022":0,
  "Enero_2023":0,
  "Febrero_2023":0,
  "Marzo_2023":0,
  "Abril_2023":0,
  "Mayo_2023":0,
  "Junio_2023":0,
  "Julio_2023":0,
  "Agosto_2023":0,
  "Septiembre_2023":0,
  "Octubre_2023":0,
  "Noviembre_2023":0,
  "Diciembre_2023":0,
  "Enero_2024":0,
  "Febrero_2024":0,
  "Marzo_2024":0,
  "Abril_2024":0,
  "Mayo_2024":0,
  "Junio_2024":0,
  "Julio_2024":0,
  "Agosto_2024":0,
  "Septiembre_2024":0,
  "Octubre_2024":0,
  "Noviembre_2024":0,
  "Diciembre_2024":0,
  "Enero_2025":0,
  "Febrero_2025":0,
  "Marzo_2025":0,
  "Abril_2025":0,
  "Mayo_2025":0,
  "Junio_2025":0,
  "Julio_2025":0,
  "Agosto_2025":10,
  "Septiembre_2025":7,
  "Octubre_2025":0,
  "Noviembre_2025":0,
  "Diciembre_2025":0
 },
 {
  "organismo_nombre":"Municipalidad de Lo Prado",
  "base":"Honorarios",
  "sexo":"mujer",
  "Enero_2018":73,
  "Febrero_2018":104,
  "Marzo_2018":88,
  "Abril_2018":75,
  "Mayo_2018":112,
  "Junio_2018":86,
  "Julio_2018":91,
  "Agosto_2018":88,
  "Septiembre_2018":89,
  "Octubre_2018":85,
  "Noviembre_2018":94,
  "Diciembre_2018":86,
  "Enero_2019":83,
  "Febrero_2019":73,
  "Marzo_2019":76,
  "Abril_2019":88,
  "Mayo_2019":91,
  "Junio_2019":94,
  "Julio_2019":88,
  "Agosto_2019":88,
  "Septiembre_2019":102,
  "Octubre_2019":97,
  "Noviembre_2019":103,
  "Diciembre_2019":105,
  "Enero_2020":84,
  "Febrero_2020":114,
  "Marzo_2020":86,
  "Abril_2020":95,
  "Mayo_2020":94,
  "Junio_2020":99,
  "Julio_2020":97,
  "Agosto_2020":109,
  "Septiembre_2020":96,
  "Octubre_2020":98,
  "Noviembre_2020":108,
  "Diciembre_2020":133,
  "Enero_2021":128,
  "Febrero_2021":44,
  "Marzo_2021":117,
  "Abril_2021":97,
  "Mayo_2021":95,
  "Junio_2021":100,
  "Julio_2021":100,
  "Agosto_2021":101,
  "Septiembre_2021":109,
  "Octubre_2021":120,
  "Noviembre_2021":114,
  "Diciembre_2021":115,
  "Enero_2022":97,
  "Febrero_2022":106,
  "Marzo_2022":116,
  "Abril_2022":113,
  "Mayo_2022":118,
  "Junio_2022":113,
  "Julio_2022":127,
  "Agosto_2022":215,
  "Septiembre_2022":73,
  "Octubre_2022":71,
  "Noviembre_2022":165,
  "Diciembre_2022":79,
  "Enero_2023":322,
  "Febrero_2023":44,
  "Marzo_2023":109,
  "Abril_2023":69,
  "Mayo_2023":160,
  "Junio_2023":71,
  "Julio_2023":134,
  "Agosto_2023":148,
  "Septiembre_2023":143,
  "Octubre_2023":132,
  "Noviembre_2023":126,
  "Diciembre_2023":247,
  "Enero_2024":102,
  "Febrero_2024":124,
  "Marzo_2024":128,
  "Abril_2024":136,
  "Mayo_2024":142,
  "Junio_2024":156,
  "Julio_2024":158,
  "Agosto_2024":175,
  "Septiembre_2024":158,
  "Octubre_2024":190,
  "Noviembre_2024":190,
  "Diciembre_2024":190,
  "Enero_2025":181,
  "Febrero_2025":223,
  "Marzo_2025":201,
  "Abril_2025":190,
  "Mayo_2025":137,
  "Junio_2025":246,
  "Julio_2025":239,
  "Agosto_2025":240,
  "Septiembre_2025":237,
  "Octubre_2025":0,
  "Noviembre_2025":0,
  "Diciembre_2025":2
 },
 {
  "organismo_nombre":"Municipalidad de Lo Prado",
  "base":"Planta",
  "sexo":"desconocido",
  "Enero_2018":2,
  "Febrero_2018":2,
  "Marzo_2018":2,
  "Abril_2018":2,
  "Mayo_2018":2,
  "Junio_2018":2,
  "Julio_2018":2,
  "Agosto_2018":2,
  "Septiembre_2018":2,
  "Octubre_2018":2,
  "Noviembre_2018":2,
  "Diciembre_2018":2,
  "Enero_2019":2,
  "Febrero_2019":2,
  "Marzo_2019":2,
  "Abril_2019":2,
  "Mayo_2019":2,
  "Junio_2019":2,
  "Julio_2019":2,
  "Agosto_2019":2,
  "Septiembre_2019":2,
  "Octubre_2019":2,
  "Noviembre_2019":2,
  "Diciembre_2019":2,
  "Enero_2020":2,
  "Febrero_2020":2,
  "Marzo_2020":2,
  "Abril_2020":2,
  "Mayo_2020":2,
  "Junio_2020":1,
  "Julio_2020":1,
  "Agosto_2020":1,
  "Septiembre_2020":1,
  "Octubre_2020":1,
  "Noviembre_2020":1,
  "Diciembre_2020":1,
  "Enero_2021":1,
  "Febrero_2021":1,
  "Marzo_2021":1,
  "Abril_2021":1,
  "Mayo_2021":1,
  "Junio_2021":1,
  "Julio_2021":1,
  "Agosto_2021":1,
  "Septiembre_2021":1,
  "Octubre_2021":1,
  "Noviembre_2021":1,
  "Diciembre_2021":1,
  "Enero_2022":1,
  "Febrero_2022":1,
  "Marzo_2022":1,
  "Abril_2022":1,
  "Mayo_2022":1,
  "Junio_2022":1,
  "Julio_2022":1,
  "Agosto_2022":1,
  "Septiembre_2022":1,
  "Octubre_2022":2,
  "Noviembre_2022":2,
  "Diciembre_2022":2,
  "Enero_2023":2,
  "Febrero_2023":1,
  "Marzo_2023":2,
  "Abril_2023":2,
  "Mayo_2023":6,
  "Junio_2023":2,
  "Julio_2023":0,
  "Agosto_2023":2,
  "Septiembre_2023":1,
  "Octubre_2023":2,
  "Noviembre_2023":3,
  "Diciembre_2023":3,
  "Enero_2024":3,
  "Febrero_2024":3,
  "Marzo_2024":4,
  "Abril_2024":4,
  "Mayo_2024":3,
  "Junio_2024":3,
  "Julio_2024":3,
  "Agosto_2024":3,
  "Septiembre_2024":3,
  "Octubre_2024":3,
  "Noviembre_2024":3,
  "Diciembre_2024":6,
  "Enero_2025":0,
  "Febrero_2025":2,
  "Marzo_2025":1,
  "Abril_2025":1,
  "Mayo_2025":1,
  "Junio_2025":1,
  "Julio_2025":1,
  "Agosto_2025":1,
  "Septiembre_2025":1,
  "Octubre_2025":0,
  "Noviembre_2025":0,
  "Diciembre_2025":0
 },
 {
  "organismo_nombre":"Municipalidad de Lo Prado",
  "base":"Planta",
  "sexo":"hombre",
  "Enero_2018":82,
  "Febrero_2018":82,
  "Marzo_2018":85,
  "Abril_2018":85,
  "Mayo_2018":84,
  "Junio_2018":85,
  "Julio_2018":82,
  "Agosto_2018":81,
  "Septiembre_2018":81,
  "Octubre_2018":81,
  "Noviembre_2018":81,
  "Diciembre_2018":82,
  "Enero_2019":79,
  "Febrero_2019":79,
  "Marzo_2019":78,
  "Abril_2019":78,
  "Mayo_2019":79,
  "Junio_2019":78,
  "Julio_2019":78,
  "Agosto_2019":78,
  "Septiembre_2019":78,
  "Octubre_2019":78,
  "Noviembre_2019":78,
  "Diciembre_2019":78,
  "Enero_2020":78,
  "Febrero_2020":78,
  "Marzo_2020":78,
  "Abril_2020":78,
  "Mayo_2020":78,
  "Junio_2020":77,
  "Julio_2020":77,
  "Agosto_2020":77,
  "Septiembre_2020":77,
  "Octubre_2020":77,
  "Noviembre_2020":77,
  "Diciembre_2020":77,
  "Enero_2021":77,
  "Febrero_2021":77,
  "Marzo_2021":77,
  "Abril_2021":77,
  "Mayo_2021":78,
  "Junio_2021":77,
  "Julio_2021":77,
  "Agosto_2021":75,
  "Septiembre_2021":75,
  "Octubre_2021":75,
  "Noviembre_2021":74,
  "Diciembre_2021":75,
  "Enero_2022":76,
  "Febrero_2022":75,
  "Marzo_2022":75,
  "Abril_2022":73,
  "Mayo_2022":75,
  "Junio_2022":73,
  "Julio_2022":73,
  "Agosto_2022":73,
  "Septiembre_2022":72,
  "Octubre_2022":72,
  "Noviembre_2022":70,
  "Diciembre_2022":72,
  "Enero_2023":70,
  "Febrero_2023":70,
  "Marzo_2023":75,
  "Abril_2023":71,
  "Mayo_2023":150,
  "Junio_2023":69,
  "Julio_2023":0,
  "Agosto_2023":69,
  "Septiembre_2023":68,
  "Octubre_2023":69,
  "Noviembre_2023":69,
  "Diciembre_2023":69,
  "Enero_2024":79,
  "Febrero_2024":78,
  "Marzo_2024":78,
  "Abril_2024":78,
  "Mayo_2024":78,
  "Junio_2024":74,
  "Julio_2024":74,
  "Agosto_2024":74,
  "Septiembre_2024":74,
  "Octubre_2024":74,
  "Noviembre_2024":74,
  "Diciembre_2024":150,
  "Enero_2025":0,
  "Febrero_2025":75,
  "Marzo_2025":74,
  "Abril_2025":73,
  "Mayo_2025":75,
  "Junio_2025":72,
  "Julio_2025":73,
  "Agosto_2025":71,
  "Septiembre_2025":70,
  "Octubre_2025":0,
  "Noviembre_2025":0,
  "Diciembre_2025":0
 },
 {
  "organismo_nombre":"Municipalidad de Lo Prado",
  "base":"Planta",
  "sexo":"mujer",
  "Enero_2018":130,
  "Febrero_2018":130,
  "Marzo_2018":131,
  "Abril_2018":131,
  "Mayo_2018":132,
  "Junio_2018":131,
  "Julio_2018":130,
  "Agosto_2018":128,
  "Septiembre_2018":128,
  "Octubre_2018":128,
  "Noviembre_2018":128,
  "Diciembre_2018":128,
  "Enero_2019":127,
  "Febrero_2019":127,
  "Marzo_2019":128,
  "Abril_2019":128,
  "Mayo_2019":128,
  "Junio_2019":128,
  "Julio_2019":126,
  "Agosto_2019":127,
  "Septiembre_2019":127,
  "Octubre_2019":127,
  "Noviembre_2019":127,
  "Diciembre_2019":127,
  "Enero_2020":127,
  "Febrero_2020":127,
  "Marzo_2020":127,
  "Abril_2020":129,
  "Mayo_2020":129,
  "Junio_2020":128,
  "Julio_2020":127,
  "Agosto_2020":128,
  "Septiembre_2020":127,
  "Octubre_2020":127,
  "Noviembre_2020":127,
  "Diciembre_2020":126,
  "Enero_2021":126,
  "Febrero_2021":126,
  "Marzo_2021":126,
  "Abril_2021":128,
  "Mayo_2021":129,
  "Junio_2021":122,
  "Julio_2021":125,
  "Agosto_2021":126,
  "Septiembre_2021":126,
  "Octubre_2021":128,
  "Noviembre_2021":128,
  "Diciembre_2021":128,
  "Enero_2022":131,
  "Febrero_2022":131,
  "Marzo_2022":131,
  "Abril_2022":130,
  "Mayo_2022":130,
  "Junio_2022":129,
  "Julio_2022":123,
  "Agosto_2022":121,
  "Septiembre_2022":121,
  "Octubre_2022":121,
  "Noviembre_2022":121,
  "Diciembre_2022":122,
  "Enero_2023":123,
  "Febrero_2023":122,
  "Marzo_2023":126,
  "Abril_2023":122,
  "Mayo_2023":255,
  "Junio_2023":120,
  "Julio_2023":0,
  "Agosto_2023":121,
  "Septiembre_2023":118,
  "Octubre_2023":120,
  "Noviembre_2023":121,
  "Diciembre_2023":121,
  "Enero_2024":131,
  "Febrero_2024":130,
  "Marzo_2024":131,
  "Abril_2024":131,
  "Mayo_2024":129,
  "Junio_2024":122,
  "Julio_2024":122,
  "Agosto_2024":123,
  "Septiembre_2024":123,
  "Octubre_2024":122,
  "Noviembre_2024":121,
  "Diciembre_2024":242,
  "Enero_2025":0,
  "Febrero_2025":119,
  "Marzo_2025":118,
  "Abril_2025":119,
  "Mayo_2025":119,
  "Junio_2025":113,
  "Julio_2025":118,
  "Agosto_2025":113,
  "Septiembre_2025":113,
  "Octubre_2025":0,
  "Noviembre_2025":0,
  "Diciembre_2025":0
 }
]