[
 {
  "organismo_nombre":"Corporación Municipal de Cultura de TilTil",
  "base":"Codigotrabajo",
  "homologado":"Administrador(a)",
  "age_label":"18 a 30",
  "sexo":"mujer",
  "Agosto_2018":0,
  "Septiembre_2018":0,
  "Octubre_2018":0,
  "Noviembre_2018":0,
  "Diciembre_2018":0,
  "Enero_2019":0,
  "Febrero_2019":0,
  "Marzo_2019":0,
  "Abril_2019":0,
  "Mayo_2019":0,
  "Junio_2019":0,
  "Julio_2019":0,
  "Agosto_2019":0,
  "Septiembre_2019":0,
  "Octubre_2019":0,
  "Noviembre_2019":0,
  "Diciembre_2019":0,
  "Enero_2020":0,
  "Febrero_2020":0,
  "Marzo_2020":0,
  "Abril_2020":0,
  "Mayo_2020":0,
  "Junio_2020":0,
  "Julio_2020":0,
  "Agosto_2020":0,
  "Septiembre_2020":0,
  "Octubre_2020":0,
  "Noviembre_2020":0,
  "Diciembre_2020":0,
  "Enero_2021":0,
  "Febrero_2021":0,
  "Marzo_2021":0,
  "Abril_2021":0,
  "Mayo_2021":0,
  "Junio_2021":0,
  "Julio_2021":0,
  "Agosto_2021":0,
  "Septiembre_2021":0,
  "Octubre_2021":0,
  "Noviembre_2021":0,
  "Diciembre_2021":0,
  "Enero_2022":0,
  "Febrero_2022":0,
  "Marzo_2022":0,
  "Abril_2022":0,
  "Mayo_2022":0,
  "Junio_2022":0,
  "Julio_2022":0,
  "Agosto_2022":0,
  "Septiembre_2022":0,
  "Octubre_2022":0,
  "Noviembre_2022":0,
  "Diciembre_2022":0,
  "Enero_2023":0,
  "Febrero_2023":0,
  "Marzo_2023":0,
  "Abril_2023":0,
  "Mayo_2023":0,
  "Junio_2023":0,
  "Julio_2023":0,
  "Agosto_2023":0,
  "Septiembre_2023":0,
  "Octubre_2023":0,
  "Noviembre_2023":0,
  "Diciembre_2023":0,
  "Enero_2024":0,
  "Febrero_2024":0,
  "Marzo_2024":0,
  "Abril_2024":0,
  "Mayo_2024":0,
  "Junio_2024":0,
  "Julio_2024":0,
  "Agosto_2024":0,
  "Septiembre_2024":0,
  "Octubre_2024":0,
  "Noviembre_2024":0,
  "Diciembre_2024":0,
  "Enero_2025":0,
  "Febrero_2025":0,
  "Marzo_2025":0,
  "Abril_2025":0,
  "Mayo_2025":0,
  "Junio_2025":0,
  "Julio_2025":0,
  "Agosto_2025":0,
  "Septiembre_2025":0,
  "Octubre_2025":0,
  "Noviembre_2025":1750000,
  "Diciembre_2025":1975000
 },
 {
  "organismo_nombre":"Corporación Municipal de Cultura de TilTil",
  "base":"Codigotrabajo",
  "homologado":"Enseñanza Media",
  "age_label":"18 a 30",
  "sexo":"hombre",
  "Agosto_2018":0,
  "Septiembre_2018":0,
  "Octubre_2018":0,
  "Noviembre_2018":0,
  "Diciembre_2018":0,
  "Enero_2019":0,
  "Febrero_2019":0,
  "Marzo_2019":0,
  "Abril_2019":0,
  "Mayo_2019":0,
  "Junio_2019":0,
  "Julio_2019":0,
  "Agosto_2019":0,
  "Septiembre_2019":0,
  "Octubre_2019":0,
  "Noviembre_2019":0,
  "Diciembre_2019":0,
  "Enero_2020":0,
  "Febrero_2020":0,
  "Marzo_2020":0,
  "Abril_2020":0,
  "Mayo_2020":0,
  "Junio_2020":0,
  "Julio_2020":0,
  "Agosto_2020":0,
  "Septiembre_2020":0,
  "Octubre_2020":0,
  "Noviembre_2020":0,
  "Diciembre_2020":0,
  "Enero_2021":0,
  "Febrero_2021":0,
  "Marzo_2021":0,
  "Abril_2021":0,
  "Mayo_2021":0,
  "Junio_2021":0,
  "Julio_2021":0,
  "Agosto_2021":0,
  "Septiembre_2021":0,
  "Octubre_2021":0,
  "Noviembre_2021":0,
  "Diciembre_2021":0,
  "Enero_2022":0,
  "Febrero_2022":0,
  "Marzo_2022":0,
  "Abril_2022":0,
  "Mayo_2022":0,
  "Junio_2022":0,
  "Julio_2022":0,
  "Agosto_2022":0,
  "Septiembre_2022":0,
  "Octubre_2022":0,
  "Noviembre_2022":0,
  "Diciembre_2022":0,
  "Enero_2023":0,
  "Febrero_2023":0,
  "Marzo_2023":0,
  "Abril_2023":0,
  "Mayo_2023":0,
  "Junio_2023":0,
  "Julio_2023":0,
  "Agosto_2023":0,
  "Septiembre_2023":0,
  "Octubre_2023":0,
  "Noviembre_2023":0,
  "Diciembre_2023":0,
  "Enero_2024":0,
  "Febrero_2024":0,
  "Marzo_2024":0,
  "Abril_2024":0,
  "Mayo_2024":0,
  "Junio_2024":0,
  "Julio_2024":0,
  "Agosto_2024":0,
  "Septiembre_2024":0,
  "Octubre_2024":0,
  "Noviembre_2024":0,
  "Diciembre_2024":0,
  "Enero_2025":0,
  "Febrero_2025":0,
  "Marzo_2025":0,
  "Abril_2025":0,
  "Mayo_2025":440500,
  "Junio_2025":0,
  "Julio_2025":0,
  "Agosto_2025":0,
  "Septiembre_2025":0,
  "Octubre_2025":0,
  "Noviembre_2025":0,
  "Diciembre_2025":0
 },
 {
  "organismo_nombre":"Corporación Municipal de Cultura de TilTil",
  "base":"Codigotrabajo",
  "homologado":"Enseñanza Media",
  "age_label":"30 a 50",
  "sexo":"hombre",
  "Agosto_2018":0,
  "Septiembre_2018":0,
  "Octubre_2018":0,
  "Noviembre_2018":0,
  "Diciembre_2018":0,
  "Enero_2019":0,
  "Febrero_2019":0,
  "Marzo_2019":0,
  "Abril_2019":0,
  "Mayo_2019":0,
  "Junio_2019":0,
  "Julio_2019":0,
  "Agosto_2019":0,
  "Septiembre_2019":0,
  "Octubre_2019":0,
  "Noviembre_2019":0,
  "Diciembre_2019":0,
  "Enero_2020":0,
  "Febrero_2020":0,
  "Marzo_2020":0,
  "Abril_2020":0,
  "Mayo_2020":0,
  "Junio_2020":0,
  "Julio_2020":0,
  "Agosto_2020":0,
  "Septiembre_2020":0,
  "Octubre_2020":0,
  "Noviembre_2020":0,
  "Diciembre_2020":0,
  "Enero_2021":0,
  "Febrero_2021":0,
  "Marzo_2021":0,
  "Abril_2021":0,
  "Mayo_2021":0,
  "Junio_2021":0,
  "Julio_2021":0,
  "Agosto_2021":0,
  "Septiembre_2021":0,
  "Octubre_2021":0,
  "Noviembre_2021":0,
  "Diciembre_2021":0,
  "Enero_2022":0,
  "Febrero_2022":0,
  "Marzo_2022":0,
  "Abril_2022":0,
  "Mayo_2022":0,
  "Junio_2022":0,
  "Julio_2022":0,
  "Agosto_2022":0,
  "Septiembre_2022":0,
  "Octubre_2022":0,
  "Noviembre_2022":0,
  "Diciembre_2022":0,
  "Enero_2023":0,
  "Febrero_2023":0,
  "Marzo_2023":0,
  "Abril_2023":0,
  "Mayo_2023":0,
  "Junio_2023":0,
  "Julio_2023":0,
  "Agosto_2023":0,
  "Septiembre_2023":0,
  "Octubre_2023":0,
  "Noviembre_2023":0,
  "Diciembre_2023":0,
  "Enero_2024":0,
  "Febrero_2024":0,
  "Marzo_2024":0,
  "Abril_2024":0,
  "Mayo_2024":0,
  "Junio_2024":0,
  "Julio_2024":0,
  "Agosto_2024":0,
  "Septiembre_2024":650000,
  "Octubre_2024":0,
  "Noviembre_2024":0,
  "Diciembre_2024":0,
  "Enero_2025":0,
  "Febrero_2025":0,
  "Marzo_2025":0,
  "Abril_2025":0,
  "Mayo_2025":0,
  "Junio_2025":0,
  "Julio_2025":0,
  "Agosto_2025":0,
  "Septiembre_2025":0,
  "Octubre_2025":516667,
  "Noviembre_2025":620000,
  "Diciembre_2025":732330
 },
 {
  "organismo_nombre":"Corporación Municipal de Cultura de TilTil",
  "base":"Codigotrabajo",
  "homologado":"Enseñanza Media",
  "age_label":"30 a 50",
  "sexo":"mujer",
  "Agosto_2018":283889,
  "Septiembre_2018":413889,
  "Octubre_2018":459667,
  "Noviembre_2018":362500,
  "Diciembre_2018":362500,
  "Enero_2019":362500,
  "Febrero_2019":362500,
  "Marzo_2019":362500,
  "Abril_2019":362500,
  "Mayo_2019":362500,
  "Junio_2019":362500,
  "Julio_2019":362500,
  "Agosto_2019":362500,
  "Septiembre_2019":362500,
  "Octubre_2019":362500,
  "Noviembre_2019":358750,
  "Diciembre_2019":362500,
  "Enero_2020":310313,
  "Febrero_2020":265313,
  "Marzo_2020":265313,
  "Abril_2020":353751,
  "Mayo_2020":353751,
  "Junio_2020":325973,
  "Julio_2020":353751,
  "Agosto_2020":353751,
  "Septiembre_2020":353751,
  "Octubre_2020":353751,
  "Noviembre_2020":353751,
  "Diciembre_2020":353751,
  "Enero_2021":353751,
  "Febrero_2021":353751,
  "Marzo_2021":344577,
  "Abril_2021":327813,
  "Mayo_2021":327813,
  "Junio_2021":327813,
  "Julio_2021":327813,
  "Agosto_2021":353751,
  "Septiembre_2021":420418,
  "Octubre_2021":420418,
  "Noviembre_2021":420418,
  "Diciembre_2021":362084,
  "Enero_2022":500000,
  "Febrero_2022":500000,
  "Marzo_2022":500000,
  "Abril_2022":500000,
  "Mayo_2022":500000,
  "Junio_2022":500000,
  "Julio_2022":485000,
  "Agosto_2022":425000,
  "Septiembre_2022":350000,
  "Octubre_2022":350000,
  "Noviembre_2022":375000,
  "Diciembre_2022":525000,
  "Enero_2023":612500,
  "Febrero_2023":612500,
  "Marzo_2023":612500,
  "Abril_2023":612500,
  "Mayo_2023":612500,
  "Junio_2023":637500,
  "Julio_2023":637500,
  "Agosto_2023":637500,
  "Septiembre_2023":637500,
  "Octubre_2023":637500,
  "Noviembre_2023":637500,
  "Diciembre_2023":637500,
  "Enero_2024":690000,
  "Febrero_2024":0,
  "Marzo_2024":690000,
  "Abril_2024":690000,
  "Mayo_2024":690000,
  "Junio_2024":690000,
  "Julio_2024":690000,
  "Agosto_2024":690000,
  "Septiembre_2024":690000,
  "Octubre_2024":0,
  "Noviembre_2024":690000,
  "Diciembre_2024":690000,
  "Enero_2025":800000,
  "Febrero_2025":956431,
  "Marzo_2025":835200,
  "Abril_2025":835200,
  "Mayo_2025":835200,
  "Junio_2025":835200,
  "Julio_2025":835200,
  "Agosto_2025":835200,
  "Septiembre_2025":835200,
  "Octubre_2025":835200,
  "Noviembre_2025":835200,
  "Diciembre_2025":975062
 },
 {
  "organismo_nombre":"Corporación Municipal de Cultura de TilTil",
  "base":"Codigotrabajo",
  "homologado":"Enseñanza Media",
  "age_label":"50 a 65",
  "sexo":"hombre",
  "Agosto_2018":0,
  "Septiembre_2018":0,
  "Octubre_2018":0,
  "Noviembre_2018":0,
  "Diciembre_2018":0,
  "Enero_2019":0,
  "Febrero_2019":0,
  "Marzo_2019":0,
  "Abril_2019":0,
  "Mayo_2019":0,
  "Junio_2019":0,
  "Julio_2019":0,
  "Agosto_2019":0,
  "Septiembre_2019":0,
  "Octubre_2019":0,
  "Noviembre_2019":0,
  "Diciembre_2019":0,
  "Enero_2020":0,
  "Febrero_2020":0,
  "Marzo_2020":0,
  "Abril_2020":0,
  "Mayo_2020":0,
  "Junio_2020":0,
  "Julio_2020":0,
  "Agosto_2020":0,
  "Septiembre_2020":0,
  "Octubre_2020":0,
  "Noviembre_2020":0,
  "Diciembre_2020":0,
  "Enero_2021":0,
  "Febrero_2021":0,
  "Marzo_2021":0,
  "Abril_2021":0,
  "Mayo_2021":0,
  "Junio_2021":0,
  "Julio_2021":0,
  "Agosto_2021":0,
  "Septiembre_2021":0,
  "Octubre_2021":0,
  "Noviembre_2021":0,
  "Diciembre_2021":0,
  "Enero_2022":0,
  "Febrero_2022":0,
  "Marzo_2022":0,
  "Abril_2022":0,
  "Mayo_2022":0,
  "Junio_2022":0,
  "Julio_2022":0,
  "Agosto_2022":0,
  "Septiembre_2022":0,
  "Octubre_2022":0,
  "Noviembre_2022":0,
  "Diciembre_2022":0,
  "Enero_2023":0,
  "Febrero_2023":0,
  "Marzo_2023":0,
  "Abril_2023":0,
  "Mayo_2023":0,
  "Junio_2023":0,
  "Julio_2023":0,
  "Agosto_2023":0,
  "Septiembre_2023":0,
  "Octubre_2023":0,
  "Noviembre_2023":0,
  "Diciembre_2023":0,
  "Enero_2024":0,
  "Febrero_2024":0,
  "Marzo_2024":0,
  "Abril_2024":0,
  "Mayo_2024":0,
  "Junio_2024":0,
  "Julio_2024":0,
  "Agosto_2024":0,
  "Septiembre_2024":0,
  "Octubre_2024":0,
  "Noviembre_2024":0,
  "Diciembre_2024":0,
  "Enero_2025":0,
  "Febrero_2025":0,
  "Marzo_2025":0,
  "Abril_2025":620000,
  "Mayo_2025":0,
  "Junio_2025":1305000,
  "Julio_2025":1305000,
  "Agosto_2025":1305000,
  "Septiembre_2025":1305000,
  "Octubre_2025":103333,
  "Noviembre_2025":0,
  "Diciembre_2025":0
 },
 {
  "organismo_nombre":"Corporación Municipal de Cultura de TilTil",
  "base":"Codigotrabajo",
  "homologado":"Enseñanza Media",
  "age_label":"50 a 65",
  "sexo":"mujer",
  "Agosto_2018":105000,
  "Septiembre_2018":350000,
  "Octubre_2018":350000,
  "Noviembre_2018":350000,
  "Diciembre_2018":350000,
  "Enero_2019":350000,
  "Febrero_2019":350000,
  "Marzo_2019":350000,
  "Abril_2019":350000,
  "Mayo_2019":350000,
  "Junio_2019":350000,
  "Julio_2019":350000,
  "Agosto_2019":350000,
  "Septiembre_2019":350000,
  "Octubre_2019":350000,
  "Noviembre_2019":350000,
  "Diciembre_2019":350000,
  "Enero_2020":411694,
  "Febrero_2020":411694,
  "Marzo_2020":411694,
  "Abril_2020":411694,
  "Mayo_2020":411694,
  "Junio_2020":411694,
  "Julio_2020":411694,
  "Agosto_2020":411694,
  "Septiembre_2020":411694,
  "Octubre_2020":411694,
  "Noviembre_2020":391106,
  "Diciembre_2020":384252,
  "Enero_2021":411694,
  "Febrero_2021":205815,
  "Marzo_2021":205815,
  "Abril_2021":205815,
  "Mayo_2021":404832,
  "Junio_2021":411694,
  "Julio_2021":411694,
  "Agosto_2021":411694,
  "Septiembre_2021":411694,
  "Octubre_2021":411694,
  "Noviembre_2021":411694,
  "Diciembre_2021":411694,
  "Enero_2022":450000,
  "Febrero_2022":450000,
  "Marzo_2022":450000,
  "Abril_2022":450000,
  "Mayo_2022":450000,
  "Junio_2022":450000,
  "Julio_2022":450000,
  "Agosto_2022":450000,
  "Septiembre_2022":450000,
  "Octubre_2022":450000,
  "Noviembre_2022":427500,
  "Diciembre_2022":450000,
  "Enero_2023":525000,
  "Febrero_2023":525000,
  "Marzo_2023":525000,
  "Abril_2023":525000,
  "Mayo_2023":525000,
  "Junio_2023":525000,
  "Julio_2023":525000,
  "Agosto_2023":525000,
  "Septiembre_2023":525000,
  "Octubre_2023":525000,
  "Noviembre_2023":320833,
  "Diciembre_2023":350000,
  "Enero_2024":550200,
  "Febrero_2024":0,
  "Marzo_2024":550200,
  "Abril_2024":550200,
  "Mayo_2024":550200,
  "Junio_2024":550200,
  "Julio_2024":550200,
  "Agosto_2024":550200,
  "Septiembre_2024":550200,
  "Octubre_2024":0,
  "Noviembre_2024":550200,
  "Diciembre_2024":550200,
  "Enero_2025":550200,
  "Febrero_2025":550200,
  "Marzo_2025":574409,
  "Abril_2025":545538,
  "Mayo_2025":574409,
  "Junio_2025":574409,
  "Julio_2025":574409,
  "Agosto_2025":402086,
  "Septiembre_2025":402086,
  "Octubre_2025":568484,
  "Noviembre_2025":603822,
  "Diciembre_2025":697204
 },
 {
  "organismo_nombre":"Corporación Municipal de Cultura de TilTil",
  "base":"Codigotrabajo",
  "homologado":"Enseñanza Media",
  "age_label":"65 a 85",
  "sexo":"mujer",
  "Agosto_2018":0,
  "Septiembre_2018":0,
  "Octubre_2018":0,
  "Noviembre_2018":0,
  "Diciembre_2018":0,
  "Enero_2019":0,
  "Febrero_2019":0,
  "Marzo_2019":0,
  "Abril_2019":0,
  "Mayo_2019":0,
  "Junio_2019":0,
  "Julio_2019":0,
  "Agosto_2019":0,
  "Septiembre_2019":0,
  "Octubre_2019":0,
  "Noviembre_2019":0,
  "Diciembre_2019":0,
  "Enero_2020":0,
  "Febrero_2020":0,
  "Marzo_2020":0,
  "Abril_2020":0,
  "Mayo_2020":0,
  "Junio_2020":0,
  "Julio_2020":0,
  "Agosto_2020":0,
  "Septiembre_2020":0,
  "Octubre_2020":0,
  "Noviembre_2020":0,
  "Diciembre_2020":0,
  "Enero_2021":0,
  "Febrero_2021":0,
  "Marzo_2021":0,
  "Abril_2021":0,
  "Mayo_2021":0,
  "Junio_2021":0,
  "Julio_2021":0,
  "Agosto_2021":0,
  "Septiembre_2021":0,
  "Octubre_2021":0,
  "Noviembre_2021":0,
  "Diciembre_2021":0,
  "Enero_2022":0,
  "Febrero_2022":0,
  "Marzo_2022":0,
  "Abril_2022":0,
  "Mayo_2022":0,
  "Junio_2022":0,
  "Julio_2022":0,
  "Agosto_2022":0,
  "Septiembre_2022":0,
  "Octubre_2022":0,
  "Noviembre_2022":0,
  "Diciembre_2022":0,
  "Enero_2023":0,
  "Febrero_2023":0,
  "Marzo_2023":0,
  "Abril_2023":0,
  "Mayo_2023":0,
  "Junio_2023":0,
  "Julio_2023":0,
  "Agosto_2023":0,
  "Septiembre_2023":0,
  "Octubre_2023":0,
  "Noviembre_2023":0,
  "Diciembre_2023":0,
  "Enero_2024":0,
  "Febrero_2024":0,
  "Marzo_2024":256760,
  "Abril_2024":400100,
  "Mayo_2024":400100,
  "Junio_2024":400100,
  "Julio_2024":400100,
  "Agosto_2024":400100,
  "Septiembre_2024":400100,
  "Octubre_2024":0,
  "Noviembre_2024":400100,
  "Diciembre_2024":400100,
  "Enero_2025":400100,
  "Febrero_2025":435309,
  "Marzo_2025":417704,
  "Abril_2025":417704,
  "Mayo_2025":620000,
  "Junio_2025":1910834,
  "Julio_2025":1919894,
  "Agosto_2025":1919894,
  "Septiembre_2025":1919894,
  "Octubre_2025":417704,
  "Noviembre_2025":417704,
  "Diciembre_2025":531108
 },
 {
  "organismo_nombre":"Corporación Municipal de Cultura de TilTil",
  "base":"Codigotrabajo",
  "homologado":"Enseñanza Media",
  "age_label":"S\/I",
  "sexo":"mujer",
  "Agosto_2018":0,
  "Septiembre_2018":315000,
  "Octubre_2018":0,
  "Noviembre_2018":0,
  "Diciembre_2018":0,
  "Enero_2019":0,
  "Febrero_2019":0,
  "Marzo_2019":0,
  "Abril_2019":0,
  "Mayo_2019":0,
  "Junio_2019":0,
  "Julio_2019":0,
  "Agosto_2019":0,
  "Septiembre_2019":0,
  "Octubre_2019":0,
  "Noviembre_2019":0,
  "Diciembre_2019":0,
  "Enero_2020":0,
  "Febrero_2020":0,
  "Marzo_2020":0,
  "Abril_2020":0,
  "Mayo_2020":0,
  "Junio_2020":0,
  "Julio_2020":0,
  "Agosto_2020":0,
  "Septiembre_2020":0,
  "Octubre_2020":0,
  "Noviembre_2020":0,
  "Diciembre_2020":0,
  "Enero_2021":0,
  "Febrero_2021":0,
  "Marzo_2021":0,
  "Abril_2021":0,
  "Mayo_2021":0,
  "Junio_2021":0,
  "Julio_2021":0,
  "Agosto_2021":0,
  "Septiembre_2021":0,
  "Octubre_2021":0,
  "Noviembre_2021":0,
  "Diciembre_2021":0,
  "Enero_2022":0,
  "Febrero_2022":0,
  "Marzo_2022":0,
  "Abril_2022":0,
  "Mayo_2022":0,
  "Junio_2022":0,
  "Julio_2022":0,
  "Agosto_2022":0,
  "Septiembre_2022":0,
  "Octubre_2022":0,
  "Noviembre_2022":0,
  "Diciembre_2022":0,
  "Enero_2023":0,
  "Febrero_2023":0,
  "Marzo_2023":0,
  "Abril_2023":0,
  "Mayo_2023":0,
  "Junio_2023":0,
  "Julio_2023":0,
  "Agosto_2023":0,
  "Septiembre_2023":0,
  "Octubre_2023":0,
  "Noviembre_2023":0,
  "Diciembre_2023":0,
  "Enero_2024":0,
  "Febrero_2024":0,
  "Marzo_2024":0,
  "Abril_2024":0,
  "Mayo_2024":0,
  "Junio_2024":0,
  "Julio_2024":0,
  "Agosto_2024":0,
  "Septiembre_2024":0,
  "Octubre_2024":0,
  "Noviembre_2024":0,
  "Diciembre_2024":0,
  "Enero_2025":0,
  "Febrero_2025":0,
  "Marzo_2025":0,
  "Abril_2025":0,
  "Mayo_2025":0,
  "Junio_2025":0,
  "Julio_2025":0,
  "Agosto_2025":0,
  "Septiembre_2025":0,
  "Octubre_2025":0,
  "Noviembre_2025":0,
  "Diciembre_2025":0
 },
 {
  "organismo_nombre":"Corporación Municipal de Cultura de TilTil",
  "base":"Codigotrabajo",
  "homologado":"Profesional",
  "age_label":"18 a 30",
  "sexo":"hombre",
  "Agosto_2018":0,
  "Septiembre_2018":0,
  "Octubre_2018":0,
  "Noviembre_2018":0,
  "Diciembre_2018":0,
  "Enero_2019":0,
  "Febrero_2019":0,
  "Marzo_2019":0,
  "Abril_2019":0,
  "Mayo_2019":0,
  "Junio_2019":0,
  "Julio_2019":0,
  "Agosto_2019":0,
  "Septiembre_2019":0,
  "Octubre_2019":0,
  "Noviembre_2019":0,
  "Diciembre_2019":0,
  "Enero_2020":0,
  "Febrero_2020":0,
  "Marzo_2020":0,
  "Abril_2020":0,
  "Mayo_2020":0,
  "Junio_2020":0,
  "Julio_2020":0,
  "Agosto_2020":0,
  "Septiembre_2020":0,
  "Octubre_2020":0,
  "Noviembre_2020":0,
  "Diciembre_2020":0,
  "Enero_2021":0,
  "Febrero_2021":0,
  "Marzo_2021":0,
  "Abril_2021":0,
  "Mayo_2021":0,
  "Junio_2021":0,
  "Julio_2021":0,
  "Agosto_2021":0,
  "Septiembre_2021":0,
  "Octubre_2021":0,
  "Noviembre_2021":0,
  "Diciembre_2021":0,
  "Enero_2022":0,
  "Febrero_2022":0,
  "Marzo_2022":0,
  "Abril_2022":0,
  "Mayo_2022":0,
  "Junio_2022":0,
  "Julio_2022":0,
  "Agosto_2022":0,
  "Septiembre_2022":0,
  "Octubre_2022":0,
  "Noviembre_2022":0,
  "Diciembre_2022":0,
  "Enero_2023":0,
  "Febrero_2023":0,
  "Marzo_2023":0,
  "Abril_2023":0,
  "Mayo_2023":0,
  "Junio_2023":0,
  "Julio_2023":0,
  "Agosto_2023":0,
  "Septiembre_2023":0,
  "Octubre_2023":0,
  "Noviembre_2023":0,
  "Diciembre_2023":0,
  "Enero_2024":0,
  "Febrero_2024":0,
  "Marzo_2024":0,
  "Abril_2024":0,
  "Mayo_2024":0,
  "Junio_2024":0,
  "Julio_2024":0,
  "Agosto_2024":0,
  "Septiembre_2024":838400,
  "Octubre_2024":0,
  "Noviembre_2024":0,
  "Diciembre_2024":0,
  "Enero_2025":0,
  "Febrero_2025":0,
  "Marzo_2025":0,
  "Abril_2025":0,
  "Mayo_2025":0,
  "Junio_2025":0,
  "Julio_2025":0,
  "Agosto_2025":0,
  "Septiembre_2025":0,
  "Octubre_2025":0,
  "Noviembre_2025":0,
  "Diciembre_2025":0
 },
 {
  "organismo_nombre":"Corporación Municipal de Cultura de TilTil",
  "base":"Codigotrabajo",
  "homologado":"Profesional",
  "age_label":"18 a 30",
  "sexo":"mujer",
  "Agosto_2018":0,
  "Septiembre_2018":0,
  "Octubre_2018":0,
  "Noviembre_2018":0,
  "Diciembre_2018":0,
  "Enero_2019":0,
  "Febrero_2019":0,
  "Marzo_2019":0,
  "Abril_2019":0,
  "Mayo_2019":0,
  "Junio_2019":0,
  "Julio_2019":0,
  "Agosto_2019":0,
  "Septiembre_2019":0,
  "Octubre_2019":0,
  "Noviembre_2019":0,
  "Diciembre_2019":0,
  "Enero_2020":0,
  "Febrero_2020":0,
  "Marzo_2020":0,
  "Abril_2020":0,
  "Mayo_2020":0,
  "Junio_2020":0,
  "Julio_2020":0,
  "Agosto_2020":0,
  "Septiembre_2020":0,
  "Octubre_2020":0,
  "Noviembre_2020":0,
  "Diciembre_2020":0,
  "Enero_2021":0,
  "Febrero_2021":0,
  "Marzo_2021":0,
  "Abril_2021":0,
  "Mayo_2021":0,
  "Junio_2021":0,
  "Julio_2021":0,
  "Agosto_2021":0,
  "Septiembre_2021":0,
  "Octubre_2021":0,
  "Noviembre_2021":0,
  "Diciembre_2021":0,
  "Enero_2022":0,
  "Febrero_2022":0,
  "Marzo_2022":0,
  "Abril_2022":0,
  "Mayo_2022":0,
  "Junio_2022":0,
  "Julio_2022":0,
  "Agosto_2022":0,
  "Septiembre_2022":0,
  "Octubre_2022":0,
  "Noviembre_2022":0,
  "Diciembre_2022":0,
  "Enero_2023":0,
  "Febrero_2023":0,
  "Marzo_2023":0,
  "Abril_2023":0,
  "Mayo_2023":0,
  "Junio_2023":0,
  "Julio_2023":0,
  "Agosto_2023":0,
  "Septiembre_2023":0,
  "Octubre_2023":1250000,
  "Noviembre_2023":1250000,
  "Diciembre_2023":1250000,
  "Enero_2024":0,
  "Febrero_2024":0,
  "Marzo_2024":1250000,
  "Abril_2024":1250000,
  "Mayo_2024":1250000,
  "Junio_2024":1250000,
  "Julio_2024":1250000,
  "Agosto_2024":1250000,
  "Septiembre_2024":1250000,
  "Octubre_2024":0,
  "Noviembre_2024":1250000,
  "Diciembre_2024":1250000,
  "Enero_2025":1500000,
  "Febrero_2025":1500000,
  "Marzo_2025":1500000,
  "Abril_2025":1500000,
  "Mayo_2025":1500000,
  "Junio_2025":1500000,
  "Julio_2025":1500000,
  "Agosto_2025":1500000,
  "Septiembre_2025":1500000,
  "Octubre_2025":1500000,
  "Noviembre_2025":0,
  "Diciembre_2025":0
 },
 {
  "organismo_nombre":"Corporación Municipal de Cultura de TilTil",
  "base":"Codigotrabajo",
  "homologado":"Profesional",
  "age_label":"30 a 50",
  "sexo":"hombre",
  "Agosto_2018":0,
  "Septiembre_2018":0,
  "Octubre_2018":0,
  "Noviembre_2018":0,
  "Diciembre_2018":0,
  "Enero_2019":0,
  "Febrero_2019":0,
  "Marzo_2019":0,
  "Abril_2019":0,
  "Mayo_2019":0,
  "Junio_2019":0,
  "Julio_2019":0,
  "Agosto_2019":0,
  "Septiembre_2019":0,
  "Octubre_2019":0,
  "Noviembre_2019":0,
  "Diciembre_2019":0,
  "Enero_2020":0,
  "Febrero_2020":0,
  "Marzo_2020":0,
  "Abril_2020":0,
  "Mayo_2020":0,
  "Junio_2020":0,
  "Julio_2020":0,
  "Agosto_2020":0,
  "Septiembre_2020":0,
  "Octubre_2020":0,
  "Noviembre_2020":0,
  "Diciembre_2020":0,
  "Enero_2021":0,
  "Febrero_2021":0,
  "Marzo_2021":0,
  "Abril_2021":0,
  "Mayo_2021":0,
  "Junio_2021":0,
  "Julio_2021":0,
  "Agosto_2021":0,
  "Septiembre_2021":0,
  "Octubre_2021":0,
  "Noviembre_2021":0,
  "Diciembre_2021":0,
  "Enero_2022":0,
  "Febrero_2022":0,
  "Marzo_2022":0,
  "Abril_2022":0,
  "Mayo_2022":0,
  "Junio_2022":0,
  "Julio_2022":0,
  "Agosto_2022":0,
  "Septiembre_2022":0,
  "Octubre_2022":0,
  "Noviembre_2022":0,
  "Diciembre_2022":0,
  "Enero_2023":0,
  "Febrero_2023":0,
  "Marzo_2023":0,
  "Abril_2023":0,
  "Mayo_2023":0,
  "Junio_2023":0,
  "Julio_2023":0,
  "Agosto_2023":0,
  "Septiembre_2023":750000,
  "Octubre_2023":750000,
  "Noviembre_2023":750000,
  "Diciembre_2023":750000,
  "Enero_2024":750000,
  "Febrero_2024":0,
  "Marzo_2024":750000,
  "Abril_2024":750000,
  "Mayo_2024":750000,
  "Junio_2024":750000,
  "Julio_2024":1250000,
  "Agosto_2024":1250000,
  "Septiembre_2024":0,
  "Octubre_2024":0,
  "Noviembre_2024":1250000,
  "Diciembre_2024":1250000,
  "Enero_2025":1250000,
  "Febrero_2025":1360000,
  "Marzo_2025":1305000,
  "Abril_2025":1305000,
  "Mayo_2025":1200000,
  "Junio_2025":1200000,
  "Julio_2025":1200000,
  "Agosto_2025":1200000,
  "Septiembre_2025":1200000,
  "Octubre_2025":1305000,
  "Noviembre_2025":1564706,
  "Diciembre_2025":1473513
 },
 {
  "organismo_nombre":"Corporación Municipal de Cultura de TilTil",
  "base":"Codigotrabajo",
  "homologado":"Profesional",
  "age_label":"30 a 50",
  "sexo":"mujer",
  "Agosto_2018":868334,
  "Septiembre_2018":1550000,
  "Octubre_2018":1550000,
  "Noviembre_2018":1550000,
  "Diciembre_2018":1550000,
  "Enero_2019":1550000,
  "Febrero_2019":1550000,
  "Marzo_2019":1550000,
  "Abril_2019":1550000,
  "Mayo_2019":1550000,
  "Junio_2019":1550000,
  "Julio_2019":1550000,
  "Agosto_2019":1550000,
  "Septiembre_2019":1550000,
  "Octubre_2019":1550000,
  "Noviembre_2019":1550000,
  "Diciembre_2019":1550000,
  "Enero_2020":1578367,
  "Febrero_2020":1578367,
  "Marzo_2020":1578367,
  "Abril_2020":1578367,
  "Mayo_2020":1578367,
  "Junio_2020":1578367,
  "Julio_2020":1578367,
  "Agosto_2020":1578367,
  "Septiembre_2020":1578367,
  "Octubre_2020":1578367,
  "Noviembre_2020":1578367,
  "Diciembre_2020":1578367,
  "Enero_2021":1578367,
  "Febrero_2021":1578367,
  "Marzo_2021":1578367,
  "Abril_2021":1578367,
  "Mayo_2021":1578367,
  "Junio_2021":1578367,
  "Julio_2021":1578367,
  "Agosto_2021":1578367,
  "Septiembre_2021":1578367,
  "Octubre_2021":538367,
  "Noviembre_2021":1458367,
  "Diciembre_2021":1578367,
  "Enero_2022":1650000,
  "Febrero_2022":1650000,
  "Marzo_2022":1650000,
  "Abril_2022":1650000,
  "Mayo_2022":1650000,
  "Junio_2022":1650000,
  "Julio_2022":1650000,
  "Agosto_2022":1650000,
  "Septiembre_2022":1650000,
  "Octubre_2022":1650000,
  "Noviembre_2022":1650000,
  "Diciembre_2022":1650000,
  "Enero_2023":1825000,
  "Febrero_2023":1825000,
  "Marzo_2023":1825000,
  "Abril_2023":2000000,
  "Mayo_2023":2000000,
  "Junio_2023":2000000,
  "Julio_2023":2000000,
  "Agosto_2023":2000000,
  "Septiembre_2023":2000000,
  "Octubre_2023":2750000,
  "Noviembre_2023":2750000,
  "Diciembre_2023":2750000,
  "Enero_2024":2160572,
  "Febrero_2024":0,
  "Marzo_2024":3071145,
  "Abril_2024":3071145,
  "Mayo_2024":3071145,
  "Junio_2024":3071145,
  "Julio_2024":3071145,
  "Agosto_2024":3071145,
  "Septiembre_2024":3071145,
  "Octubre_2024":0,
  "Noviembre_2024":3071145,
  "Diciembre_2024":3071145,
  "Enero_2025":3201669,
  "Febrero_2025":3201669,
  "Marzo_2025":3201669,
  "Abril_2025":3201669,
  "Mayo_2025":0,
  "Junio_2025":678600,
  "Julio_2025":678600,
  "Agosto_2025":678600,
  "Septiembre_2025":678600,
  "Octubre_2025":3219788,
  "Noviembre_2025":3283002,
  "Diciembre_2025":3319788
 },
 {
  "organismo_nombre":"Corporación Municipal de Cultura de TilTil",
  "base":"Codigotrabajo",
  "homologado":"Profesional",
  "age_label":"50 a 65",
  "sexo":"hombre",
  "Agosto_2018":0,
  "Septiembre_2018":0,
  "Octubre_2018":0,
  "Noviembre_2018":0,
  "Diciembre_2018":0,
  "Enero_2019":0,
  "Febrero_2019":0,
  "Marzo_2019":0,
  "Abril_2019":0,
  "Mayo_2019":0,
  "Junio_2019":0,
  "Julio_2019":0,
  "Agosto_2019":0,
  "Septiembre_2019":0,
  "Octubre_2019":0,
  "Noviembre_2019":0,
  "Diciembre_2019":0,
  "Enero_2020":0,
  "Febrero_2020":0,
  "Marzo_2020":0,
  "Abril_2020":0,
  "Mayo_2020":0,
  "Junio_2020":0,
  "Julio_2020":0,
  "Agosto_2020":0,
  "Septiembre_2020":0,
  "Octubre_2020":0,
  "Noviembre_2020":0,
  "Diciembre_2020":0,
  "Enero_2021":0,
  "Febrero_2021":0,
  "Marzo_2021":0,
  "Abril_2021":0,
  "Mayo_2021":0,
  "Junio_2021":0,
  "Julio_2021":0,
  "Agosto_2021":0,
  "Septiembre_2021":0,
  "Octubre_2021":0,
  "Noviembre_2021":0,
  "Diciembre_2021":0,
  "Enero_2022":0,
  "Febrero_2022":0,
  "Marzo_2022":0,
  "Abril_2022":0,
  "Mayo_2022":0,
  "Junio_2022":0,
  "Julio_2022":0,
  "Agosto_2022":0,
  "Septiembre_2022":0,
  "Octubre_2022":0,
  "Noviembre_2022":0,
  "Diciembre_2022":0,
  "Enero_2023":0,
  "Febrero_2023":0,
  "Marzo_2023":0,
  "Abril_2023":0,
  "Mayo_2023":0,
  "Junio_2023":0,
  "Julio_2023":0,
  "Agosto_2023":0,
  "Septiembre_2023":0,
  "Octubre_2023":0,
  "Noviembre_2023":0,
  "Diciembre_2023":0,
  "Enero_2024":0,
  "Febrero_2024":0,
  "Marzo_2024":0,
  "Abril_2024":0,
  "Mayo_2024":0,
  "Junio_2024":0,
  "Julio_2024":0,
  "Agosto_2024":0,
  "Septiembre_2024":0,
  "Octubre_2024":0,
  "Noviembre_2024":0,
  "Diciembre_2024":0,
  "Enero_2025":0,
  "Febrero_2025":1200000,
  "Marzo_2025":1200000,
  "Abril_2025":1200000,
  "Mayo_2025":1305000,
  "Junio_2025":875290,
  "Julio_2025":875290,
  "Agosto_2025":875290,
  "Septiembre_2025":875290,
  "Octubre_2025":1200000,
  "Noviembre_2025":1200000,
  "Diciembre_2025":1395455
 },
 {
  "organismo_nombre":"Corporación Municipal de Cultura de TilTil",
  "base":"Codigotrabajo",
  "homologado":"Profesional",
  "age_label":"65 a 85",
  "sexo":"mujer",
  "Agosto_2018":0,
  "Septiembre_2018":0,
  "Octubre_2018":0,
  "Noviembre_2018":0,
  "Diciembre_2018":0,
  "Enero_2019":0,
  "Febrero_2019":0,
  "Marzo_2019":0,
  "Abril_2019":0,
  "Mayo_2019":0,
  "Junio_2019":0,
  "Julio_2019":0,
  "Agosto_2019":0,
  "Septiembre_2019":0,
  "Octubre_2019":0,
  "Noviembre_2019":0,
  "Diciembre_2019":0,
  "Enero_2020":0,
  "Febrero_2020":0,
  "Marzo_2020":0,
  "Abril_2020":0,
  "Mayo_2020":0,
  "Junio_2020":0,
  "Julio_2020":0,
  "Agosto_2020":0,
  "Septiembre_2020":0,
  "Octubre_2020":0,
  "Noviembre_2020":0,
  "Diciembre_2020":0,
  "Enero_2021":0,
  "Febrero_2021":0,
  "Marzo_2021":0,
  "Abril_2021":0,
  "Mayo_2021":0,
  "Junio_2021":0,
  "Julio_2021":0,
  "Agosto_2021":0,
  "Septiembre_2021":0,
  "Octubre_2021":0,
  "Noviembre_2021":0,
  "Diciembre_2021":0,
  "Enero_2022":0,
  "Febrero_2022":0,
  "Marzo_2022":0,
  "Abril_2022":0,
  "Mayo_2022":0,
  "Junio_2022":0,
  "Julio_2022":0,
  "Agosto_2022":0,
  "Septiembre_2022":0,
  "Octubre_2022":0,
  "Noviembre_2022":0,
  "Diciembre_2022":0,
  "Enero_2023":0,
  "Febrero_2023":0,
  "Marzo_2023":0,
  "Abril_2023":0,
  "Mayo_2023":0,
  "Junio_2023":0,
  "Julio_2023":0,
  "Agosto_2023":0,
  "Septiembre_2023":0,
  "Octubre_2023":0,
  "Noviembre_2023":0,
  "Diciembre_2023":0,
  "Enero_2024":0,
  "Febrero_2024":0,
  "Marzo_2024":0,
  "Abril_2024":0,
  "Mayo_2024":0,
  "Junio_2024":0,
  "Julio_2024":0,
  "Agosto_2024":0,
  "Septiembre_2024":0,
  "Octubre_2024":0,
  "Noviembre_2024":0,
  "Diciembre_2024":0,
  "Enero_2025":0,
  "Febrero_2025":0,
  "Marzo_2025":0,
  "Abril_2025":0,
  "Mayo_2025":3201669,
  "Junio_2025":0,
  "Julio_2025":0,
  "Agosto_2025":0,
  "Septiembre_2025":0,
  "Octubre_2025":0,
  "Noviembre_2025":0,
  "Diciembre_2025":0
 },
 {
  "organismo_nombre":"Corporación Municipal de Cultura de TilTil",
  "base":"Codigotrabajo",
  "homologado":"Técnico",
  "age_label":"18 a 30",
  "sexo":"hombre",
  "Agosto_2018":360000,
  "Septiembre_2018":400000,
  "Octubre_2018":400000,
  "Noviembre_2018":400000,
  "Diciembre_2018":400000,
  "Enero_2019":400000,
  "Febrero_2019":400000,
  "Marzo_2019":500000,
  "Abril_2019":500000,
  "Mayo_2019":500000,
  "Junio_2019":500000,
  "Julio_2019":500000,
  "Agosto_2019":500000,
  "Septiembre_2019":500000,
  "Octubre_2019":225000,
  "Noviembre_2019":325000,
  "Diciembre_2019":400000,
  "Enero_2020":400000,
  "Febrero_2020":400000,
  "Marzo_2020":325000,
  "Abril_2020":450000,
  "Mayo_2020":450000,
  "Junio_2020":450000,
  "Julio_2020":450000,
  "Agosto_2020":450000,
  "Septiembre_2020":450000,
  "Octubre_2020":500000,
  "Noviembre_2020":500000,
  "Diciembre_2020":500000,
  "Enero_2021":500000,
  "Febrero_2021":500000,
  "Marzo_2021":500000,
  "Abril_2021":500000,
  "Mayo_2021":500000,
  "Junio_2021":500000,
  "Julio_2021":500000,
  "Agosto_2021":500000,
  "Septiembre_2021":500000,
  "Octubre_2021":383334,
  "Noviembre_2021":500000,
  "Diciembre_2021":500000,
  "Enero_2022":650000,
  "Febrero_2022":650000,
  "Marzo_2022":650000,
  "Abril_2022":650000,
  "Mayo_2022":650000,
  "Junio_2022":650000,
  "Julio_2022":650000,
  "Agosto_2022":650000,
  "Septiembre_2022":650000,
  "Octubre_2022":650000,
  "Noviembre_2022":650000,
  "Diciembre_2022":650000,
  "Enero_2023":800000,
  "Febrero_2023":800000,
  "Marzo_2023":800000,
  "Abril_2023":800000,
  "Mayo_2023":800000,
  "Junio_2023":825000,
  "Julio_2023":825000,
  "Agosto_2023":825000,
  "Septiembre_2023":825000,
  "Octubre_2023":825000,
  "Noviembre_2023":825000,
  "Diciembre_2023":825000,
  "Enero_2024":838400,
  "Febrero_2024":0,
  "Marzo_2024":685979,
  "Abril_2024":907956,
  "Mayo_2024":838400,
  "Junio_2024":670720,
  "Julio_2024":744200,
  "Agosto_2024":744200,
  "Septiembre_2024":1250000,
  "Octubre_2024":0,
  "Noviembre_2024":744200,
  "Diciembre_2024":744200,
  "Enero_2025":744200,
  "Febrero_2025":863949,
  "Marzo_2025":776945,
  "Abril_2025":776945,
  "Mayo_2025":0,
  "Junio_2025":440500,
  "Julio_2025":440500,
  "Agosto_2025":440500,
  "Septiembre_2025":440500,
  "Octubre_2025":776945,
  "Noviembre_2025":783763,
  "Diciembre_2025":1308823
 },
 {
  "organismo_nombre":"Corporación Municipal de Cultura de TilTil",
  "base":"Codigotrabajo",
  "homologado":"Técnico",
  "age_label":"30 a 50",
  "sexo":"hombre",
  "Agosto_2018":0,
  "Septiembre_2018":0,
  "Octubre_2018":0,
  "Noviembre_2018":0,
  "Diciembre_2018":0,
  "Enero_2019":400000,
  "Febrero_2019":400000,
  "Marzo_2019":450000,
  "Abril_2019":450000,
  "Mayo_2019":450000,
  "Junio_2019":450000,
  "Julio_2019":450000,
  "Agosto_2019":450000,
  "Septiembre_2019":450000,
  "Octubre_2019":450000,
  "Noviembre_2019":450000,
  "Diciembre_2019":550000,
  "Enero_2020":500000,
  "Febrero_2020":500000,
  "Marzo_2020":233333,
  "Abril_2020":0,
  "Mayo_2020":0,
  "Junio_2020":0,
  "Julio_2020":0,
  "Agosto_2020":0,
  "Septiembre_2020":0,
  "Octubre_2020":0,
  "Noviembre_2020":0,
  "Diciembre_2020":0,
  "Enero_2021":0,
  "Febrero_2021":0,
  "Marzo_2021":0,
  "Abril_2021":0,
  "Mayo_2021":0,
  "Junio_2021":0,
  "Julio_2021":0,
  "Agosto_2021":0,
  "Septiembre_2021":0,
  "Octubre_2021":0,
  "Noviembre_2021":0,
  "Diciembre_2021":0,
  "Enero_2022":0,
  "Febrero_2022":0,
  "Marzo_2022":0,
  "Abril_2022":0,
  "Mayo_2022":0,
  "Junio_2022":0,
  "Julio_2022":0,
  "Agosto_2022":0,
  "Septiembre_2022":0,
  "Octubre_2022":0,
  "Noviembre_2022":0,
  "Diciembre_2022":0,
  "Enero_2023":0,
  "Febrero_2023":0,
  "Marzo_2023":0,
  "Abril_2023":0,
  "Mayo_2023":0,
  "Junio_2023":0,
  "Julio_2023":0,
  "Agosto_2023":0,
  "Septiembre_2023":0,
  "Octubre_2023":0,
  "Noviembre_2023":0,
  "Diciembre_2023":0,
  "Enero_2024":0,
  "Febrero_2024":0,
  "Marzo_2024":0,
  "Abril_2024":0,
  "Mayo_2024":0,
  "Junio_2024":0,
  "Julio_2024":0,
  "Agosto_2024":0,
  "Septiembre_2024":0,
  "Octubre_2024":0,
  "Noviembre_2024":0,
  "Diciembre_2024":0,
  "Enero_2025":0,
  "Febrero_2025":0,
  "Marzo_2025":0,
  "Abril_2025":0,
  "Mayo_2025":0,
  "Junio_2025":0,
  "Julio_2025":0,
  "Agosto_2025":0,
  "Septiembre_2025":750000,
  "Octubre_2025":750000,
  "Noviembre_2025":750000,
  "Diciembre_2025":888136
 },
 {
  "organismo_nombre":"Corporación Municipal de Cultura de TilTil",
  "base":"Codigotrabajo",
  "homologado":"Técnico",
  "age_label":"30 a 50",
  "sexo":"mujer",
  "Agosto_2018":0,
  "Septiembre_2018":0,
  "Octubre_2018":0,
  "Noviembre_2018":0,
  "Diciembre_2018":0,
  "Enero_2019":0,
  "Febrero_2019":0,
  "Marzo_2019":0,
  "Abril_2019":0,
  "Mayo_2019":0,
  "Junio_2019":0,
  "Julio_2019":0,
  "Agosto_2019":0,
  "Septiembre_2019":0,
  "Octubre_2019":0,
  "Noviembre_2019":0,
  "Diciembre_2019":0,
  "Enero_2020":0,
  "Febrero_2020":0,
  "Marzo_2020":0,
  "Abril_2020":0,
  "Mayo_2020":0,
  "Junio_2020":0,
  "Julio_2020":0,
  "Agosto_2020":0,
  "Septiembre_2020":0,
  "Octubre_2020":0,
  "Noviembre_2020":0,
  "Diciembre_2020":0,
  "Enero_2021":0,
  "Febrero_2021":0,
  "Marzo_2021":0,
  "Abril_2021":0,
  "Mayo_2021":0,
  "Junio_2021":0,
  "Julio_2021":0,
  "Agosto_2021":0,
  "Septiembre_2021":0,
  "Octubre_2021":0,
  "Noviembre_2021":0,
  "Diciembre_2021":0,
  "Enero_2022":0,
  "Febrero_2022":0,
  "Marzo_2022":0,
  "Abril_2022":0,
  "Mayo_2022":0,
  "Junio_2022":0,
  "Julio_2022":0,
  "Agosto_2022":0,
  "Septiembre_2022":0,
  "Octubre_2022":0,
  "Noviembre_2022":0,
  "Diciembre_2022":0,
  "Enero_2023":0,
  "Febrero_2023":0,
  "Marzo_2023":0,
  "Abril_2023":0,
  "Mayo_2023":0,
  "Junio_2023":0,
  "Julio_2023":0,
  "Agosto_2023":0,
  "Septiembre_2023":0,
  "Octubre_2023":0,
  "Noviembre_2023":0,
  "Diciembre_2023":0,
  "Enero_2024":0,
  "Febrero_2024":0,
  "Marzo_2024":0,
  "Abril_2024":0,
  "Mayo_2024":0,
  "Junio_2024":0,
  "Julio_2024":0,
  "Agosto_2024":0,
  "Septiembre_2024":0,
  "Octubre_2024":0,
  "Noviembre_2024":0,
  "Diciembre_2024":0,
  "Enero_2025":0,
  "Febrero_2025":0,
  "Marzo_2025":0,
  "Abril_2025":0,
  "Mayo_2025":678600,
  "Junio_2025":0,
  "Julio_2025":0,
  "Agosto_2025":0,
  "Septiembre_2025":0,
  "Octubre_2025":0,
  "Noviembre_2025":0,
  "Diciembre_2025":0
 },
 {
  "organismo_nombre":"Corporación Municipal de Cultura de TilTil",
  "base":"Codigotrabajo",
  "homologado":"Técnico",
  "age_label":"50 a 65",
  "sexo":"hombre",
  "Agosto_2018":0,
  "Septiembre_2018":0,
  "Octubre_2018":0,
  "Noviembre_2018":0,
  "Diciembre_2018":0,
  "Enero_2019":0,
  "Febrero_2019":0,
  "Marzo_2019":0,
  "Abril_2019":0,
  "Mayo_2019":0,
  "Junio_2019":0,
  "Julio_2019":0,
  "Agosto_2019":0,
  "Septiembre_2019":0,
  "Octubre_2019":0,
  "Noviembre_2019":0,
  "Diciembre_2019":0,
  "Enero_2020":0,
  "Febrero_2020":0,
  "Marzo_2020":0,
  "Abril_2020":0,
  "Mayo_2020":0,
  "Junio_2020":0,
  "Julio_2020":0,
  "Agosto_2020":0,
  "Septiembre_2020":0,
  "Octubre_2020":0,
  "Noviembre_2020":0,
  "Diciembre_2020":0,
  "Enero_2021":0,
  "Febrero_2021":0,
  "Marzo_2021":0,
  "Abril_2021":0,
  "Mayo_2021":0,
  "Junio_2021":0,
  "Julio_2021":0,
  "Agosto_2021":0,
  "Septiembre_2021":0,
  "Octubre_2021":0,
  "Noviembre_2021":0,
  "Diciembre_2021":0,
  "Enero_2022":0,
  "Febrero_2022":0,
  "Marzo_2022":0,
  "Abril_2022":0,
  "Mayo_2022":0,
  "Junio_2022":0,
  "Julio_2022":0,
  "Agosto_2022":0,
  "Septiembre_2022":0,
  "Octubre_2022":0,
  "Noviembre_2022":0,
  "Diciembre_2022":0,
  "Enero_2023":0,
  "Febrero_2023":0,
  "Marzo_2023":0,
  "Abril_2023":0,
  "Mayo_2023":0,
  "Junio_2023":0,
  "Julio_2023":0,
  "Agosto_2023":0,
  "Septiembre_2023":0,
  "Octubre_2023":0,
  "Noviembre_2023":0,
  "Diciembre_2023":0,
  "Enero_2024":0,
  "Febrero_2024":0,
  "Marzo_2024":0,
  "Abril_2024":0,
  "Mayo_2024":0,
  "Junio_2024":0,
  "Julio_2024":0,
  "Agosto_2024":0,
  "Septiembre_2024":0,
  "Octubre_2024":0,
  "Noviembre_2024":0,
  "Diciembre_2024":0,
  "Enero_2025":0,
  "Febrero_2025":0,
  "Marzo_2025":0,
  "Abril_2025":0,
  "Mayo_2025":875290,
  "Junio_2025":0,
  "Julio_2025":0,
  "Agosto_2025":0,
  "Septiembre_2025":0,
  "Octubre_2025":0,
  "Noviembre_2025":0,
  "Diciembre_2025":0
 },
 {
  "organismo_nombre":"Corporación Municipal de Cultura de TilTil",
  "base":"Codigotrabajo",
  "homologado":"Técnico",
  "age_label":"50 a 65",
  "sexo":"mujer",
  "Agosto_2018":0,
  "Septiembre_2018":0,
  "Octubre_2018":0,
  "Noviembre_2018":0,
  "Diciembre_2018":0,
  "Enero_2019":0,
  "Febrero_2019":0,
  "Marzo_2019":0,
  "Abril_2019":0,
  "Mayo_2019":0,
  "Junio_2019":0,
  "Julio_2019":0,
  "Agosto_2019":0,
  "Septiembre_2019":0,
  "Octubre_2019":0,
  "Noviembre_2019":0,
  "Diciembre_2019":0,
  "Enero_2020":0,
  "Febrero_2020":0,
  "Marzo_2020":0,
  "Abril_2020":0,
  "Mayo_2020":0,
  "Junio_2020":0,
  "Julio_2020":0,
  "Agosto_2020":0,
  "Septiembre_2020":0,
  "Octubre_2020":0,
  "Noviembre_2020":0,
  "Diciembre_2020":0,
  "Enero_2021":0,
  "Febrero_2021":0,
  "Marzo_2021":0,
  "Abril_2021":0,
  "Mayo_2021":0,
  "Junio_2021":0,
  "Julio_2021":0,
  "Agosto_2021":0,
  "Septiembre_2021":0,
  "Octubre_2021":0,
  "Noviembre_2021":0,
  "Diciembre_2021":0,
  "Enero_2022":0,
  "Febrero_2022":0,
  "Marzo_2022":0,
  "Abril_2022":0,
  "Mayo_2022":0,
  "Junio_2022":0,
  "Julio_2022":0,
  "Agosto_2022":0,
  "Septiembre_2022":0,
  "Octubre_2022":0,
  "Noviembre_2022":0,
  "Diciembre_2022":0,
  "Enero_2023":0,
  "Febrero_2023":0,
  "Marzo_2023":0,
  "Abril_2023":0,
  "Mayo_2023":0,
  "Junio_2023":0,
  "Julio_2023":0,
  "Agosto_2023":0,
  "Septiembre_2023":0,
  "Octubre_2023":0,
  "Noviembre_2023":0,
  "Diciembre_2023":0,
  "Enero_2024":0,
  "Febrero_2024":0,
  "Marzo_2024":0,
  "Abril_2024":0,
  "Mayo_2024":0,
  "Junio_2024":0,
  "Julio_2024":0,
  "Agosto_2024":0,
  "Septiembre_2024":0,
  "Octubre_2024":0,
  "Noviembre_2024":0,
  "Diciembre_2024":0,
  "Enero_2025":580000,
  "Febrero_2025":580000,
  "Marzo_2025":605520,
  "Abril_2025":605520,
  "Mayo_2025":678600,
  "Junio_2025":678600,
  "Julio_2025":678600,
  "Agosto_2025":678600,
  "Septiembre_2025":678600,
  "Octubre_2025":588120,
  "Noviembre_2025":171845,
  "Diciembre_2025":810988
 },
 {
  "organismo_nombre":"Corporación Municipal de Cultura de TilTil",
  "base":"Contratohonorarios",
  "homologado":"Artes Musicales",
  "age_label":"18 a 30",
  "sexo":"hombre",
  "Agosto_2018":0,
  "Septiembre_2018":0,
  "Octubre_2018":0,
  "Noviembre_2018":0,
  "Diciembre_2018":0,
  "Enero_2019":0,
  "Febrero_2019":0,
  "Marzo_2019":0,
  "Abril_2019":0,
  "Mayo_2019":0,
  "Junio_2019":0,
  "Julio_2019":0,
  "Agosto_2019":0,
  "Septiembre_2019":0,
  "Octubre_2019":0,
  "Noviembre_2019":0,
  "Diciembre_2019":0,
  "Enero_2020":0,
  "Febrero_2020":0,
  "Marzo_2020":0,
  "Abril_2020":0,
  "Mayo_2020":0,
  "Junio_2020":0,
  "Julio_2020":0,
  "Agosto_2020":0,
  "Septiembre_2020":0,
  "Octubre_2020":0,
  "Noviembre_2020":0,
  "Diciembre_2020":0,
  "Enero_2021":0,
  "Febrero_2021":0,
  "Marzo_2021":0,
  "Abril_2021":0,
  "Mayo_2021":0,
  "Junio_2021":0,
  "Julio_2021":0,
  "Agosto_2021":0,
  "Septiembre_2021":0,
  "Octubre_2021":0,
  "Noviembre_2021":0,
  "Diciembre_2021":0,
  "Enero_2022":0,
  "Febrero_2022":0,
  "Marzo_2022":0,
  "Abril_2022":0,
  "Mayo_2022":0,
  "Junio_2022":0,
  "Julio_2022":0,
  "Agosto_2022":0,
  "Septiembre_2022":0,
  "Octubre_2022":0,
  "Noviembre_2022":0,
  "Diciembre_2022":0,
  "Enero_2023":0,
  "Febrero_2023":0,
  "Marzo_2023":0,
  "Abril_2023":0,
  "Mayo_2023":0,
  "Junio_2023":0,
  "Julio_2023":0,
  "Agosto_2023":66666,
  "Septiembre_2023":0,
  "Octubre_2023":0,
  "Noviembre_2023":0,
  "Diciembre_2023":0,
  "Enero_2024":0,
  "Febrero_2024":0,
  "Marzo_2024":0,
  "Abril_2024":0,
  "Mayo_2024":0,
  "Junio_2024":0,
  "Julio_2024":0,
  "Agosto_2024":0,
  "Septiembre_2024":0,
  "Octubre_2024":0,
  "Noviembre_2024":0,
  "Diciembre_2024":0,
  "Enero_2025":0,
  "Febrero_2025":0,
  "Marzo_2025":0,
  "Abril_2025":0,
  "Mayo_2025":0,
  "Junio_2025":0,
  "Julio_2025":0,
  "Agosto_2025":0,
  "Septiembre_2025":0,
  "Octubre_2025":0,
  "Noviembre_2025":0,
  "Diciembre_2025":0
 },
 {
  "organismo_nombre":"Corporación Municipal de Cultura de TilTil",
  "base":"Contratohonorarios",
  "homologado":"Artes Musicales",
  "age_label":"30 a 50",
  "sexo":"hombre",
  "Agosto_2018":0,
  "Septiembre_2018":0,
  "Octubre_2018":0,
  "Noviembre_2018":0,
  "Diciembre_2018":0,
  "Enero_2019":0,
  "Febrero_2019":0,
  "Marzo_2019":0,
  "Abril_2019":0,
  "Mayo_2019":0,
  "Junio_2019":0,
  "Julio_2019":0,
  "Agosto_2019":0,
  "Septiembre_2019":0,
  "Octubre_2019":0,
  "Noviembre_2019":0,
  "Diciembre_2019":0,
  "Enero_2020":0,
  "Febrero_2020":0,
  "Marzo_2020":0,
  "Abril_2020":0,
  "Mayo_2020":0,
  "Junio_2020":0,
  "Julio_2020":0,
  "Agosto_2020":0,
  "Septiembre_2020":0,
  "Octubre_2020":0,
  "Noviembre_2020":0,
  "Diciembre_2020":0,
  "Enero_2021":0,
  "Febrero_2021":0,
  "Marzo_2021":0,
  "Abril_2021":0,
  "Mayo_2021":0,
  "Junio_2021":0,
  "Julio_2021":0,
  "Agosto_2021":0,
  "Septiembre_2021":0,
  "Octubre_2021":0,
  "Noviembre_2021":0,
  "Diciembre_2021":0,
  "Enero_2022":0,
  "Febrero_2022":0,
  "Marzo_2022":0,
  "Abril_2022":0,
  "Mayo_2022":0,
  "Junio_2022":0,
  "Julio_2022":0,
  "Agosto_2022":0,
  "Septiembre_2022":0,
  "Octubre_2022":0,
  "Noviembre_2022":0,
  "Diciembre_2022":0,
  "Enero_2023":0,
  "Febrero_2023":100000,
  "Marzo_2023":0,
  "Abril_2023":0,
  "Mayo_2023":0,
  "Junio_2023":0,
  "Julio_2023":0,
  "Agosto_2023":0,
  "Septiembre_2023":0,
  "Octubre_2023":0,
  "Noviembre_2023":0,
  "Diciembre_2023":0,
  "Enero_2024":0,
  "Febrero_2024":0,
  "Marzo_2024":0,
  "Abril_2024":0,
  "Mayo_2024":0,
  "Junio_2024":0,
  "Julio_2024":0,
  "Agosto_2024":0,
  "Septiembre_2024":0,
  "Octubre_2024":0,
  "Noviembre_2024":0,
  "Diciembre_2024":0,
  "Enero_2025":0,
  "Febrero_2025":0,
  "Marzo_2025":0,
  "Abril_2025":0,
  "Mayo_2025":0,
  "Junio_2025":0,
  "Julio_2025":0,
  "Agosto_2025":0,
  "Septiembre_2025":0,
  "Octubre_2025":0,
  "Noviembre_2025":0,
  "Diciembre_2025":0
 },
 {
  "organismo_nombre":"Corporación Municipal de Cultura de TilTil",
  "base":"Contratohonorarios",
  "homologado":"Ingeniero(a)",
  "age_label":"30 a 50",
  "sexo":"hombre",
  "Agosto_2018":0,
  "Septiembre_2018":0,
  "Octubre_2018":0,
  "Noviembre_2018":0,
  "Diciembre_2018":0,
  "Enero_2019":0,
  "Febrero_2019":0,
  "Marzo_2019":0,
  "Abril_2019":0,
  "Mayo_2019":0,
  "Junio_2019":0,
  "Julio_2019":0,
  "Agosto_2019":0,
  "Septiembre_2019":0,
  "Octubre_2019":0,
  "Noviembre_2019":0,
  "Diciembre_2019":0,
  "Enero_2020":0,
  "Febrero_2020":0,
  "Marzo_2020":0,
  "Abril_2020":0,
  "Mayo_2020":0,
  "Junio_2020":0,
  "Julio_2020":0,
  "Agosto_2020":0,
  "Septiembre_2020":0,
  "Octubre_2020":0,
  "Noviembre_2020":0,
  "Diciembre_2020":0,
  "Enero_2021":0,
  "Febrero_2021":0,
  "Marzo_2021":0,
  "Abril_2021":0,
  "Mayo_2021":0,
  "Junio_2021":0,
  "Julio_2021":0,
  "Agosto_2021":0,
  "Septiembre_2021":0,
  "Octubre_2021":0,
  "Noviembre_2021":0,
  "Diciembre_2021":0,
  "Enero_2022":0,
  "Febrero_2022":0,
  "Marzo_2022":0,
  "Abril_2022":0,
  "Mayo_2022":0,
  "Junio_2022":0,
  "Julio_2022":0,
  "Agosto_2022":0,
  "Septiembre_2022":0,
  "Octubre_2022":0,
  "Noviembre_2022":0,
  "Diciembre_2022":0,
  "Enero_2023":0,
  "Febrero_2023":115230,
  "Marzo_2023":0,
  "Abril_2023":0,
  "Mayo_2023":0,
  "Junio_2023":0,
  "Julio_2023":0,
  "Agosto_2023":0,
  "Septiembre_2023":0,
  "Octubre_2023":0,
  "Noviembre_2023":0,
  "Diciembre_2023":0,
  "Enero_2024":0,
  "Febrero_2024":0,
  "Marzo_2024":0,
  "Abril_2024":0,
  "Mayo_2024":0,
  "Junio_2024":0,
  "Julio_2024":0,
  "Agosto_2024":0,
  "Septiembre_2024":0,
  "Octubre_2024":0,
  "Noviembre_2024":0,
  "Diciembre_2024":0,
  "Enero_2025":0,
  "Febrero_2025":0,
  "Marzo_2025":0,
  "Abril_2025":0,
  "Mayo_2025":0,
  "Junio_2025":0,
  "Julio_2025":0,
  "Agosto_2025":0,
  "Septiembre_2025":0,
  "Octubre_2025":0,
  "Noviembre_2025":0,
  "Diciembre_2025":0
 },
 {
  "organismo_nombre":"Corporación Municipal de Cultura de TilTil",
  "base":"Contratohonorarios",
  "homologado":"Profesional",
  "age_label":"50 a 65",
  "sexo":"mujer",
  "Agosto_2018":0,
  "Septiembre_2018":0,
  "Octubre_2018":0,
  "Noviembre_2018":0,
  "Diciembre_2018":0,
  "Enero_2019":0,
  "Febrero_2019":0,
  "Marzo_2019":0,
  "Abril_2019":0,
  "Mayo_2019":0,
  "Junio_2019":0,
  "Julio_2019":0,
  "Agosto_2019":0,
  "Septiembre_2019":0,
  "Octubre_2019":0,
  "Noviembre_2019":0,
  "Diciembre_2019":0,
  "Enero_2020":0,
  "Febrero_2020":0,
  "Marzo_2020":0,
  "Abril_2020":0,
  "Mayo_2020":0,
  "Junio_2020":0,
  "Julio_2020":0,
  "Agosto_2020":0,
  "Septiembre_2020":0,
  "Octubre_2020":0,
  "Noviembre_2020":0,
  "Diciembre_2020":0,
  "Enero_2021":0,
  "Febrero_2021":0,
  "Marzo_2021":0,
  "Abril_2021":0,
  "Mayo_2021":0,
  "Junio_2021":0,
  "Julio_2021":0,
  "Agosto_2021":0,
  "Septiembre_2021":0,
  "Octubre_2021":0,
  "Noviembre_2021":0,
  "Diciembre_2021":0,
  "Enero_2022":0,
  "Febrero_2022":0,
  "Marzo_2022":0,
  "Abril_2022":0,
  "Mayo_2022":0,
  "Junio_2022":0,
  "Julio_2022":0,
  "Agosto_2022":0,
  "Septiembre_2022":0,
  "Octubre_2022":0,
  "Noviembre_2022":0,
  "Diciembre_2022":0,
  "Enero_2023":13000,
  "Febrero_2023":0,
  "Marzo_2023":0,
  "Abril_2023":0,
  "Mayo_2023":0,
  "Junio_2023":0,
  "Julio_2023":0,
  "Agosto_2023":0,
  "Septiembre_2023":0,
  "Octubre_2023":0,
  "Noviembre_2023":0,
  "Diciembre_2023":0,
  "Enero_2024":0,
  "Febrero_2024":0,
  "Marzo_2024":0,
  "Abril_2024":0,
  "Mayo_2024":0,
  "Junio_2024":0,
  "Julio_2024":0,
  "Agosto_2024":0,
  "Septiembre_2024":0,
  "Octubre_2024":0,
  "Noviembre_2024":0,
  "Diciembre_2024":0,
  "Enero_2025":0,
  "Febrero_2025":0,
  "Marzo_2025":0,
  "Abril_2025":0,
  "Mayo_2025":0,
  "Junio_2025":0,
  "Julio_2025":0,
  "Agosto_2025":0,
  "Septiembre_2025":0,
  "Octubre_2025":0,
  "Noviembre_2025":0,
  "Diciembre_2025":0
 },
 {
  "organismo_nombre":"Corporación Municipal de Cultura de TilTil",
  "base":"Contratohonorarios",
  "homologado":"Psicólogo(a)",
  "age_label":"S\/I",
  "sexo":"hombre",
  "Agosto_2018":0,
  "Septiembre_2018":0,
  "Octubre_2018":0,
  "Noviembre_2018":0,
  "Diciembre_2018":0,
  "Enero_2019":0,
  "Febrero_2019":0,
  "Marzo_2019":0,
  "Abril_2019":0,
  "Mayo_2019":0,
  "Junio_2019":0,
  "Julio_2019":0,
  "Agosto_2019":0,
  "Septiembre_2019":0,
  "Octubre_2019":0,
  "Noviembre_2019":0,
  "Diciembre_2019":0,
  "Enero_2020":0,
  "Febrero_2020":0,
  "Marzo_2020":0,
  "Abril_2020":0,
  "Mayo_2020":0,
  "Junio_2020":0,
  "Julio_2020":0,
  "Agosto_2020":0,
  "Septiembre_2020":0,
  "Octubre_2020":0,
  "Noviembre_2020":0,
  "Diciembre_2020":0,
  "Enero_2021":0,
  "Febrero_2021":0,
  "Marzo_2021":0,
  "Abril_2021":0,
  "Mayo_2021":0,
  "Junio_2021":0,
  "Julio_2021":0,
  "Agosto_2021":0,
  "Septiembre_2021":0,
  "Octubre_2021":0,
  "Noviembre_2021":0,
  "Diciembre_2021":0,
  "Enero_2022":0,
  "Febrero_2022":0,
  "Marzo_2022":0,
  "Abril_2022":0,
  "Mayo_2022":0,
  "Junio_2022":0,
  "Julio_2022":0,
  "Agosto_2022":0,
  "Septiembre_2022":0,
  "Octubre_2022":0,
  "Noviembre_2022":0,
  "Diciembre_2022":0,
  "Enero_2023":0,
  "Febrero_2023":0,
  "Marzo_2023":0,
  "Abril_2023":0,
  "Mayo_2023":0,
  "Junio_2023":0,
  "Julio_2023":0,
  "Agosto_2023":266664,
  "Septiembre_2023":0,
  "Octubre_2023":0,
  "Noviembre_2023":0,
  "Diciembre_2023":0,
  "Enero_2024":0,
  "Febrero_2024":0,
  "Marzo_2024":0,
  "Abril_2024":0,
  "Mayo_2024":0,
  "Junio_2024":0,
  "Julio_2024":0,
  "Agosto_2024":0,
  "Septiembre_2024":0,
  "Octubre_2024":0,
  "Noviembre_2024":0,
  "Diciembre_2024":0,
  "Enero_2025":0,
  "Febrero_2025":0,
  "Marzo_2025":0,
  "Abril_2025":0,
  "Mayo_2025":0,
  "Junio_2025":0,
  "Julio_2025":0,
  "Agosto_2025":0,
  "Septiembre_2025":0,
  "Octubre_2025":0,
  "Noviembre_2025":0,
  "Diciembre_2025":0
 },
 {
  "organismo_nombre":"Corporación Municipal de Cultura de TilTil",
  "base":"Contratohonorarios",
  "homologado":"Sin Clasificar",
  "age_label":"18 a 30",
  "sexo":"hombre",
  "Agosto_2018":0,
  "Septiembre_2018":0,
  "Octubre_2018":0,
  "Noviembre_2018":0,
  "Diciembre_2018":250000,
  "Enero_2019":250000,
  "Febrero_2019":250000,
  "Marzo_2019":250000,
  "Abril_2019":250000,
  "Mayo_2019":250000,
  "Junio_2019":250000,
  "Julio_2019":250000,
  "Agosto_2019":180556,
  "Septiembre_2019":250000,
  "Octubre_2019":180556,
  "Noviembre_2019":111111,
  "Diciembre_2019":111111,
  "Enero_2020":180556,
  "Febrero_2020":180556,
  "Marzo_2020":250000,
  "Abril_2020":250000,
  "Mayo_2020":250000,
  "Junio_2020":250000,
  "Julio_2020":15951,
  "Agosto_2020":181000,
  "Septiembre_2020":158000,
  "Octubre_2020":143076,
  "Noviembre_2020":181000,
  "Diciembre_2020":158000,
  "Enero_2021":181000,
  "Febrero_2021":250000,
  "Marzo_2021":346655,
  "Abril_2021":250000,
  "Mayo_2021":181000,
  "Junio_2021":195000,
  "Julio_2021":250000,
  "Agosto_2021":234423,
  "Septiembre_2021":162000,
  "Octubre_2021":179198,
  "Noviembre_2021":331111,
  "Diciembre_2021":194039,
  "Enero_2022":433333,
  "Febrero_2022":600000,
  "Marzo_2022":600000,
  "Abril_2022":245223,
  "Mayo_2022":146667,
  "Junio_2022":146667,
  "Julio_2022":146667,
  "Agosto_2022":50000,
  "Septiembre_2022":83571,
  "Octubre_2022":0,
  "Noviembre_2022":25000,
  "Diciembre_2022":131054,
  "Enero_2023":900000,
  "Febrero_2023":172414,
  "Marzo_2023":51724,
  "Abril_2023":0,
  "Mayo_2023":75000,
  "Junio_2023":0,
  "Julio_2023":0,
  "Agosto_2023":193332,
  "Septiembre_2023":57471,
  "Octubre_2023":0,
  "Noviembre_2023":0,
  "Diciembre_2023":57471,
  "Enero_2024":600000,
  "Febrero_2024":0,
  "Marzo_2024":0,
  "Abril_2024":0,
  "Mayo_2024":600000,
  "Junio_2024":419324,
  "Julio_2024":0,
  "Agosto_2024":0,
  "Septiembre_2024":0,
  "Octubre_2024":106246,
  "Noviembre_2024":231884,
  "Diciembre_2024":52174,
  "Enero_2025":0,
  "Febrero_2025":0,
  "Marzo_2025":0,
  "Abril_2025":191815,
  "Mayo_2025":150000,
  "Junio_2025":200000,
  "Julio_2025":200000,
  "Agosto_2025":200000,
  "Septiembre_2025":150000,
  "Octubre_2025":158480,
  "Noviembre_2025":200000,
  "Diciembre_2025":350000
 },
 {
  "organismo_nombre":"Corporación Municipal de Cultura de TilTil",
  "base":"Contratohonorarios",
  "homologado":"Sin Clasificar",
  "age_label":"18 a 30",
  "sexo":"mujer",
  "Agosto_2018":0,
  "Septiembre_2018":0,
  "Octubre_2018":0,
  "Noviembre_2018":0,
  "Diciembre_2018":0,
  "Enero_2019":0,
  "Febrero_2019":0,
  "Marzo_2019":0,
  "Abril_2019":200000,
  "Mayo_2019":133333,
  "Junio_2019":138889,
  "Julio_2019":88889,
  "Agosto_2019":144444,
  "Septiembre_2019":144444,
  "Octubre_2019":167222,
  "Noviembre_2019":177778,
  "Diciembre_2019":225000,
  "Enero_2020":0,
  "Febrero_2020":0,
  "Marzo_2020":0,
  "Abril_2020":0,
  "Mayo_2020":0,
  "Junio_2020":0,
  "Julio_2020":0,
  "Agosto_2020":0,
  "Septiembre_2020":0,
  "Octubre_2020":0,
  "Noviembre_2020":0,
  "Diciembre_2020":0,
  "Enero_2021":0,
  "Febrero_2021":0,
  "Marzo_2021":0,
  "Abril_2021":0,
  "Mayo_2021":0,
  "Junio_2021":0,
  "Julio_2021":56497,
  "Agosto_2021":134746,
  "Septiembre_2021":169492,
  "Octubre_2021":169492,
  "Noviembre_2021":186442,
  "Diciembre_2021":186442,
  "Enero_2022":153846,
  "Febrero_2022":170940,
  "Marzo_2022":170940,
  "Abril_2022":60000,
  "Mayo_2022":61396,
  "Junio_2022":61396,
  "Julio_2022":65698,
  "Agosto_2022":35000,
  "Septiembre_2022":74074,
  "Octubre_2022":0,
  "Noviembre_2022":0,
  "Diciembre_2022":0,
  "Enero_2023":0,
  "Febrero_2023":0,
  "Marzo_2023":159544,
  "Abril_2023":0,
  "Mayo_2023":0,
  "Junio_2023":0,
  "Julio_2023":0,
  "Agosto_2023":0,
  "Septiembre_2023":0,
  "Octubre_2023":160920,
  "Noviembre_2023":160920,
  "Diciembre_2023":201150,
  "Enero_2024":81159,
  "Febrero_2024":0,
  "Marzo_2024":151786,
  "Abril_2024":0,
  "Mayo_2024":0,
  "Junio_2024":0,
  "Julio_2024":0,
  "Agosto_2024":0,
  "Septiembre_2024":92745,
  "Octubre_2024":0,
  "Noviembre_2024":0,
  "Diciembre_2024":0,
  "Enero_2025":0,
  "Febrero_2025":350876,
  "Marzo_2025":0,
  "Abril_2025":375000,
  "Mayo_2025":375000,
  "Junio_2025":225000,
  "Julio_2025":300000,
  "Agosto_2025":300000,
  "Septiembre_2025":225000,
  "Octubre_2025":300000,
  "Noviembre_2025":3000000,
  "Diciembre_2025":500000
 },
 {
  "organismo_nombre":"Corporación Municipal de Cultura de TilTil",
  "base":"Contratohonorarios",
  "homologado":"Sin Clasificar",
  "age_label":"30 a 50",
  "sexo":"desconocido",
  "Agosto_2018":0,
  "Septiembre_2018":0,
  "Octubre_2018":0,
  "Noviembre_2018":0,
  "Diciembre_2018":0,
  "Enero_2019":0,
  "Febrero_2019":0,
  "Marzo_2019":0,
  "Abril_2019":0,
  "Mayo_2019":0,
  "Junio_2019":0,
  "Julio_2019":0,
  "Agosto_2019":0,
  "Septiembre_2019":0,
  "Octubre_2019":0,
  "Noviembre_2019":0,
  "Diciembre_2019":0,
  "Enero_2020":0,
  "Febrero_2020":0,
  "Marzo_2020":0,
  "Abril_2020":0,
  "Mayo_2020":0,
  "Junio_2020":0,
  "Julio_2020":0,
  "Agosto_2020":0,
  "Septiembre_2020":0,
  "Octubre_2020":0,
  "Noviembre_2020":0,
  "Diciembre_2020":0,
  "Enero_2021":0,
  "Febrero_2021":0,
  "Marzo_2021":0,
  "Abril_2021":0,
  "Mayo_2021":0,
  "Junio_2021":0,
  "Julio_2021":0,
  "Agosto_2021":0,
  "Septiembre_2021":0,
  "Octubre_2021":0,
  "Noviembre_2021":0,
  "Diciembre_2021":0,
  "Enero_2022":0,
  "Febrero_2022":0,
  "Marzo_2022":85470,
  "Abril_2022":0,
  "Mayo_2022":0,
  "Junio_2022":0,
  "Julio_2022":0,
  "Agosto_2022":0,
  "Septiembre_2022":0,
  "Octubre_2022":0,
  "Noviembre_2022":0,
  "Diciembre_2022":0,
  "Enero_2023":0,
  "Febrero_2023":0,
  "Marzo_2023":0,
  "Abril_2023":0,
  "Mayo_2023":0,
  "Junio_2023":0,
  "Julio_2023":225000,
  "Agosto_2023":500000,
  "Septiembre_2023":0,
  "Octubre_2023":0,
  "Noviembre_2023":0,
  "Diciembre_2023":0,
  "Enero_2024":0,
  "Febrero_2024":0,
  "Marzo_2024":0,
  "Abril_2024":0,
  "Mayo_2024":0,
  "Junio_2024":0,
  "Julio_2024":0,
  "Agosto_2024":500000,
  "Septiembre_2024":0,
  "Octubre_2024":0,
  "Noviembre_2024":0,
  "Diciembre_2024":0,
  "Enero_2025":0,
  "Febrero_2025":0,
  "Marzo_2025":0,
  "Abril_2025":0,
  "Mayo_2025":0,
  "Junio_2025":0,
  "Julio_2025":0,
  "Agosto_2025":0,
  "Septiembre_2025":0,
  "Octubre_2025":0,
  "Noviembre_2025":0,
  "Diciembre_2025":0
 },
 {
  "organismo_nombre":"Corporación Municipal de Cultura de TilTil",
  "base":"Contratohonorarios",
  "homologado":"Sin Clasificar",
  "age_label":"30 a 50",
  "sexo":"hombre",
  "Agosto_2018":0,
  "Septiembre_2018":0,
  "Octubre_2018":0,
  "Noviembre_2018":0,
  "Diciembre_2018":0,
  "Enero_2019":222222,
  "Febrero_2019":222222,
  "Marzo_2019":0,
  "Abril_2019":222222,
  "Mayo_2019":188444,
  "Junio_2019":180000,
  "Julio_2019":180000,
  "Agosto_2019":180000,
  "Septiembre_2019":180000,
  "Octubre_2019":180000,
  "Noviembre_2019":190556,
  "Diciembre_2019":179762,
  "Enero_2020":316666,
  "Febrero_2020":1110000,
  "Marzo_2020":112000,
  "Abril_2020":80000,
  "Mayo_2020":0,
  "Junio_2020":0,
  "Julio_2020":19350,
  "Agosto_2020":112045,
  "Septiembre_2020":180000,
  "Octubre_2020":180000,
  "Noviembre_2020":134680,
  "Diciembre_2020":164511,
  "Enero_2021":246916,
  "Febrero_2021":0,
  "Marzo_2021":229685,
  "Abril_2021":135593,
  "Mayo_2021":180000,
  "Junio_2021":131500,
  "Julio_2021":158286,
  "Agosto_2021":190395,
  "Septiembre_2021":206429,
  "Octubre_2021":195844,
  "Noviembre_2021":126955,
  "Diciembre_2021":120289,
  "Enero_2022":227778,
  "Febrero_2022":233333,
  "Marzo_2022":150854,
  "Abril_2022":178063,
  "Mayo_2022":128167,
  "Junio_2022":131008,
  "Julio_2022":144311,
  "Agosto_2022":82602,
  "Septiembre_2022":94017,
  "Octubre_2022":146154,
  "Noviembre_2022":113960,
  "Diciembre_2022":284769,
  "Enero_2023":264368,
  "Febrero_2023":158477,
  "Marzo_2023":153219,
  "Abril_2023":57471,
  "Mayo_2023":57471,
  "Junio_2023":72797,
  "Julio_2023":852490,
  "Agosto_2023":200695,
  "Septiembre_2023":823000,
  "Octubre_2023":265000,
  "Noviembre_2023":57471,
  "Diciembre_2023":258621,
  "Enero_2024":84000,
  "Febrero_2024":63768,
  "Marzo_2024":0,
  "Abril_2024":342935,
  "Mayo_2024":57971,
  "Junio_2024":57971,
  "Julio_2024":0,
  "Agosto_2024":280698,
  "Septiembre_2024":78086,
  "Octubre_2024":57971,
  "Noviembre_2024":173913,
  "Diciembre_2024":122251,
  "Enero_2025":52632,
  "Febrero_2025":216376,
  "Marzo_2025":267150,
  "Abril_2025":492680,
  "Mayo_2025":409542,
  "Junio_2025":329132,
  "Julio_2025":166277,
  "Agosto_2025":325000,
  "Septiembre_2025":287500,
  "Octubre_2025":170080,
  "Noviembre_2025":533852,
  "Diciembre_2025":617924
 },
 {
  "organismo_nombre":"Corporación Municipal de Cultura de TilTil",
  "base":"Contratohonorarios",
  "homologado":"Sin Clasificar",
  "age_label":"30 a 50",
  "sexo":"mujer",
  "Agosto_2018":0,
  "Septiembre_2018":0,
  "Octubre_2018":0,
  "Noviembre_2018":0,
  "Diciembre_2018":161111,
  "Enero_2019":216666,
  "Febrero_2019":100000,
  "Marzo_2019":105556,
  "Abril_2019":100000,
  "Mayo_2019":98333,
  "Junio_2019":103333,
  "Julio_2019":105556,
  "Agosto_2019":87407,
  "Septiembre_2019":108889,
  "Octubre_2019":103333,
  "Noviembre_2019":95556,
  "Diciembre_2019":138889,
  "Enero_2020":125556,
  "Febrero_2020":0,
  "Marzo_2020":264828,
  "Abril_2020":111924,
  "Mayo_2020":112045,
  "Junio_2020":121511,
  "Julio_2020":13558,
  "Agosto_2020":82136,
  "Septiembre_2020":112045,
  "Octubre_2020":117625,
  "Noviembre_2020":150682,
  "Diciembre_2020":196015,
  "Enero_2021":143583,
  "Febrero_2021":112994,
  "Marzo_2021":102832,
  "Abril_2021":128331,
  "Mayo_2021":112248,
  "Junio_2021":168499,
  "Julio_2021":155585,
  "Agosto_2021":112045,
  "Septiembre_2021":108772,
  "Octubre_2021":113785,
  "Noviembre_2021":141405,
  "Diciembre_2021":103487,
  "Enero_2022":237580,
  "Febrero_2022":0,
  "Marzo_2022":0,
  "Abril_2022":126698,
  "Mayo_2022":139535,
  "Junio_2022":146415,
  "Julio_2022":101698,
  "Agosto_2022":325627,
  "Septiembre_2022":96132,
  "Octubre_2022":164577,
  "Noviembre_2022":34188,
  "Diciembre_2022":39886,
  "Enero_2023":140645,
  "Febrero_2023":0,
  "Marzo_2023":82443,
  "Abril_2023":0,
  "Mayo_2023":51724,
  "Junio_2023":360000,
  "Julio_2023":34483,
  "Agosto_2023":307816,
  "Septiembre_2023":0,
  "Octubre_2023":229885,
  "Noviembre_2023":344828,
  "Diciembre_2023":57471,
  "Enero_2024":411484,
  "Febrero_2024":0,
  "Marzo_2024":0,
  "Abril_2024":315942,
  "Mayo_2024":0,
  "Junio_2024":0,
  "Julio_2024":0,
  "Agosto_2024":216667,
  "Septiembre_2024":106749,
  "Octubre_2024":473913,
  "Noviembre_2024":115942,
  "Diciembre_2024":150150,
  "Enero_2025":0,
  "Febrero_2025":543858,
  "Marzo_2025":0,
  "Abril_2025":285088,
  "Mayo_2025":375000,
  "Junio_2025":95980,
  "Julio_2025":0,
  "Agosto_2025":252558,
  "Septiembre_2025":0,
  "Octubre_2025":108188,
  "Noviembre_2025":350877,
  "Diciembre_2025":350877
 },
 {
  "organismo_nombre":"Corporación Municipal de Cultura de TilTil",
  "base":"Contratohonorarios",
  "homologado":"Sin Clasificar",
  "age_label":"50 a 65",
  "sexo":"hombre",
  "Agosto_2018":0,
  "Septiembre_2018":0,
  "Octubre_2018":0,
  "Noviembre_2018":0,
  "Diciembre_2018":0,
  "Enero_2019":22222,
  "Febrero_2019":0,
  "Marzo_2019":0,
  "Abril_2019":0,
  "Mayo_2019":0,
  "Junio_2019":222222,
  "Julio_2019":222222,
  "Agosto_2019":162815,
  "Septiembre_2019":0,
  "Octubre_2019":0,
  "Noviembre_2019":0,
  "Diciembre_2019":0,
  "Enero_2020":111111,
  "Febrero_2020":0,
  "Marzo_2020":0,
  "Abril_2020":80000,
  "Mayo_2020":0,
  "Junio_2020":0,
  "Julio_2020":0,
  "Agosto_2020":0,
  "Septiembre_2020":0,
  "Octubre_2020":0,
  "Noviembre_2020":132403,
  "Diciembre_2020":224000,
  "Enero_2021":139429,
  "Febrero_2021":0,
  "Marzo_2021":162667,
  "Abril_2021":0,
  "Mayo_2021":180000,
  "Junio_2021":152000,
  "Julio_2021":220920,
  "Agosto_2021":0,
  "Septiembre_2021":155000,
  "Octubre_2021":160000,
  "Noviembre_2021":228571,
  "Diciembre_2021":145395,
  "Enero_2022":75000,
  "Febrero_2022":0,
  "Marzo_2022":0,
  "Abril_2022":218095,
  "Mayo_2022":143333,
  "Junio_2022":143333,
  "Julio_2022":143333,
  "Agosto_2022":120470,
  "Septiembre_2022":79772,
  "Octubre_2022":83032,
  "Noviembre_2022":137037,
  "Diciembre_2022":28490,
  "Enero_2023":472988,
  "Febrero_2023":0,
  "Marzo_2023":45977,
  "Abril_2023":0,
  "Mayo_2023":0,
  "Junio_2023":0,
  "Julio_2023":156980,
  "Agosto_2023":153211,
  "Septiembre_2023":0,
  "Octubre_2023":0,
  "Noviembre_2023":0,
  "Diciembre_2023":0,
  "Enero_2024":34783,
  "Febrero_2024":0,
  "Marzo_2024":0,
  "Abril_2024":400000,
  "Mayo_2024":0,
  "Junio_2024":0,
  "Julio_2024":0,
  "Agosto_2024":0,
  "Septiembre_2024":137932,
  "Octubre_2024":92754,
  "Noviembre_2024":0,
  "Diciembre_2024":575314,
  "Enero_2025":50000,
  "Febrero_2025":296800,
  "Marzo_2025":522015,
  "Abril_2025":296800,
  "Mayo_2025":0,
  "Junio_2025":250438,
  "Julio_2025":300000,
  "Agosto_2025":243568,
  "Septiembre_2025":225000,
  "Octubre_2025":266959,
  "Noviembre_2025":300000,
  "Diciembre_2025":300000
 },
 {
  "organismo_nombre":"Corporación Municipal de Cultura de TilTil",
  "base":"Contratohonorarios",
  "homologado":"Sin Clasificar",
  "age_label":"50 a 65",
  "sexo":"mujer",
  "Agosto_2018":0,
  "Septiembre_2018":0,
  "Octubre_2018":0,
  "Noviembre_2018":0,
  "Diciembre_2018":111111,
  "Enero_2019":111111,
  "Febrero_2019":0,
  "Marzo_2019":0,
  "Abril_2019":122222,
  "Mayo_2019":133333,
  "Junio_2019":155556,
  "Julio_2019":133333,
  "Agosto_2019":133333,
  "Septiembre_2019":120000,
  "Octubre_2019":130159,
  "Noviembre_2019":164815,
  "Diciembre_2019":202778,
  "Enero_2020":166667,
  "Febrero_2020":0,
  "Marzo_2020":151851,
  "Abril_2020":167259,
  "Mayo_2020":277778,
  "Junio_2020":0,
  "Julio_2020":0,
  "Agosto_2020":0,
  "Septiembre_2020":0,
  "Octubre_2020":0,
  "Noviembre_2020":101000,
  "Diciembre_2020":145956,
  "Enero_2021":80688,
  "Febrero_2021":0,
  "Marzo_2021":67500,
  "Abril_2021":112000,
  "Mayo_2021":104667,
  "Junio_2021":113625,
  "Julio_2021":85800,
  "Agosto_2021":0,
  "Septiembre_2021":134286,
  "Octubre_2021":106250,
  "Noviembre_2021":140000,
  "Diciembre_2021":128079,
  "Enero_2022":0,
  "Febrero_2022":0,
  "Marzo_2022":850000,
  "Abril_2022":123647,
  "Mayo_2022":91980,
  "Junio_2022":135470,
  "Julio_2022":135470,
  "Agosto_2022":170940,
  "Septiembre_2022":142640,
  "Octubre_2022":185470,
  "Noviembre_2022":170940,
  "Diciembre_2022":456980,
  "Enero_2023":172414,
  "Febrero_2023":0,
  "Marzo_2023":34483,
  "Abril_2023":0,
  "Mayo_2023":0,
  "Junio_2023":0,
  "Julio_2023":10000,
  "Agosto_2023":0,
  "Septiembre_2023":0,
  "Octubre_2023":0,
  "Noviembre_2023":0,
  "Diciembre_2023":138850,
  "Enero_2024":525000,
  "Febrero_2024":0,
  "Marzo_2024":220000,
  "Abril_2024":0,
  "Mayo_2024":0,
  "Junio_2024":0,
  "Julio_2024":0,
  "Agosto_2024":0,
  "Septiembre_2024":104348,
  "Octubre_2024":0,
  "Noviembre_2024":0,
  "Diciembre_2024":150000,
  "Enero_2025":0,
  "Febrero_2025":0,
  "Marzo_2025":441705,
  "Abril_2025":0,
  "Mayo_2025":0,
  "Junio_2025":0,
  "Julio_2025":0,
  "Agosto_2025":0,
  "Septiembre_2025":0,
  "Octubre_2025":0,
  "Noviembre_2025":0,
  "Diciembre_2025":35088
 },
 {
  "organismo_nombre":"Corporación Municipal de Cultura de TilTil",
  "base":"Contratohonorarios",
  "homologado":"Sin Clasificar",
  "age_label":"65 a 85",
  "sexo":"hombre",
  "Agosto_2018":0,
  "Septiembre_2018":0,
  "Octubre_2018":0,
  "Noviembre_2018":0,
  "Diciembre_2018":0,
  "Enero_2019":0,
  "Febrero_2019":0,
  "Marzo_2019":0,
  "Abril_2019":0,
  "Mayo_2019":0,
  "Junio_2019":0,
  "Julio_2019":0,
  "Agosto_2019":0,
  "Septiembre_2019":0,
  "Octubre_2019":0,
  "Noviembre_2019":0,
  "Diciembre_2019":0,
  "Enero_2020":0,
  "Febrero_2020":0,
  "Marzo_2020":0,
  "Abril_2020":0,
  "Mayo_2020":0,
  "Junio_2020":0,
  "Julio_2020":0,
  "Agosto_2020":0,
  "Septiembre_2020":56000,
  "Octubre_2020":0,
  "Noviembre_2020":180000,
  "Diciembre_2020":112045,
  "Enero_2021":0,
  "Febrero_2021":0,
  "Marzo_2021":0,
  "Abril_2021":0,
  "Mayo_2021":0,
  "Junio_2021":0,
  "Julio_2021":0,
  "Agosto_2021":0,
  "Septiembre_2021":0,
  "Octubre_2021":0,
  "Noviembre_2021":0,
  "Diciembre_2021":0,
  "Enero_2022":0,
  "Febrero_2022":0,
  "Marzo_2022":0,
  "Abril_2022":0,
  "Mayo_2022":0,
  "Junio_2022":0,
  "Julio_2022":0,
  "Agosto_2022":0,
  "Septiembre_2022":56989,
  "Octubre_2022":0,
  "Noviembre_2022":79772,
  "Diciembre_2022":0,
  "Enero_2023":37131,
  "Febrero_2023":0,
  "Marzo_2023":0,
  "Abril_2023":0,
  "Mayo_2023":0,
  "Junio_2023":0,
  "Julio_2023":0,
  "Agosto_2023":400000,
  "Septiembre_2023":126438,
  "Octubre_2023":130269,
  "Noviembre_2023":97702,
  "Diciembre_2023":114944,
  "Enero_2024":74864,
  "Febrero_2024":0,
  "Marzo_2024":0,
  "Abril_2024":115944,
  "Mayo_2024":0,
  "Junio_2024":378313,
  "Julio_2024":0,
  "Agosto_2024":500000,
  "Septiembre_2024":57972,
  "Octubre_2024":57972,
  "Noviembre_2024":425121,
  "Diciembre_2024":249034,
  "Enero_2025":0,
  "Febrero_2025":0,
  "Marzo_2025":0,
  "Abril_2025":0,
  "Mayo_2025":111112,
  "Junio_2025":0,
  "Julio_2025":0,
  "Agosto_2025":116959,
  "Septiembre_2025":0,
  "Octubre_2025":116960,
  "Noviembre_2025":0,
  "Diciembre_2025":233918
 },
 {
  "organismo_nombre":"Corporación Municipal de Cultura de TilTil",
  "base":"Contratohonorarios",
  "homologado":"Sin Clasificar",
  "age_label":"65 a 85",
  "sexo":"mujer",
  "Agosto_2018":0,
  "Septiembre_2018":0,
  "Octubre_2018":0,
  "Noviembre_2018":0,
  "Diciembre_2018":0,
  "Enero_2019":0,
  "Febrero_2019":0,
  "Marzo_2019":0,
  "Abril_2019":0,
  "Mayo_2019":0,
  "Junio_2019":0,
  "Julio_2019":0,
  "Agosto_2019":0,
  "Septiembre_2019":0,
  "Octubre_2019":0,
  "Noviembre_2019":0,
  "Diciembre_2019":0,
  "Enero_2020":0,
  "Febrero_2020":0,
  "Marzo_2020":0,
  "Abril_2020":0,
  "Mayo_2020":0,
  "Junio_2020":0,
  "Julio_2020":0,
  "Agosto_2020":0,
  "Septiembre_2020":0,
  "Octubre_2020":0,
  "Noviembre_2020":90000,
  "Diciembre_2020":90000,
  "Enero_2021":101250,
  "Febrero_2021":0,
  "Marzo_2021":0,
  "Abril_2021":0,
  "Mayo_2021":0,
  "Junio_2021":90000,
  "Julio_2021":90000,
  "Agosto_2021":0,
  "Septiembre_2021":100000,
  "Octubre_2021":100000,
  "Noviembre_2021":100000,
  "Diciembre_2021":100000,
  "Enero_2022":75000,
  "Febrero_2022":0,
  "Marzo_2022":0,
  "Abril_2022":0,
  "Mayo_2022":100000,
  "Junio_2022":100000,
  "Julio_2022":100000,
  "Agosto_2022":0,
  "Septiembre_2022":228490,
  "Octubre_2022":400000,
  "Noviembre_2022":0,
  "Diciembre_2022":0,
  "Enero_2023":0,
  "Febrero_2023":149425,
  "Marzo_2023":160920,
  "Abril_2023":220000,
  "Mayo_2023":220000,
  "Junio_2023":220000,
  "Julio_2023":220000,
  "Agosto_2023":166980,
  "Septiembre_2023":166980,
  "Octubre_2023":220000,
  "Noviembre_2023":260000,
  "Diciembre_2023":220000,
  "Enero_2024":220000,
  "Febrero_2024":0,
  "Marzo_2024":92800,
  "Abril_2024":0,
  "Mayo_2024":0,
  "Junio_2024":0,
  "Julio_2024":0,
  "Agosto_2024":0,
  "Septiembre_2024":57972,
  "Octubre_2024":0,
  "Noviembre_2024":0,
  "Diciembre_2024":0,
  "Enero_2025":0,
  "Febrero_2025":0,
  "Marzo_2025":0,
  "Abril_2025":0,
  "Mayo_2025":0,
  "Junio_2025":0,
  "Julio_2025":0,
  "Agosto_2025":0,
  "Septiembre_2025":0,
  "Octubre_2025":0,
  "Noviembre_2025":0,
  "Diciembre_2025":0
 },
 {
  "organismo_nombre":"Corporación Municipal de Cultura de TilTil",
  "base":"Contratohonorarios",
  "homologado":"Sin Clasificar",
  "age_label":"S\/I",
  "sexo":"hombre",
  "Agosto_2018":0,
  "Septiembre_2018":0,
  "Octubre_2018":0,
  "Noviembre_2018":0,
  "Diciembre_2018":111111,
  "Enero_2019":111111,
  "Febrero_2019":0,
  "Marzo_2019":180000,
  "Abril_2019":88889,
  "Mayo_2019":126667,
  "Junio_2019":149630,
  "Julio_2019":0,
  "Agosto_2019":140000,
  "Septiembre_2019":134074,
  "Octubre_2019":140000,
  "Noviembre_2019":145556,
  "Diciembre_2019":128889,
  "Enero_2020":0,
  "Febrero_2020":88889,
  "Marzo_2020":0,
  "Abril_2020":0,
  "Mayo_2020":0,
  "Junio_2020":0,
  "Julio_2020":0,
  "Agosto_2020":0,
  "Septiembre_2020":0,
  "Octubre_2020":0,
  "Noviembre_2020":89999,
  "Diciembre_2020":0,
  "Enero_2021":74999,
  "Febrero_2021":0,
  "Marzo_2021":73248,
  "Abril_2021":0,
  "Mayo_2021":0,
  "Junio_2021":89998,
  "Julio_2021":200000,
  "Agosto_2021":0,
  "Septiembre_2021":90000,
  "Octubre_2021":90000,
  "Noviembre_2021":90000,
  "Diciembre_2021":100000,
  "Enero_2022":0,
  "Febrero_2022":0,
  "Marzo_2022":0,
  "Abril_2022":100000,
  "Mayo_2022":100000,
  "Junio_2022":100000,
  "Julio_2022":100000,
  "Agosto_2022":0,
  "Septiembre_2022":56980,
  "Octubre_2022":0,
  "Noviembre_2022":0,
  "Diciembre_2022":0,
  "Enero_2023":0,
  "Febrero_2023":0,
  "Marzo_2023":0,
  "Abril_2023":0,
  "Mayo_2023":0,
  "Junio_2023":0,
  "Julio_2023":0,
  "Agosto_2023":75000,
  "Septiembre_2023":0,
  "Octubre_2023":0,
  "Noviembre_2023":0,
  "Diciembre_2023":436782,
  "Enero_2024":0,
  "Febrero_2024":0,
  "Marzo_2024":393237,
  "Abril_2024":0,
  "Mayo_2024":0,
  "Junio_2024":0,
  "Julio_2024":50436,
  "Agosto_2024":0,
  "Septiembre_2024":61836,
  "Octubre_2024":0,
  "Noviembre_2024":0,
  "Diciembre_2024":0,
  "Enero_2025":0,
  "Febrero_2025":0,
  "Marzo_2025":281085,
  "Abril_2025":0,
  "Mayo_2025":361395,
  "Junio_2025":200775,
  "Julio_2025":250000,
  "Agosto_2025":0,
  "Septiembre_2025":0,
  "Octubre_2025":0,
  "Noviembre_2025":0,
  "Diciembre_2025":0
 },
 {
  "organismo_nombre":"Corporación Municipal de Cultura de TilTil",
  "base":"Contratohonorarios",
  "homologado":"Sin Clasificar",
  "age_label":"S\/I",
  "sexo":"mujer",
  "Agosto_2018":0,
  "Septiembre_2018":0,
  "Octubre_2018":0,
  "Noviembre_2018":0,
  "Diciembre_2018":0,
  "Enero_2019":0,
  "Febrero_2019":0,
  "Marzo_2019":0,
  "Abril_2019":0,
  "Mayo_2019":0,
  "Junio_2019":0,
  "Julio_2019":0,
  "Agosto_2019":0,
  "Septiembre_2019":222222,
  "Octubre_2019":0,
  "Noviembre_2019":0,
  "Diciembre_2019":0,
  "Enero_2020":0,
  "Febrero_2020":0,
  "Marzo_2020":0,
  "Abril_2020":0,
  "Mayo_2020":0,
  "Junio_2020":0,
  "Julio_2020":0,
  "Agosto_2020":0,
  "Septiembre_2020":500000,
  "Octubre_2020":90000,
  "Noviembre_2020":35854,
  "Diciembre_2020":0,
  "Enero_2021":0,
  "Febrero_2021":0,
  "Marzo_2021":0,
  "Abril_2021":0,
  "Mayo_2021":0,
  "Junio_2021":0,
  "Julio_2021":0,
  "Agosto_2021":0,
  "Septiembre_2021":0,
  "Octubre_2021":0,
  "Noviembre_2021":0,
  "Diciembre_2021":0,
  "Enero_2022":0,
  "Febrero_2022":0,
  "Marzo_2022":0,
  "Abril_2022":100000,
  "Mayo_2022":0,
  "Junio_2022":0,
  "Julio_2022":600000,
  "Agosto_2022":0,
  "Septiembre_2022":0,
  "Octubre_2022":0,
  "Noviembre_2022":0,
  "Diciembre_2022":0,
  "Enero_2023":0,
  "Febrero_2023":0,
  "Marzo_2023":0,
  "Abril_2023":0,
  "Mayo_2023":0,
  "Junio_2023":0,
  "Julio_2023":0,
  "Agosto_2023":66236,
  "Septiembre_2023":57471,
  "Octubre_2023":279885,
  "Noviembre_2023":5000,
  "Diciembre_2023":0,
  "Enero_2024":74305,
  "Febrero_2024":0,
  "Marzo_2024":57971,
  "Abril_2024":0,
  "Mayo_2024":0,
  "Junio_2024":0,
  "Julio_2024":162319,
  "Agosto_2024":0,
  "Septiembre_2024":57972,
  "Octubre_2024":200000,
  "Noviembre_2024":0,
  "Diciembre_2024":0,
  "Enero_2025":0,
  "Febrero_2025":0,
  "Marzo_2025":175439,
  "Abril_2025":350000,
  "Mayo_2025":0,
  "Junio_2025":350000,
  "Julio_2025":350000,
  "Agosto_2025":0,
  "Septiembre_2025":0,
  "Octubre_2025":0,
  "Noviembre_2025":0,
  "Diciembre_2025":0
 },
 {
  "organismo_nombre":"Corporación Municipal de Cultura de TilTil",
  "base":"Contratohonorarios",
  "homologado":"Técnico",
  "age_label":"18 a 30",
  "sexo":"hombre",
  "Agosto_2018":0,
  "Septiembre_2018":0,
  "Octubre_2018":0,
  "Noviembre_2018":0,
  "Diciembre_2018":0,
  "Enero_2019":0,
  "Febrero_2019":0,
  "Marzo_2019":0,
  "Abril_2019":0,
  "Mayo_2019":0,
  "Junio_2019":0,
  "Julio_2019":0,
  "Agosto_2019":0,
  "Septiembre_2019":0,
  "Octubre_2019":0,
  "Noviembre_2019":0,
  "Diciembre_2019":0,
  "Enero_2020":0,
  "Febrero_2020":0,
  "Marzo_2020":0,
  "Abril_2020":0,
  "Mayo_2020":0,
  "Junio_2020":0,
  "Julio_2020":0,
  "Agosto_2020":0,
  "Septiembre_2020":0,
  "Octubre_2020":0,
  "Noviembre_2020":0,
  "Diciembre_2020":0,
  "Enero_2021":0,
  "Febrero_2021":0,
  "Marzo_2021":0,
  "Abril_2021":0,
  "Mayo_2021":0,
  "Junio_2021":0,
  "Julio_2021":0,
  "Agosto_2021":0,
  "Septiembre_2021":0,
  "Octubre_2021":0,
  "Noviembre_2021":0,
  "Diciembre_2021":0,
  "Enero_2022":0,
  "Febrero_2022":0,
  "Marzo_2022":0,
  "Abril_2022":0,
  "Mayo_2022":0,
  "Junio_2022":0,
  "Julio_2022":0,
  "Agosto_2022":0,
  "Septiembre_2022":0,
  "Octubre_2022":0,
  "Noviembre_2022":0,
  "Diciembre_2022":0,
  "Enero_2023":0,
  "Febrero_2023":229885,
  "Marzo_2023":0,
  "Abril_2023":0,
  "Mayo_2023":0,
  "Junio_2023":0,
  "Julio_2023":0,
  "Agosto_2023":0,
  "Septiembre_2023":0,
  "Octubre_2023":0,
  "Noviembre_2023":0,
  "Diciembre_2023":0,
  "Enero_2024":0,
  "Febrero_2024":0,
  "Marzo_2024":0,
  "Abril_2024":0,
  "Mayo_2024":0,
  "Junio_2024":0,
  "Julio_2024":0,
  "Agosto_2024":0,
  "Septiembre_2024":0,
  "Octubre_2024":0,
  "Noviembre_2024":0,
  "Diciembre_2024":0,
  "Enero_2025":0,
  "Febrero_2025":0,
  "Marzo_2025":0,
  "Abril_2025":0,
  "Mayo_2025":0,
  "Junio_2025":0,
  "Julio_2025":0,
  "Agosto_2025":0,
  "Septiembre_2025":0,
  "Octubre_2025":0,
  "Noviembre_2025":0,
  "Diciembre_2025":0
 }
]