[
 {
  "organismo_nombre":"Fundación Artesanías de Chile",
  "base":"Cod. Trabajo",
  "Enero_2024":1260115,
  "Febrero_2024":1242701,
  "Marzo_2024":1201636,
  "Abril_2024":1292056,
  "Mayo_2024":1165383,
  "Junio_2024":1275138,
  "Julio_2024":1292255,
  "Agosto_2024":1258078,
  "Septiembre_2024":1292699,
  "Octubre_2024":1329919,
  "Noviembre_2024":1194504,
  "Diciembre_2024":1186468,
  "Enero_2025":1166300,
  "Febrero_2025":1086619,
  "Marzo_2025":1076243,
  "Abril_2025":1071723,
  "Mayo_2025":1052457,
  "Junio_2025":1172817
 },
 {
  "organismo_nombre":"Fundación Artesanías de Chile",
  "base":"Honorarios",
  "Enero_2024":0,
  "Febrero_2024":0,
  "Marzo_2024":0,
  "Abril_2024":0,
  "Mayo_2024":0,
  "Junio_2024":0,
  "Julio_2024":0,
  "Agosto_2024":0,
  "Septiembre_2024":0,
  "Octubre_2024":0,
  "Noviembre_2024":0,
  "Diciembre_2024":313691,
  "Enero_2025":268410,
  "Febrero_2025":404740,
  "Marzo_2025":256225,
  "Abril_2025":426509,
  "Mayo_2025":303290,
  "Junio_2025":276547
 }
]