[
 {
  "organismo_nombre":"Municipalidad de Puente Alto",
  "base":"Cod. Trabajo",
  "age_label":"18 a 30",
  "Enero_2018":0,
  "Febrero_2018":0,
  "Marzo_2018":0,
  "Abril_2018":0,
  "Mayo_2018":0,
  "Junio_2018":0,
  "Julio_2018":0,
  "Agosto_2018":0,
  "Septiembre_2018":0,
  "Octubre_2018":0,
  "Noviembre_2018":0,
  "Diciembre_2018":0,
  "Enero_2019":0,
  "Febrero_2019":0,
  "Marzo_2019":0,
  "Abril_2019":0,
  "Mayo_2019":0,
  "Junio_2019":0,
  "Julio_2019":0,
  "Agosto_2019":0,
  "Septiembre_2019":0,
  "Octubre_2019":0,
  "Noviembre_2019":0,
  "Diciembre_2019":0,
  "Enero_2020":0,
  "Febrero_2020":0,
  "Marzo_2020":0,
  "Abril_2020":0,
  "Mayo_2020":0,
  "Junio_2020":0,
  "Julio_2020":0,
  "Agosto_2020":0,
  "Septiembre_2020":0,
  "Octubre_2020":0,
  "Noviembre_2020":0,
  "Diciembre_2020":0,
  "Enero_2021":0,
  "Febrero_2021":0,
  "Marzo_2021":0,
  "Abril_2021":0,
  "Mayo_2021":0,
  "Junio_2021":0,
  "Julio_2021":0,
  "Agosto_2021":0,
  "Septiembre_2021":0,
  "Octubre_2021":0,
  "Noviembre_2021":0,
  "Diciembre_2021":0,
  "Enero_2022":0,
  "Febrero_2022":0,
  "Marzo_2022":0,
  "Abril_2022":0,
  "Mayo_2022":0,
  "Junio_2022":0,
  "Julio_2022":0,
  "Agosto_2022":0,
  "Septiembre_2022":0,
  "Octubre_2022":0,
  "Noviembre_2022":0,
  "Diciembre_2022":0,
  "Enero_2023":0,
  "Febrero_2023":0,
  "Marzo_2023":0,
  "Abril_2023":0,
  "Mayo_2023":0,
  "Junio_2023":0,
  "Julio_2023":0,
  "Agosto_2023":0,
  "Septiembre_2023":0,
  "Octubre_2023":0,
  "Noviembre_2023":0,
  "Diciembre_2023":0,
  "Enero_2024":11,
  "Febrero_2024":11,
  "Marzo_2024":11,
  "Abril_2024":0,
  "Mayo_2024":10,
  "Junio_2024":10,
  "Julio_2024":0,
  "Agosto_2024":10,
  "Septiembre_2024":10,
  "Octubre_2024":10,
  "Noviembre_2024":10,
  "Diciembre_2024":10,
  "Enero_2025":10,
  "Febrero_2025":10,
  "Marzo_2025":10,
  "Abril_2025":11,
  "Mayo_2025":0,
  "Junio_2025":0,
  "Julio_2025":0,
  "Agosto_2025":0,
  "Septiembre_2025":0,
  "Octubre_2025":0,
  "Noviembre_2025":0,
  "Diciembre_2025":0
 },
 {
  "organismo_nombre":"Municipalidad de Puente Alto",
  "base":"Cod. Trabajo",
  "age_label":"30 a 50",
  "Enero_2018":0,
  "Febrero_2018":0,
  "Marzo_2018":0,
  "Abril_2018":0,
  "Mayo_2018":0,
  "Junio_2018":0,
  "Julio_2018":0,
  "Agosto_2018":0,
  "Septiembre_2018":0,
  "Octubre_2018":0,
  "Noviembre_2018":0,
  "Diciembre_2018":0,
  "Enero_2019":0,
  "Febrero_2019":0,
  "Marzo_2019":0,
  "Abril_2019":0,
  "Mayo_2019":0,
  "Junio_2019":0,
  "Julio_2019":0,
  "Agosto_2019":0,
  "Septiembre_2019":0,
  "Octubre_2019":0,
  "Noviembre_2019":0,
  "Diciembre_2019":0,
  "Enero_2020":0,
  "Febrero_2020":0,
  "Marzo_2020":0,
  "Abril_2020":0,
  "Mayo_2020":0,
  "Junio_2020":0,
  "Julio_2020":0,
  "Agosto_2020":0,
  "Septiembre_2020":0,
  "Octubre_2020":0,
  "Noviembre_2020":0,
  "Diciembre_2020":0,
  "Enero_2021":0,
  "Febrero_2021":0,
  "Marzo_2021":0,
  "Abril_2021":0,
  "Mayo_2021":0,
  "Junio_2021":0,
  "Julio_2021":0,
  "Agosto_2021":0,
  "Septiembre_2021":0,
  "Octubre_2021":0,
  "Noviembre_2021":0,
  "Diciembre_2021":0,
  "Enero_2022":0,
  "Febrero_2022":0,
  "Marzo_2022":0,
  "Abril_2022":0,
  "Mayo_2022":0,
  "Junio_2022":0,
  "Julio_2022":0,
  "Agosto_2022":0,
  "Septiembre_2022":0,
  "Octubre_2022":0,
  "Noviembre_2022":0,
  "Diciembre_2022":0,
  "Enero_2023":0,
  "Febrero_2023":0,
  "Marzo_2023":0,
  "Abril_2023":0,
  "Mayo_2023":0,
  "Junio_2023":8,
  "Julio_2023":0,
  "Agosto_2023":0,
  "Septiembre_2023":0,
  "Octubre_2023":0,
  "Noviembre_2023":0,
  "Diciembre_2023":0,
  "Enero_2024":56,
  "Febrero_2024":56,
  "Marzo_2024":56,
  "Abril_2024":0,
  "Mayo_2024":55,
  "Junio_2024":55,
  "Julio_2024":0,
  "Agosto_2024":54,
  "Septiembre_2024":53,
  "Octubre_2024":53,
  "Noviembre_2024":51,
  "Diciembre_2024":51,
  "Enero_2025":48,
  "Febrero_2025":54,
  "Marzo_2025":40,
  "Abril_2025":46,
  "Mayo_2025":0,
  "Junio_2025":0,
  "Julio_2025":0,
  "Agosto_2025":0,
  "Septiembre_2025":0,
  "Octubre_2025":0,
  "Noviembre_2025":0,
  "Diciembre_2025":0
 },
 {
  "organismo_nombre":"Municipalidad de Puente Alto",
  "base":"Cod. Trabajo",
  "age_label":"50 a 65",
  "Enero_2018":0,
  "Febrero_2018":0,
  "Marzo_2018":0,
  "Abril_2018":0,
  "Mayo_2018":0,
  "Junio_2018":0,
  "Julio_2018":0,
  "Agosto_2018":0,
  "Septiembre_2018":0,
  "Octubre_2018":0,
  "Noviembre_2018":0,
  "Diciembre_2018":0,
  "Enero_2019":0,
  "Febrero_2019":0,
  "Marzo_2019":0,
  "Abril_2019":0,
  "Mayo_2019":0,
  "Junio_2019":0,
  "Julio_2019":0,
  "Agosto_2019":0,
  "Septiembre_2019":0,
  "Octubre_2019":0,
  "Noviembre_2019":0,
  "Diciembre_2019":0,
  "Enero_2020":0,
  "Febrero_2020":0,
  "Marzo_2020":0,
  "Abril_2020":0,
  "Mayo_2020":0,
  "Junio_2020":0,
  "Julio_2020":0,
  "Agosto_2020":0,
  "Septiembre_2020":0,
  "Octubre_2020":0,
  "Noviembre_2020":0,
  "Diciembre_2020":0,
  "Enero_2021":0,
  "Febrero_2021":0,
  "Marzo_2021":0,
  "Abril_2021":0,
  "Mayo_2021":0,
  "Junio_2021":0,
  "Julio_2021":0,
  "Agosto_2021":0,
  "Septiembre_2021":0,
  "Octubre_2021":0,
  "Noviembre_2021":0,
  "Diciembre_2021":0,
  "Enero_2022":0,
  "Febrero_2022":0,
  "Marzo_2022":0,
  "Abril_2022":0,
  "Mayo_2022":0,
  "Junio_2022":0,
  "Julio_2022":0,
  "Agosto_2022":0,
  "Septiembre_2022":0,
  "Octubre_2022":0,
  "Noviembre_2022":0,
  "Diciembre_2022":0,
  "Enero_2023":0,
  "Febrero_2023":0,
  "Marzo_2023":0,
  "Abril_2023":0,
  "Mayo_2023":0,
  "Junio_2023":8,
  "Julio_2023":0,
  "Agosto_2023":0,
  "Septiembre_2023":0,
  "Octubre_2023":0,
  "Noviembre_2023":0,
  "Diciembre_2023":0,
  "Enero_2024":39,
  "Febrero_2024":39,
  "Marzo_2024":39,
  "Abril_2024":0,
  "Mayo_2024":39,
  "Junio_2024":39,
  "Julio_2024":0,
  "Agosto_2024":39,
  "Septiembre_2024":39,
  "Octubre_2024":39,
  "Noviembre_2024":39,
  "Diciembre_2024":38,
  "Enero_2025":41,
  "Febrero_2025":47,
  "Marzo_2025":35,
  "Abril_2025":41,
  "Mayo_2025":0,
  "Junio_2025":0,
  "Julio_2025":0,
  "Agosto_2025":0,
  "Septiembre_2025":0,
  "Octubre_2025":0,
  "Noviembre_2025":0,
  "Diciembre_2025":0
 },
 {
  "organismo_nombre":"Municipalidad de Puente Alto",
  "base":"Cod. Trabajo",
  "age_label":"65 a 85",
  "Enero_2018":0,
  "Febrero_2018":0,
  "Marzo_2018":0,
  "Abril_2018":0,
  "Mayo_2018":0,
  "Junio_2018":0,
  "Julio_2018":0,
  "Agosto_2018":0,
  "Septiembre_2018":0,
  "Octubre_2018":0,
  "Noviembre_2018":0,
  "Diciembre_2018":0,
  "Enero_2019":0,
  "Febrero_2019":0,
  "Marzo_2019":0,
  "Abril_2019":0,
  "Mayo_2019":0,
  "Junio_2019":0,
  "Julio_2019":0,
  "Agosto_2019":0,
  "Septiembre_2019":0,
  "Octubre_2019":0,
  "Noviembre_2019":0,
  "Diciembre_2019":0,
  "Enero_2020":0,
  "Febrero_2020":0,
  "Marzo_2020":0,
  "Abril_2020":0,
  "Mayo_2020":0,
  "Junio_2020":0,
  "Julio_2020":0,
  "Agosto_2020":0,
  "Septiembre_2020":0,
  "Octubre_2020":0,
  "Noviembre_2020":0,
  "Diciembre_2020":0,
  "Enero_2021":0,
  "Febrero_2021":0,
  "Marzo_2021":0,
  "Abril_2021":0,
  "Mayo_2021":0,
  "Junio_2021":0,
  "Julio_2021":0,
  "Agosto_2021":0,
  "Septiembre_2021":0,
  "Octubre_2021":0,
  "Noviembre_2021":0,
  "Diciembre_2021":0,
  "Enero_2022":0,
  "Febrero_2022":0,
  "Marzo_2022":0,
  "Abril_2022":0,
  "Mayo_2022":0,
  "Junio_2022":0,
  "Julio_2022":0,
  "Agosto_2022":0,
  "Septiembre_2022":0,
  "Octubre_2022":0,
  "Noviembre_2022":0,
  "Diciembre_2022":0,
  "Enero_2023":0,
  "Febrero_2023":0,
  "Marzo_2023":0,
  "Abril_2023":0,
  "Mayo_2023":0,
  "Junio_2023":5,
  "Julio_2023":0,
  "Agosto_2023":0,
  "Septiembre_2023":0,
  "Octubre_2023":0,
  "Noviembre_2023":0,
  "Diciembre_2023":0,
  "Enero_2024":22,
  "Febrero_2024":22,
  "Marzo_2024":22,
  "Abril_2024":0,
  "Mayo_2024":22,
  "Junio_2024":22,
  "Julio_2024":0,
  "Agosto_2024":22,
  "Septiembre_2024":22,
  "Octubre_2024":22,
  "Noviembre_2024":22,
  "Diciembre_2024":22,
  "Enero_2025":21,
  "Febrero_2025":27,
  "Marzo_2025":15,
  "Abril_2025":21,
  "Mayo_2025":0,
  "Junio_2025":0,
  "Julio_2025":0,
  "Agosto_2025":0,
  "Septiembre_2025":0,
  "Octubre_2025":0,
  "Noviembre_2025":0,
  "Diciembre_2025":0
 },
 {
  "organismo_nombre":"Municipalidad de Puente Alto",
  "base":"Contrata",
  "age_label":"18 a 30",
  "Enero_2018":0,
  "Febrero_2018":0,
  "Marzo_2018":0,
  "Abril_2018":0,
  "Mayo_2018":0,
  "Junio_2018":0,
  "Julio_2018":0,
  "Agosto_2018":0,
  "Septiembre_2018":0,
  "Octubre_2018":0,
  "Noviembre_2018":0,
  "Diciembre_2018":0,
  "Enero_2019":0,
  "Febrero_2019":0,
  "Marzo_2019":0,
  "Abril_2019":0,
  "Mayo_2019":0,
  "Junio_2019":0,
  "Julio_2019":0,
  "Agosto_2019":0,
  "Septiembre_2019":0,
  "Octubre_2019":0,
  "Noviembre_2019":0,
  "Diciembre_2019":0,
  "Enero_2020":0,
  "Febrero_2020":0,
  "Marzo_2020":0,
  "Abril_2020":0,
  "Mayo_2020":0,
  "Junio_2020":0,
  "Julio_2020":0,
  "Agosto_2020":0,
  "Septiembre_2020":0,
  "Octubre_2020":0,
  "Noviembre_2020":0,
  "Diciembre_2020":0,
  "Enero_2021":0,
  "Febrero_2021":0,
  "Marzo_2021":0,
  "Abril_2021":0,
  "Mayo_2021":0,
  "Junio_2021":0,
  "Julio_2021":0,
  "Agosto_2021":0,
  "Septiembre_2021":0,
  "Octubre_2021":0,
  "Noviembre_2021":0,
  "Diciembre_2021":0,
  "Enero_2022":0,
  "Febrero_2022":0,
  "Marzo_2022":0,
  "Abril_2022":0,
  "Mayo_2022":0,
  "Junio_2022":0,
  "Julio_2022":0,
  "Agosto_2022":0,
  "Septiembre_2022":0,
  "Octubre_2022":0,
  "Noviembre_2022":0,
  "Diciembre_2022":0,
  "Enero_2023":0,
  "Febrero_2023":0,
  "Marzo_2023":0,
  "Abril_2023":0,
  "Mayo_2023":0,
  "Junio_2023":26,
  "Julio_2023":0,
  "Agosto_2023":0,
  "Septiembre_2023":0,
  "Octubre_2023":0,
  "Noviembre_2023":0,
  "Diciembre_2023":0,
  "Enero_2024":20,
  "Febrero_2024":0,
  "Marzo_2024":0,
  "Abril_2024":0,
  "Mayo_2024":0,
  "Junio_2024":0,
  "Julio_2024":0,
  "Agosto_2024":0,
  "Septiembre_2024":0,
  "Octubre_2024":0,
  "Noviembre_2024":0,
  "Diciembre_2024":0,
  "Enero_2025":13,
  "Febrero_2025":0,
  "Marzo_2025":14,
  "Abril_2025":0,
  "Mayo_2025":0,
  "Junio_2025":0,
  "Julio_2025":0,
  "Agosto_2025":0,
  "Septiembre_2025":0,
  "Octubre_2025":0,
  "Noviembre_2025":0,
  "Diciembre_2025":0
 },
 {
  "organismo_nombre":"Municipalidad de Puente Alto",
  "base":"Contrata",
  "age_label":"30 a 50",
  "Enero_2018":0,
  "Febrero_2018":0,
  "Marzo_2018":0,
  "Abril_2018":0,
  "Mayo_2018":0,
  "Junio_2018":0,
  "Julio_2018":0,
  "Agosto_2018":0,
  "Septiembre_2018":0,
  "Octubre_2018":0,
  "Noviembre_2018":0,
  "Diciembre_2018":0,
  "Enero_2019":0,
  "Febrero_2019":0,
  "Marzo_2019":0,
  "Abril_2019":0,
  "Mayo_2019":0,
  "Junio_2019":0,
  "Julio_2019":0,
  "Agosto_2019":0,
  "Septiembre_2019":0,
  "Octubre_2019":0,
  "Noviembre_2019":0,
  "Diciembre_2019":0,
  "Enero_2020":0,
  "Febrero_2020":0,
  "Marzo_2020":0,
  "Abril_2020":0,
  "Mayo_2020":0,
  "Junio_2020":0,
  "Julio_2020":0,
  "Agosto_2020":0,
  "Septiembre_2020":0,
  "Octubre_2020":0,
  "Noviembre_2020":0,
  "Diciembre_2020":0,
  "Enero_2021":0,
  "Febrero_2021":0,
  "Marzo_2021":0,
  "Abril_2021":0,
  "Mayo_2021":0,
  "Junio_2021":0,
  "Julio_2021":0,
  "Agosto_2021":0,
  "Septiembre_2021":0,
  "Octubre_2021":0,
  "Noviembre_2021":0,
  "Diciembre_2021":0,
  "Enero_2022":0,
  "Febrero_2022":0,
  "Marzo_2022":0,
  "Abril_2022":0,
  "Mayo_2022":0,
  "Junio_2022":0,
  "Julio_2022":0,
  "Agosto_2022":0,
  "Septiembre_2022":0,
  "Octubre_2022":0,
  "Noviembre_2022":0,
  "Diciembre_2022":0,
  "Enero_2023":0,
  "Febrero_2023":0,
  "Marzo_2023":0,
  "Abril_2023":0,
  "Mayo_2023":0,
  "Junio_2023":188,
  "Julio_2023":0,
  "Agosto_2023":0,
  "Septiembre_2023":0,
  "Octubre_2023":0,
  "Noviembre_2023":0,
  "Diciembre_2023":0,
  "Enero_2024":180,
  "Febrero_2024":0,
  "Marzo_2024":0,
  "Abril_2024":0,
  "Mayo_2024":0,
  "Junio_2024":0,
  "Julio_2024":0,
  "Agosto_2024":0,
  "Septiembre_2024":0,
  "Octubre_2024":0,
  "Noviembre_2024":0,
  "Diciembre_2024":0,
  "Enero_2025":175,
  "Febrero_2025":0,
  "Marzo_2025":180,
  "Abril_2025":0,
  "Mayo_2025":0,
  "Junio_2025":0,
  "Julio_2025":0,
  "Agosto_2025":0,
  "Septiembre_2025":0,
  "Octubre_2025":0,
  "Noviembre_2025":0,
  "Diciembre_2025":0
 },
 {
  "organismo_nombre":"Municipalidad de Puente Alto",
  "base":"Contrata",
  "age_label":"50 a 65",
  "Enero_2018":0,
  "Febrero_2018":0,
  "Marzo_2018":0,
  "Abril_2018":0,
  "Mayo_2018":0,
  "Junio_2018":0,
  "Julio_2018":0,
  "Agosto_2018":0,
  "Septiembre_2018":0,
  "Octubre_2018":0,
  "Noviembre_2018":0,
  "Diciembre_2018":0,
  "Enero_2019":0,
  "Febrero_2019":0,
  "Marzo_2019":0,
  "Abril_2019":0,
  "Mayo_2019":0,
  "Junio_2019":0,
  "Julio_2019":0,
  "Agosto_2019":0,
  "Septiembre_2019":0,
  "Octubre_2019":0,
  "Noviembre_2019":0,
  "Diciembre_2019":0,
  "Enero_2020":0,
  "Febrero_2020":0,
  "Marzo_2020":0,
  "Abril_2020":0,
  "Mayo_2020":0,
  "Junio_2020":0,
  "Julio_2020":0,
  "Agosto_2020":0,
  "Septiembre_2020":0,
  "Octubre_2020":0,
  "Noviembre_2020":0,
  "Diciembre_2020":0,
  "Enero_2021":0,
  "Febrero_2021":0,
  "Marzo_2021":0,
  "Abril_2021":0,
  "Mayo_2021":0,
  "Junio_2021":0,
  "Julio_2021":0,
  "Agosto_2021":0,
  "Septiembre_2021":0,
  "Octubre_2021":0,
  "Noviembre_2021":0,
  "Diciembre_2021":0,
  "Enero_2022":0,
  "Febrero_2022":0,
  "Marzo_2022":0,
  "Abril_2022":0,
  "Mayo_2022":0,
  "Junio_2022":0,
  "Julio_2022":0,
  "Agosto_2022":0,
  "Septiembre_2022":0,
  "Octubre_2022":0,
  "Noviembre_2022":0,
  "Diciembre_2022":0,
  "Enero_2023":0,
  "Febrero_2023":0,
  "Marzo_2023":0,
  "Abril_2023":0,
  "Mayo_2023":0,
  "Junio_2023":75,
  "Julio_2023":0,
  "Agosto_2023":0,
  "Septiembre_2023":0,
  "Octubre_2023":0,
  "Noviembre_2023":0,
  "Diciembre_2023":0,
  "Enero_2024":83,
  "Febrero_2024":0,
  "Marzo_2024":0,
  "Abril_2024":0,
  "Mayo_2024":0,
  "Junio_2024":0,
  "Julio_2024":0,
  "Agosto_2024":0,
  "Septiembre_2024":0,
  "Octubre_2024":0,
  "Noviembre_2024":0,
  "Diciembre_2024":0,
  "Enero_2025":86,
  "Febrero_2025":0,
  "Marzo_2025":88,
  "Abril_2025":0,
  "Mayo_2025":0,
  "Junio_2025":0,
  "Julio_2025":0,
  "Agosto_2025":0,
  "Septiembre_2025":0,
  "Octubre_2025":0,
  "Noviembre_2025":0,
  "Diciembre_2025":0
 },
 {
  "organismo_nombre":"Municipalidad de Puente Alto",
  "base":"Contrata",
  "age_label":"65 a 85",
  "Enero_2018":0,
  "Febrero_2018":0,
  "Marzo_2018":0,
  "Abril_2018":0,
  "Mayo_2018":0,
  "Junio_2018":0,
  "Julio_2018":0,
  "Agosto_2018":0,
  "Septiembre_2018":0,
  "Octubre_2018":0,
  "Noviembre_2018":0,
  "Diciembre_2018":0,
  "Enero_2019":0,
  "Febrero_2019":0,
  "Marzo_2019":0,
  "Abril_2019":0,
  "Mayo_2019":0,
  "Junio_2019":0,
  "Julio_2019":0,
  "Agosto_2019":0,
  "Septiembre_2019":0,
  "Octubre_2019":0,
  "Noviembre_2019":0,
  "Diciembre_2019":0,
  "Enero_2020":0,
  "Febrero_2020":0,
  "Marzo_2020":0,
  "Abril_2020":0,
  "Mayo_2020":0,
  "Junio_2020":0,
  "Julio_2020":0,
  "Agosto_2020":0,
  "Septiembre_2020":0,
  "Octubre_2020":0,
  "Noviembre_2020":0,
  "Diciembre_2020":0,
  "Enero_2021":0,
  "Febrero_2021":0,
  "Marzo_2021":0,
  "Abril_2021":0,
  "Mayo_2021":0,
  "Junio_2021":0,
  "Julio_2021":0,
  "Agosto_2021":0,
  "Septiembre_2021":0,
  "Octubre_2021":0,
  "Noviembre_2021":0,
  "Diciembre_2021":0,
  "Enero_2022":0,
  "Febrero_2022":0,
  "Marzo_2022":0,
  "Abril_2022":0,
  "Mayo_2022":0,
  "Junio_2022":0,
  "Julio_2022":0,
  "Agosto_2022":0,
  "Septiembre_2022":0,
  "Octubre_2022":0,
  "Noviembre_2022":0,
  "Diciembre_2022":0,
  "Enero_2023":0,
  "Febrero_2023":0,
  "Marzo_2023":0,
  "Abril_2023":0,
  "Mayo_2023":0,
  "Junio_2023":23,
  "Julio_2023":0,
  "Agosto_2023":0,
  "Septiembre_2023":0,
  "Octubre_2023":0,
  "Noviembre_2023":0,
  "Diciembre_2023":0,
  "Enero_2024":24,
  "Febrero_2024":0,
  "Marzo_2024":0,
  "Abril_2024":0,
  "Mayo_2024":0,
  "Junio_2024":0,
  "Julio_2024":0,
  "Agosto_2024":0,
  "Septiembre_2024":0,
  "Octubre_2024":0,
  "Noviembre_2024":0,
  "Diciembre_2024":0,
  "Enero_2025":26,
  "Febrero_2025":0,
  "Marzo_2025":26,
  "Abril_2025":0,
  "Mayo_2025":0,
  "Junio_2025":0,
  "Julio_2025":0,
  "Agosto_2025":0,
  "Septiembre_2025":0,
  "Octubre_2025":0,
  "Noviembre_2025":0,
  "Diciembre_2025":0
 },
 {
  "organismo_nombre":"Municipalidad de Puente Alto",
  "base":"Honorarios",
  "age_label":"18 a 30",
  "Enero_2018":0,
  "Febrero_2018":0,
  "Marzo_2018":0,
  "Abril_2018":0,
  "Mayo_2018":0,
  "Junio_2018":0,
  "Julio_2018":0,
  "Agosto_2018":0,
  "Septiembre_2018":0,
  "Octubre_2018":0,
  "Noviembre_2018":0,
  "Diciembre_2018":0,
  "Enero_2019":0,
  "Febrero_2019":0,
  "Marzo_2019":0,
  "Abril_2019":0,
  "Mayo_2019":0,
  "Junio_2019":0,
  "Julio_2019":0,
  "Agosto_2019":0,
  "Septiembre_2019":0,
  "Octubre_2019":0,
  "Noviembre_2019":0,
  "Diciembre_2019":0,
  "Enero_2020":0,
  "Febrero_2020":0,
  "Marzo_2020":0,
  "Abril_2020":0,
  "Mayo_2020":0,
  "Junio_2020":0,
  "Julio_2020":0,
  "Agosto_2020":0,
  "Septiembre_2020":0,
  "Octubre_2020":0,
  "Noviembre_2020":0,
  "Diciembre_2020":0,
  "Enero_2021":0,
  "Febrero_2021":0,
  "Marzo_2021":0,
  "Abril_2021":0,
  "Mayo_2021":0,
  "Junio_2021":0,
  "Julio_2021":0,
  "Agosto_2021":0,
  "Septiembre_2021":0,
  "Octubre_2021":0,
  "Noviembre_2021":0,
  "Diciembre_2021":0,
  "Enero_2022":0,
  "Febrero_2022":0,
  "Marzo_2022":0,
  "Abril_2022":0,
  "Mayo_2022":0,
  "Junio_2022":0,
  "Julio_2022":0,
  "Agosto_2022":0,
  "Septiembre_2022":0,
  "Octubre_2022":0,
  "Noviembre_2022":0,
  "Diciembre_2022":0,
  "Enero_2023":0,
  "Febrero_2023":0,
  "Marzo_2023":0,
  "Abril_2023":0,
  "Mayo_2023":0,
  "Junio_2023":0,
  "Julio_2023":216,
  "Agosto_2023":0,
  "Septiembre_2023":0,
  "Octubre_2023":0,
  "Noviembre_2023":0,
  "Diciembre_2023":0,
  "Enero_2024":0,
  "Febrero_2024":0,
  "Marzo_2024":0,
  "Abril_2024":0,
  "Mayo_2024":0,
  "Junio_2024":0,
  "Julio_2024":0,
  "Agosto_2024":0,
  "Septiembre_2024":0,
  "Octubre_2024":0,
  "Noviembre_2024":0,
  "Diciembre_2024":0,
  "Enero_2025":204,
  "Febrero_2025":228,
  "Marzo_2025":270,
  "Abril_2025":249,
  "Mayo_2025":0,
  "Junio_2025":0,
  "Julio_2025":0,
  "Agosto_2025":0,
  "Septiembre_2025":0,
  "Octubre_2025":0,
  "Noviembre_2025":0,
  "Diciembre_2025":0
 },
 {
  "organismo_nombre":"Municipalidad de Puente Alto",
  "base":"Honorarios",
  "age_label":"30 a 50",
  "Enero_2018":0,
  "Febrero_2018":0,
  "Marzo_2018":0,
  "Abril_2018":0,
  "Mayo_2018":0,
  "Junio_2018":0,
  "Julio_2018":0,
  "Agosto_2018":0,
  "Septiembre_2018":0,
  "Octubre_2018":0,
  "Noviembre_2018":0,
  "Diciembre_2018":0,
  "Enero_2019":0,
  "Febrero_2019":0,
  "Marzo_2019":0,
  "Abril_2019":0,
  "Mayo_2019":0,
  "Junio_2019":0,
  "Julio_2019":0,
  "Agosto_2019":0,
  "Septiembre_2019":0,
  "Octubre_2019":0,
  "Noviembre_2019":0,
  "Diciembre_2019":0,
  "Enero_2020":0,
  "Febrero_2020":0,
  "Marzo_2020":0,
  "Abril_2020":0,
  "Mayo_2020":0,
  "Junio_2020":0,
  "Julio_2020":0,
  "Agosto_2020":0,
  "Septiembre_2020":0,
  "Octubre_2020":0,
  "Noviembre_2020":0,
  "Diciembre_2020":0,
  "Enero_2021":0,
  "Febrero_2021":0,
  "Marzo_2021":0,
  "Abril_2021":0,
  "Mayo_2021":0,
  "Junio_2021":0,
  "Julio_2021":0,
  "Agosto_2021":0,
  "Septiembre_2021":0,
  "Octubre_2021":0,
  "Noviembre_2021":0,
  "Diciembre_2021":0,
  "Enero_2022":0,
  "Febrero_2022":0,
  "Marzo_2022":0,
  "Abril_2022":0,
  "Mayo_2022":0,
  "Junio_2022":0,
  "Julio_2022":0,
  "Agosto_2022":0,
  "Septiembre_2022":0,
  "Octubre_2022":0,
  "Noviembre_2022":0,
  "Diciembre_2022":0,
  "Enero_2023":0,
  "Febrero_2023":0,
  "Marzo_2023":0,
  "Abril_2023":0,
  "Mayo_2023":0,
  "Junio_2023":0,
  "Julio_2023":641,
  "Agosto_2023":0,
  "Septiembre_2023":0,
  "Octubre_2023":0,
  "Noviembre_2023":0,
  "Diciembre_2023":0,
  "Enero_2024":0,
  "Febrero_2024":0,
  "Marzo_2024":0,
  "Abril_2024":0,
  "Mayo_2024":0,
  "Junio_2024":0,
  "Julio_2024":0,
  "Agosto_2024":0,
  "Septiembre_2024":0,
  "Octubre_2024":0,
  "Noviembre_2024":0,
  "Diciembre_2024":0,
  "Enero_2025":570,
  "Febrero_2025":626,
  "Marzo_2025":685,
  "Abril_2025":681,
  "Mayo_2025":0,
  "Junio_2025":0,
  "Julio_2025":0,
  "Agosto_2025":0,
  "Septiembre_2025":0,
  "Octubre_2025":0,
  "Noviembre_2025":0,
  "Diciembre_2025":0
 },
 {
  "organismo_nombre":"Municipalidad de Puente Alto",
  "base":"Honorarios",
  "age_label":"50 a 65",
  "Enero_2018":0,
  "Febrero_2018":0,
  "Marzo_2018":0,
  "Abril_2018":0,
  "Mayo_2018":0,
  "Junio_2018":0,
  "Julio_2018":0,
  "Agosto_2018":0,
  "Septiembre_2018":0,
  "Octubre_2018":0,
  "Noviembre_2018":0,
  "Diciembre_2018":0,
  "Enero_2019":0,
  "Febrero_2019":0,
  "Marzo_2019":0,
  "Abril_2019":0,
  "Mayo_2019":0,
  "Junio_2019":0,
  "Julio_2019":0,
  "Agosto_2019":0,
  "Septiembre_2019":0,
  "Octubre_2019":0,
  "Noviembre_2019":0,
  "Diciembre_2019":0,
  "Enero_2020":0,
  "Febrero_2020":0,
  "Marzo_2020":0,
  "Abril_2020":0,
  "Mayo_2020":0,
  "Junio_2020":0,
  "Julio_2020":0,
  "Agosto_2020":0,
  "Septiembre_2020":0,
  "Octubre_2020":0,
  "Noviembre_2020":0,
  "Diciembre_2020":0,
  "Enero_2021":0,
  "Febrero_2021":0,
  "Marzo_2021":0,
  "Abril_2021":0,
  "Mayo_2021":0,
  "Junio_2021":0,
  "Julio_2021":0,
  "Agosto_2021":0,
  "Septiembre_2021":0,
  "Octubre_2021":0,
  "Noviembre_2021":0,
  "Diciembre_2021":0,
  "Enero_2022":0,
  "Febrero_2022":0,
  "Marzo_2022":0,
  "Abril_2022":0,
  "Mayo_2022":0,
  "Junio_2022":0,
  "Julio_2022":0,
  "Agosto_2022":0,
  "Septiembre_2022":0,
  "Octubre_2022":0,
  "Noviembre_2022":0,
  "Diciembre_2022":0,
  "Enero_2023":0,
  "Febrero_2023":0,
  "Marzo_2023":0,
  "Abril_2023":0,
  "Mayo_2023":0,
  "Junio_2023":0,
  "Julio_2023":435,
  "Agosto_2023":0,
  "Septiembre_2023":0,
  "Octubre_2023":0,
  "Noviembre_2023":0,
  "Diciembre_2023":0,
  "Enero_2024":0,
  "Febrero_2024":0,
  "Marzo_2024":0,
  "Abril_2024":0,
  "Mayo_2024":0,
  "Junio_2024":0,
  "Julio_2024":0,
  "Agosto_2024":0,
  "Septiembre_2024":0,
  "Octubre_2024":0,
  "Noviembre_2024":0,
  "Diciembre_2024":0,
  "Enero_2025":406,
  "Febrero_2025":437,
  "Marzo_2025":459,
  "Abril_2025":455,
  "Mayo_2025":0,
  "Junio_2025":0,
  "Julio_2025":0,
  "Agosto_2025":0,
  "Septiembre_2025":0,
  "Octubre_2025":0,
  "Noviembre_2025":0,
  "Diciembre_2025":0
 },
 {
  "organismo_nombre":"Municipalidad de Puente Alto",
  "base":"Honorarios",
  "age_label":"65 a 85",
  "Enero_2018":0,
  "Febrero_2018":0,
  "Marzo_2018":0,
  "Abril_2018":0,
  "Mayo_2018":0,
  "Junio_2018":0,
  "Julio_2018":0,
  "Agosto_2018":0,
  "Septiembre_2018":0,
  "Octubre_2018":0,
  "Noviembre_2018":0,
  "Diciembre_2018":0,
  "Enero_2019":0,
  "Febrero_2019":0,
  "Marzo_2019":0,
  "Abril_2019":0,
  "Mayo_2019":0,
  "Junio_2019":0,
  "Julio_2019":0,
  "Agosto_2019":0,
  "Septiembre_2019":0,
  "Octubre_2019":0,
  "Noviembre_2019":0,
  "Diciembre_2019":0,
  "Enero_2020":0,
  "Febrero_2020":0,
  "Marzo_2020":0,
  "Abril_2020":0,
  "Mayo_2020":0,
  "Junio_2020":0,
  "Julio_2020":0,
  "Agosto_2020":0,
  "Septiembre_2020":0,
  "Octubre_2020":0,
  "Noviembre_2020":0,
  "Diciembre_2020":0,
  "Enero_2021":0,
  "Febrero_2021":0,
  "Marzo_2021":0,
  "Abril_2021":0,
  "Mayo_2021":0,
  "Junio_2021":0,
  "Julio_2021":0,
  "Agosto_2021":0,
  "Septiembre_2021":0,
  "Octubre_2021":0,
  "Noviembre_2021":0,
  "Diciembre_2021":0,
  "Enero_2022":0,
  "Febrero_2022":0,
  "Marzo_2022":0,
  "Abril_2022":0,
  "Mayo_2022":0,
  "Junio_2022":0,
  "Julio_2022":0,
  "Agosto_2022":0,
  "Septiembre_2022":0,
  "Octubre_2022":0,
  "Noviembre_2022":0,
  "Diciembre_2022":0,
  "Enero_2023":0,
  "Febrero_2023":0,
  "Marzo_2023":0,
  "Abril_2023":0,
  "Mayo_2023":0,
  "Junio_2023":0,
  "Julio_2023":288,
  "Agosto_2023":0,
  "Septiembre_2023":0,
  "Octubre_2023":0,
  "Noviembre_2023":0,
  "Diciembre_2023":0,
  "Enero_2024":0,
  "Febrero_2024":0,
  "Marzo_2024":0,
  "Abril_2024":0,
  "Mayo_2024":0,
  "Junio_2024":0,
  "Julio_2024":0,
  "Agosto_2024":0,
  "Septiembre_2024":0,
  "Octubre_2024":0,
  "Noviembre_2024":0,
  "Diciembre_2024":0,
  "Enero_2025":263,
  "Febrero_2025":264,
  "Marzo_2025":276,
  "Abril_2025":279,
  "Mayo_2025":0,
  "Junio_2025":0,
  "Julio_2025":0,
  "Agosto_2025":0,
  "Septiembre_2025":0,
  "Octubre_2025":0,
  "Noviembre_2025":0,
  "Diciembre_2025":0
 },
 {
  "organismo_nombre":"Municipalidad de Puente Alto",
  "base":"Planta",
  "age_label":"18 a 30",
  "Enero_2018":0,
  "Febrero_2018":0,
  "Marzo_2018":0,
  "Abril_2018":0,
  "Mayo_2018":0,
  "Junio_2018":0,
  "Julio_2018":0,
  "Agosto_2018":0,
  "Septiembre_2018":0,
  "Octubre_2018":0,
  "Noviembre_2018":0,
  "Diciembre_2018":0,
  "Enero_2019":0,
  "Febrero_2019":0,
  "Marzo_2019":0,
  "Abril_2019":0,
  "Mayo_2019":0,
  "Junio_2019":0,
  "Julio_2019":0,
  "Agosto_2019":0,
  "Septiembre_2019":0,
  "Octubre_2019":0,
  "Noviembre_2019":0,
  "Diciembre_2019":0,
  "Enero_2020":0,
  "Febrero_2020":0,
  "Marzo_2020":0,
  "Abril_2020":0,
  "Mayo_2020":0,
  "Junio_2020":0,
  "Julio_2020":0,
  "Agosto_2020":0,
  "Septiembre_2020":0,
  "Octubre_2020":0,
  "Noviembre_2020":0,
  "Diciembre_2020":0,
  "Enero_2021":0,
  "Febrero_2021":0,
  "Marzo_2021":0,
  "Abril_2021":0,
  "Mayo_2021":0,
  "Junio_2021":0,
  "Julio_2021":0,
  "Agosto_2021":0,
  "Septiembre_2021":0,
  "Octubre_2021":0,
  "Noviembre_2021":0,
  "Diciembre_2021":0,
  "Enero_2022":0,
  "Febrero_2022":0,
  "Marzo_2022":0,
  "Abril_2022":0,
  "Mayo_2022":0,
  "Junio_2022":0,
  "Julio_2022":0,
  "Agosto_2022":0,
  "Septiembre_2022":0,
  "Octubre_2022":0,
  "Noviembre_2022":0,
  "Diciembre_2022":0,
  "Enero_2023":0,
  "Febrero_2023":0,
  "Marzo_2023":0,
  "Abril_2023":0,
  "Mayo_2023":0,
  "Junio_2023":14,
  "Julio_2023":0,
  "Agosto_2023":0,
  "Septiembre_2023":0,
  "Octubre_2023":0,
  "Noviembre_2023":0,
  "Diciembre_2023":0,
  "Enero_2024":9,
  "Febrero_2024":9,
  "Marzo_2024":9,
  "Abril_2024":9,
  "Mayo_2024":9,
  "Junio_2024":9,
  "Julio_2024":9,
  "Agosto_2024":9,
  "Septiembre_2024":9,
  "Octubre_2024":9,
  "Noviembre_2024":9,
  "Diciembre_2024":9,
  "Enero_2025":5,
  "Febrero_2025":0,
  "Marzo_2025":5,
  "Abril_2025":0,
  "Mayo_2025":0,
  "Junio_2025":0,
  "Julio_2025":0,
  "Agosto_2025":0,
  "Septiembre_2025":0,
  "Octubre_2025":0,
  "Noviembre_2025":0,
  "Diciembre_2025":0
 },
 {
  "organismo_nombre":"Municipalidad de Puente Alto",
  "base":"Planta",
  "age_label":"30 a 50",
  "Enero_2018":0,
  "Febrero_2018":0,
  "Marzo_2018":0,
  "Abril_2018":0,
  "Mayo_2018":0,
  "Junio_2018":0,
  "Julio_2018":0,
  "Agosto_2018":0,
  "Septiembre_2018":0,
  "Octubre_2018":0,
  "Noviembre_2018":0,
  "Diciembre_2018":0,
  "Enero_2019":0,
  "Febrero_2019":0,
  "Marzo_2019":0,
  "Abril_2019":0,
  "Mayo_2019":0,
  "Junio_2019":0,
  "Julio_2019":0,
  "Agosto_2019":0,
  "Septiembre_2019":0,
  "Octubre_2019":0,
  "Noviembre_2019":0,
  "Diciembre_2019":0,
  "Enero_2020":0,
  "Febrero_2020":0,
  "Marzo_2020":0,
  "Abril_2020":0,
  "Mayo_2020":0,
  "Junio_2020":0,
  "Julio_2020":0,
  "Agosto_2020":0,
  "Septiembre_2020":0,
  "Octubre_2020":0,
  "Noviembre_2020":0,
  "Diciembre_2020":0,
  "Enero_2021":0,
  "Febrero_2021":0,
  "Marzo_2021":0,
  "Abril_2021":0,
  "Mayo_2021":0,
  "Junio_2021":0,
  "Julio_2021":0,
  "Agosto_2021":0,
  "Septiembre_2021":0,
  "Octubre_2021":0,
  "Noviembre_2021":0,
  "Diciembre_2021":0,
  "Enero_2022":0,
  "Febrero_2022":0,
  "Marzo_2022":0,
  "Abril_2022":0,
  "Mayo_2022":0,
  "Junio_2022":0,
  "Julio_2022":0,
  "Agosto_2022":0,
  "Septiembre_2022":0,
  "Octubre_2022":0,
  "Noviembre_2022":0,
  "Diciembre_2022":0,
  "Enero_2023":0,
  "Febrero_2023":0,
  "Marzo_2023":0,
  "Abril_2023":0,
  "Mayo_2023":0,
  "Junio_2023":287,
  "Julio_2023":0,
  "Agosto_2023":0,
  "Septiembre_2023":0,
  "Octubre_2023":0,
  "Noviembre_2023":0,
  "Diciembre_2023":0,
  "Enero_2024":259,
  "Febrero_2024":259,
  "Marzo_2024":284,
  "Abril_2024":262,
  "Mayo_2024":258,
  "Junio_2024":260,
  "Julio_2024":257,
  "Agosto_2024":257,
  "Septiembre_2024":258,
  "Octubre_2024":255,
  "Noviembre_2024":254,
  "Diciembre_2024":255,
  "Enero_2025":229,
  "Febrero_2025":0,
  "Marzo_2025":229,
  "Abril_2025":0,
  "Mayo_2025":0,
  "Junio_2025":0,
  "Julio_2025":0,
  "Agosto_2025":0,
  "Septiembre_2025":0,
  "Octubre_2025":0,
  "Noviembre_2025":0,
  "Diciembre_2025":0
 },
 {
  "organismo_nombre":"Municipalidad de Puente Alto",
  "base":"Planta",
  "age_label":"50 a 65",
  "Enero_2018":0,
  "Febrero_2018":0,
  "Marzo_2018":0,
  "Abril_2018":0,
  "Mayo_2018":0,
  "Junio_2018":0,
  "Julio_2018":0,
  "Agosto_2018":0,
  "Septiembre_2018":0,
  "Octubre_2018":0,
  "Noviembre_2018":0,
  "Diciembre_2018":0,
  "Enero_2019":0,
  "Febrero_2019":0,
  "Marzo_2019":0,
  "Abril_2019":0,
  "Mayo_2019":0,
  "Junio_2019":0,
  "Julio_2019":0,
  "Agosto_2019":0,
  "Septiembre_2019":0,
  "Octubre_2019":0,
  "Noviembre_2019":0,
  "Diciembre_2019":0,
  "Enero_2020":0,
  "Febrero_2020":0,
  "Marzo_2020":0,
  "Abril_2020":0,
  "Mayo_2020":0,
  "Junio_2020":0,
  "Julio_2020":0,
  "Agosto_2020":0,
  "Septiembre_2020":0,
  "Octubre_2020":0,
  "Noviembre_2020":0,
  "Diciembre_2020":0,
  "Enero_2021":0,
  "Febrero_2021":0,
  "Marzo_2021":0,
  "Abril_2021":0,
  "Mayo_2021":0,
  "Junio_2021":0,
  "Julio_2021":0,
  "Agosto_2021":0,
  "Septiembre_2021":0,
  "Octubre_2021":0,
  "Noviembre_2021":0,
  "Diciembre_2021":0,
  "Enero_2022":0,
  "Febrero_2022":0,
  "Marzo_2022":0,
  "Abril_2022":0,
  "Mayo_2022":0,
  "Junio_2022":0,
  "Julio_2022":0,
  "Agosto_2022":0,
  "Septiembre_2022":0,
  "Octubre_2022":0,
  "Noviembre_2022":0,
  "Diciembre_2022":0,
  "Enero_2023":0,
  "Febrero_2023":0,
  "Marzo_2023":0,
  "Abril_2023":0,
  "Mayo_2023":0,
  "Junio_2023":227,
  "Julio_2023":0,
  "Agosto_2023":0,
  "Septiembre_2023":0,
  "Octubre_2023":0,
  "Noviembre_2023":0,
  "Diciembre_2023":0,
  "Enero_2024":243,
  "Febrero_2024":243,
  "Marzo_2024":248,
  "Abril_2024":239,
  "Mayo_2024":238,
  "Junio_2024":238,
  "Julio_2024":238,
  "Agosto_2024":238,
  "Septiembre_2024":239,
  "Octubre_2024":239,
  "Noviembre_2024":239,
  "Diciembre_2024":240,
  "Enero_2025":258,
  "Febrero_2025":0,
  "Marzo_2025":257,
  "Abril_2025":0,
  "Mayo_2025":0,
  "Junio_2025":0,
  "Julio_2025":0,
  "Agosto_2025":0,
  "Septiembre_2025":0,
  "Octubre_2025":0,
  "Noviembre_2025":0,
  "Diciembre_2025":0
 },
 {
  "organismo_nombre":"Municipalidad de Puente Alto",
  "base":"Planta",
  "age_label":"65 a 85",
  "Enero_2018":0,
  "Febrero_2018":0,
  "Marzo_2018":0,
  "Abril_2018":0,
  "Mayo_2018":0,
  "Junio_2018":0,
  "Julio_2018":0,
  "Agosto_2018":0,
  "Septiembre_2018":0,
  "Octubre_2018":0,
  "Noviembre_2018":0,
  "Diciembre_2018":0,
  "Enero_2019":0,
  "Febrero_2019":0,
  "Marzo_2019":0,
  "Abril_2019":0,
  "Mayo_2019":0,
  "Junio_2019":0,
  "Julio_2019":0,
  "Agosto_2019":0,
  "Septiembre_2019":0,
  "Octubre_2019":0,
  "Noviembre_2019":0,
  "Diciembre_2019":0,
  "Enero_2020":0,
  "Febrero_2020":0,
  "Marzo_2020":0,
  "Abril_2020":0,
  "Mayo_2020":0,
  "Junio_2020":0,
  "Julio_2020":0,
  "Agosto_2020":0,
  "Septiembre_2020":0,
  "Octubre_2020":0,
  "Noviembre_2020":0,
  "Diciembre_2020":0,
  "Enero_2021":0,
  "Febrero_2021":0,
  "Marzo_2021":0,
  "Abril_2021":0,
  "Mayo_2021":0,
  "Junio_2021":0,
  "Julio_2021":0,
  "Agosto_2021":0,
  "Septiembre_2021":0,
  "Octubre_2021":0,
  "Noviembre_2021":0,
  "Diciembre_2021":0,
  "Enero_2022":0,
  "Febrero_2022":0,
  "Marzo_2022":0,
  "Abril_2022":0,
  "Mayo_2022":0,
  "Junio_2022":0,
  "Julio_2022":0,
  "Agosto_2022":0,
  "Septiembre_2022":0,
  "Octubre_2022":0,
  "Noviembre_2022":0,
  "Diciembre_2022":0,
  "Enero_2023":0,
  "Febrero_2023":0,
  "Marzo_2023":0,
  "Abril_2023":0,
  "Mayo_2023":0,
  "Junio_2023":92,
  "Julio_2023":0,
  "Agosto_2023":0,
  "Septiembre_2023":0,
  "Octubre_2023":0,
  "Noviembre_2023":0,
  "Diciembre_2023":0,
  "Enero_2024":102,
  "Febrero_2024":102,
  "Marzo_2024":122,
  "Abril_2024":97,
  "Mayo_2024":97,
  "Junio_2024":97,
  "Julio_2024":97,
  "Agosto_2024":97,
  "Septiembre_2024":97,
  "Octubre_2024":95,
  "Noviembre_2024":94,
  "Diciembre_2024":93,
  "Enero_2025":107,
  "Febrero_2025":0,
  "Marzo_2025":107,
  "Abril_2025":0,
  "Mayo_2025":0,
  "Junio_2025":0,
  "Julio_2025":0,
  "Agosto_2025":0,
  "Septiembre_2025":0,
  "Octubre_2025":0,
  "Noviembre_2025":0,
  "Diciembre_2025":0
 }
]